Workbook

Sheet General Information
B2: Scenario code: | C2: TRANSFORM
B3: Bron profielen: | C3: Flexnet
B4: Timeslice indicator: | C4: AVDiff-TimeAwareDayEveningNightSeasonXtrReserved
B5: # Timeslices step 1: | C5: 85
B6: Year: | C6: 2035
B7: # Options: | C7: 884
B8: Hour Resolution: | C8: Not applicable
B9: Model: | C9: Opera
B10: Version: | C10: 2023.1
B11: Time stamp: | C11: 27-03-2025 09:57
B12: Type of run: | C12: Static model
B14: Solver: | C14: GUROBI 9.1
B15: CrossOverStep1: | C15: Off
B16: NumericFocusStep1: | C16: 1
B17: Hom. Algorithm Step1: | C17: On
B18: Mode step 2: | C18: Not applicable
B19: # Timeslices Step 2: | C19: Not applicable
B20: CrossOverStep2: | C20: Not applicable
B21: NumericFocusStep2: | C21: Not applicable
B22: Hom. Algorithm Step2: | C22: Not applicable

Sheet Summary
A2: Main indicators | F2: Net consumption [PJ] / Primary energy [PJ] | Q2: Primary energy [PJ]
A4: Indicator | B4: Unit | C4: Value | H4: KIP built environment | I4: KIP energy | J4: KIP agriculture | K4: KIP transport | L4: KIP industry | M4: KIP bunkers | N4: LULUCF | O4: Total net consumption | R4: Bunkers | S4: Feedstock | T4: Total | U4: Total, excl. BFFS | V4: EED | Y4: pFinalEnergyDataTot_Eagg
A5: Total GHG emissions | B5: [Mton CO2eq] | C5: 88.358666 | F5: Netto levering(+ verbruik, - productie) | G5: Warmte | H5: 31.778022 | I5: -9.9366663 | J5: 0.033330082 | K5: -8.5451571e-08 | L5: -21.874756 | M5: 0 | N5: 0 | O5: =SUM(H5:N5) -> -7.0228983e-05 | Q5: Warmte | R5: 9.5122877e-06 | S5: 6.202301e-06 | T5: -7.0228983e-05 | U5: -8.5943572e-05 | V5: -7.0228983e-05
A6: Shadow price CO2 | B6: [€/ton] | C6: 0 | G6: Waterstof | H6: 0.0038427522 | I6: 0.00010893526 | J6: 0 | K6: 0.021746282 | L6: -0.02570361 | M6: 0 | N6: 0 | O6: =SUM(H6:N6) -> -5.6409034e-06 | Q6: Waterstof | R6: 2.3912096e-05 | S6: 7.7994142e-05 | T6: -5.6409034e-06 | U6: -0.00010754714 | V6: -0.53161224
A7: Total system cost | B7: [M€/yr] | C7: 86376.288 | G7: Elektriciteit | H7: 152.33089 | I7: -389.34124 | J7: 43.446171 | K7: 60.127335 | L7: 162.8293 | M7: 0 | N7: 0 | O7: =SUM(H7:N7) -> 29.392449 | Q7: Elektriciteit | R7: 0.42270492 | S7: 0.30736603 | T7: 54.034763 | U7: 53.304692 | V7: 29.392452
A8: Penetration Wind | B8: [GWe] | C8: 21.190971 | G8: Afval (niet-biogeen) | H8: 0 | I8: 0 | J8: 0 | K8: 0 | L8: 25.698003 | M8: 0 | N8: 0 | O8: =SUM(H8:N8) -> 25.698003 | Q8: Afval (niet-biogeen) | R8: 0.15499698 | S8: 0.11272844 | T8: 25.698003 | U8: 25.430277 | V8: 25.698003
A9: Penetration Wind | B9: [TWh/yr] | C9: 88.500002 | G9: Aardgas | H9: 290.51992 | I9: 115.81359 | J9: 5.0027179 | K9: 2.4315968 | L9: 251.85237 | M9: 123.29986 | N9: 0 | O9: =SUM(H9:N9) -> 788.92006 | Q9: Aardgas | R9: 140.7312 | S9: 66.203551 | T9: 788.92006 | U9: 581.9853 | V9: 609.13889
A10: Penetration Solar PV | B10: [GWe] | C10: 33.967177 | G10: Aardwarmte | H10: 0 | I10: 0.79997676 | J10: 24.189351 | K10: 0 | L10: 1.0106738 | M10: 0 | N10: 0 | O10: =SUM(H10:N10) -> 26.000002 | Q10: Aardwarmte | R10: 0.0010051083 | S10: 0.00030814107 | T10: 26.000002 | U10: 25.998688 | V10: 26.000002
A11: Penetration Solar PV | B11: [TWh/yr] | C11: 30.089556 | G11: Ammonia | H11: 0 | I11: 0 | J11: 0 | K11: 0 | L11: 0.10005027 | M11: 0 | N11: 0 | O11: =SUM(H11:N11) -> 0.10005027 | Q11: Ammonia | R11: 1.4245609e-06 | S11: 0.10004351 | T11: 0.10005027 | U11: 5.3324326e-06 | V11: 7.6450637e-06
A12: Curtailment Wind | B12: [TWh/yr] | C12: 11.57541 | G12: Biobrandstoffen | H12: 0 | I12: 0 | J12: 0 | K12: 9.4372872 | L12: -21.9089 | M12: 21.996599 | N12: 0 | O12: =SUM(H12:N12) -> 9.5249865 | Q12: Biobrandstoffen | R12: 0.2819509 | S12: 0.34738756 | T12: 9.5249865 | U12: 8.895648 | V12: -10.99782
A13: Curtailment Wind | B13: [%] | C13: 11.566688 | G13: Biogas | H13: 0.00034101887 | I13: 0 | J13: 15 | K13: 0 | L13: 23.699749 | M13: 0 | N13: 0 | O13: =SUM(H13:N13) -> 38.70009 | Q13: Biogas | R13: 0.40057927 | S13: 1.4961857 | T13: 38.70009 | U13: 36.803325 | V13: 38.70009
A14: Curtailment Solar PV | B14: [TWh/yr] | C14: 0 | G14: Biomassa | H14: 11.307015 | I14: 0.00011959194 | J14: 0 | K14: 0 | L14: 106.03651 | M14: 0 | N14: 0 | O14: =SUM(H14:N14) -> 117.34364 | Q14: Biomassa | R14: 22.277323 | S14: 5.2047491 | T14: 117.34364 | U14: 89.861571 | V14: 117.34364
A15: Curtailment Solar PV | B15: [%] | C15: 0 | G15: Kolen | H15: 0 | I15: 0 | J15: 0 | K15: 0 | L15: 45.368588 | M15: 0 | N15: 0 | O15: =SUM(H15:N15) -> 45.368588 | Q15: Kolen | R15: 0.21696605 | S15: 0.14244535 | T15: 45.368588 | U15: 45.009177 | V15: 45.368588
A16: Electrolysis | B16: [GWe] | C16: 1.4465324e-05 | G16: Olie | H16: 0.87095578 | I16: 0 | J16: 5.4424899e-05 | K16: 313.7363 | L16: 643.78452 | M16: 408.18616 | N16: 0 | O16: =SUM(H16:N16) -> 1366.578 | Q16: Olie | R16: 385.36437 | S16: 415.52692 | T16: 1366.578 | U16: 565.6867 | V16: 667.24302
A17: Electrolysis | B17: [TWhe/yr] (input) | C17: 3.7858345e-05 | G17: Omgevingswarmte | H17: 48.858891 | I17: 0.40105508 | J17: 1.839996 | K17: 0 | L17: 9.5000069 | M17: 0 | N17: 0 | O17: =SUM(H17:N17) -> 60.599949 | Q17: Omgevingswarmte | R17: 4.867919e-07 | S17: 1.4922265e-07 | T17: 60.599949 | U17: 60.599949 | V17: 0
... A23: Electricity export | B23: [TWh/yr] | C23: 6.8450874 | G23: Zon thermisch | H23: 0.18901593 | I23: 7.2875689e-05 | J23: 0 | K23: 0 | L23: 2.0150209e-05 | M23: 0 | N23: 0 | O23: =SUM(H23:N23) -> 0.18910896 | Q23: Zon thermisch | R23: 1.5190889e-09 | S23: 4.6566606e-10 | T23: 0.18910896 | U23: 0.18910896 | V23: 0.18910896
A24: Hydrogen import | B24: [TWh/yr] | C24: 0 | G24: Totaal | H24: 603.39975 | I24: 103.53895 | J24: 96.43139 | K24: 386.03613 | L24: 1230.4654 | M24: 553.88004 | N24: 0 | O24: =SUM(O5:O23) -> 2973.7517
A25: Hydrogen export | B25: [TWh/yr] | C25: 0
A26: CCS | B26: [Mton CO2] | C26: 10.500004
A27: CCU | B27: [Mton CO2] | C27: 0.12988494
A28: Dispatchable power capacity | B28: [GWe] | C28: 20.840173

Sheet GHG emissions
A3: GHG emissions [Mton CO2-eq] per sector (Excluding emissions from aviation and international shipping!)
B5: TRANSFORM
B6: KIP built environment | C6: KIP energy | D6: KIP agriculture | E6: KIP transport | F6: KIP industry | G6: LULUCF
A7: Total GHG emissions | B7: 17.178973 | C7: 6.5550496 | D7: 8.8637532 | E7: 23.339739 | F7: 29.337152 | G7: 3.0839998 | I7: =SUM(B7:G7) -> 88.358666 | J7: Sum of all Green House Gasses (excl. Aviation and international shipping)
A8: GHG emissions - energy carrier related | B8: 16.507009 | C8: 6.5550496 | D8: 0.28315746 | E8: 22.969287 | F8: 35.854684 | G8: 0 | I8: =SUM(B8:G8) -> 82.169187 | J8: Sum all GHG emissions related to consumption of energy carriers. Sum of line 8 and 9 add up to 7.
A9: GHG emissions - Non energy and Process related | B9: 0 | C9: 0 | D9: 0 | E9: 0 | F9: 0 | G9: 0 | I9: =SUM(B9:G9) -> 0 | J9: Sum all process GHG and negative emissions because of storage in chemicals, plastics, etc.. Sum of line 8 and 9 add up to 7.
A10: Total emissions - CO2 | B10: 16.806835 | C10: 6.5550496 | D10: 0.46117296 | E10: 22.969287 | F10: 27.156585 | G10: 3.0839998 | I10: =SUM(B10:G10) -> 77.032929 | J10: CO2 part of GHG emissions. Sum of line 10 and 11 adds up to line 7.
A11: Total emissions - Other GHG | B11: 0.37213799 | C11: 0 | D11: 8.4025802 | E11: 0.37045203 | F11: 2.1805669 | G11: 0 | I11: =SUM(B11:G11) -> 11.325737 | J11: Other GHG emissions part of GHG emissions. Sum of line 10 and 11 adds up to line 7.
A12: CCS [Mton] | B12: 0 | C12: 0 | D12: 0 | E12: 0 | F12: 10.500004 | G12: 0 | I12: =SUM(B12:G12) -> 10.500004 | J12: Total amount of CO2 captured using CCS
A15: Corrected, so all CO2 storage is allocated to the sectors, based on the storage/capture ratio
B17: KIP agriculture | C17: KIP built environment | D17: KIP bunkers | E17: KIP energy | F17: KIP industry | G17: KIP transport
A18: Total GHG emissions | B18: =B19+B20 -> 0.83331096 | C18: =C19+C20 -> 16.806835 | D18: =D19+D20 -> 8.4025802 | E18: =E19+E20 -> 6.9254669 | F18: =F19+F20 -> 29.337187 | G18: =G19+G20 -> 22.969287 | I18: =SUM(B18:G18) -> 85.274666
A19: Total emissions - CO2 | B19: ='CO2 emissions per sector'!K33 -> 0.46117297 | C19: ='CO2 emissions per sector'!L33 -> 16.806835 | D19: ='CO2 emissions per sector'!M33 -> 0 | E19: ='CO2 emissions per sector'!N33 -> 6.5550149 | F19: ='CO2 emissions per sector'!O33 -> 27.15662 | G19: ='CO2 emissions per sector'!P33 -> 22.969287 | I19: =SUM(B19:G19) -> 73.948929
A20: Total emissions - Other GHG | B20: =B11 -> 0.37213799 | C20: =C11 -> 0 | D20: =D11 -> 8.4025802 | E20: =E11 -> 0.37045203 | F20: =F11 -> 2.1805669 | G20: =G11 -> 0 | I20: =SUM(B20:G20) -> 11.325737
A21: CCS [Mton] | B21: ='CO2 emissions per sector'!K34 -> 0 | C21: ='CO2 emissions per sector'!L34 -> 0 | D21: ='CO2 emissions per sector'!M34 -> 0 | E21: ='CO2 emissions per sector'!N34 -> 3.4653138e-05 | F21: ='CO2 emissions per sector'!O34 -> 10.499966 | G21: ='CO2 emissions per sector'!P34 -> 0 | I21: =SUM(B21:G21) -> 10.500001
A24: GHG emissions per type[Mton CO2-eq] (Including emissions from aviation and international shipping)
B26: GHG emissions per type [Mton CO2-eq]
B28: 149.24001
A29: CO2 | B29: 77.032929
A30: CH4 | B30: 6.7038762
A31: N2O | B31: 3.9184315
A32: F-gassen | B32: 0.68684857
A33: CO2, shipping | B33: 32.547891
A34: CO2, aviation | B34: 9.9971522
A35: CO2, LULUCF | B35: 0
A36: Total [Mton CO2-eq] | B36: =SUM(B29:B35) -> 130.88713

Sheet Service Demand
A2: Service demands (activities) | B2: Activity specific units (ie Mton staal), but in case PJ, it might mean simply one unit of activity, for example 1.0 ''PJ" for AVI means all (=1,0 in this case) municipal solid waste is combusted.
A4: Service demand | B4: Option | C4: v | D4: zj | E4: Activity Baseline | F4: Activitity Run | G4: Unit Activity | H4: Capacity Baseline | I4: Capacity Run | J4: Unit Capacity
A5: Energy in education | B5: 2190 Energy in education - GFE label | C5: 1 | D5: 2035 | E5: 0.8406 | F5: 0.0005 | G5: km2 GFA | H5: 0.063 | I5: 0.0005 | J5: km2 GFA
A6: Energy in education | B6: 2191 Energy in education - DC label | C6: 1 | D6: 2035 | F6: 14.2298 | G6: km2 GFA | I6: 14.2297 | J6: km2 GFA
A7: Energy in education | B7: 2192 Energy in education - B label | C7: 1 | D7: 2035 | F7: 5.7003 | G7: km2 GFA | I7: 5.7003 | J7: km2 GFA
A8: Energy in education | B8: 2193 Energy in education - A label | C8: 1 | D8: 2035 | F8: 1.5737 | G8: km2 GFA | I8: 1.5737 | J8: km2 GFA
A9: Energy in education | B9: 2194 Energy in education - A+ label | C9: 1 | D9: 2035 | F9: 9.9946 | G9: km2 GFA | I9: 9.9946 | J9: km2 GFA
A10: Energy in hospitals | B10: 2201 Energy in hospitals - DC label | C10: 1 | D10: 2035 | F10: 11.0272 | G10: km2 GFA | I10: 11.0272 | J10: km2 GFA
A11: Energy in hospitals | B11: 2202 Energy in hospitals - B label | C11: 1 | D11: 2035 | F11: 3.8952 | G11: km2 GFA | I11: 3.8952 | J11: km2 GFA
A12: Energy in hospitals | B12: 2203 Energy in hospitals - A label | C12: 1 | D12: 2035 | F12: 1.3325 | G12: km2 GFA | I12: 1.3325 | J12: km2 GFA
A13: Energy in hospitals | B13: 2204 Energy in hospitals - A+ label | C13: 1 | D13: 2035 | F13: 7.126 | G13: km2 GFA | I13: 7.126 | J13: km2 GFA
A14: Energy in industrial halls | B14: 2196 Energy in industrial halls - DC label | C14: 1 | D14: 2035 | F14: 128.1773 | G14: km2 GFA | I14: 128.1773 | J14: km2 GFA
A15: Energy in industrial halls | B15: 2197 Energy in industrial halls - B label | C15: 1 | D15: 2035 | F15: 27.2023 | G15: km2 GFA | I15: 27.2023 | J15: km2 GFA
A16: Energy in industrial halls | B16: 2198 Energy in industrial halls - A label | C16: 1 | D16: 2035 | F16: 0.0009 | G16: km2 GFA | I16: 0.0008 | J16: km2 GFA
A17: Energy in industrial halls | B17: 2199 Energy in industrial halls - A+ label | C17: 1 | D17: 2035 | F17: 28.8066 | G17: km2 GFA | I17: 28.8066 | J17: km2 GFA
... A28: Energy in apartments with startlabel DC and B | B28: 2178 Apartments - startlabel DC | C28: 1 | D28: 2035 | F28: 0.3249 | G28: M apartments | I28: 0.3252 | J28: M apartments
A29: Energy in apartments with startlabel DC and B | B29: 2179 Apartments - startlabel DC/B retrofitted to A | C29: 1 | D29: 2035 | G29: M apartments | I29: 0 | J29: M apartments
A30: Energy in apartments with startlabel GFE | B30: 2400 Apartments - startlabel GFE retrofitted to DC | C30: 1 | D30: 2035 | F30: 0.6792 | G30: M apartments | I30: 0.6792 | J30: M apartments
A31: Energy in apartments with startlabel GFE | B31: 2401 Apartments - startlabel GFE retrofitted to B | C31: 1 | D31: 2035 | F31: 0 | G31: M apartments | I31: 0 | J31: M apartments
A32: Energy in other dwellings with startlabel A | B32: 2183 Other dwelllings - startlabel A | C32: 1 | D32: 2035 | F32: 0.4534 | G32: M other dwellings | I32: 0.4534 | J32: M other dwellings
A33: Energy in other dwellings with startlabel A | B33: 2396 Other dwelllings - startlabel A retrofitted to A+ | C33: 1 | D33: 2035 | F33: 0 | G33: M other dwellings | I33: 0 | J33: M other dwellings
A34: Energy in other dwellings with startlabel A+ | B34: 2184 Other dwelllings - startlabel A+ | C34: 1 | D34: 2035 | F34: 0.5261 | G34: M other dwellings | I34: 0.5261 | J34: M other dwellings
A35: Energy in other dwellings with startlabel DC and B | B35: 2173 Other dwelllings - startlabel B or DC retrofitted to B | C35: 1 | D35: 2035 | F35: 1.0843 | G35: M other dwellings | I35: 1.084 | J35: M other dwellings
A36: Energy in other dwellings with startlabel DC and B | B36: 2182 Other dwelllings - startlabel DC | C36: 1 | D36: 2035 | F36: 0.2846 | G36: M other dwellings | I36: 0.2849 | J36: M other dwellings
A37: Energy in other dwellings with startlabel DC and B | B37: 2398 Other dwelllings - startlabel DC/B retrofitted to A | C37: 1 | D37: 2035 | F37: 0 | G37: M other dwellings | I37: 0 | J37: M other dwellings
A38: Energy in other dwellings with startlabel GFE | B38: 2402 Other dwelllings - startlabel GFE retrofitted to DC | C38: 1 | D38: 2035 | F38: 0.6056 | G38: M other dwellings | I38: 0.6056 | J38: M other dwellings
A39: Energy in other dwellings with startlabel GFE | B39: 2403 Other dwelllings - startlabel GFE retrofitted to B | C39: 1 | D39: 2035 | G39: M other dwellings | I39: 0 | J39: M other dwellings
A40: Energy in terraced houses with startlabel A | B40: 2176 Terraced houses - startlabel A | C40: 1 | D40: 2035 | F40: 0.3625 | G40: M terraced houses | I40: 0.3625 | J40: M terraced houses
A41: Energy in terraced houses with startlabel A | B41: 2397 Terraced houses - startlabel A retrofitted to A+ | C41: 1 | D41: 2035 | F41: 0 | G41: M terraced houses | I41: 0 | J41: M terraced houses
A42: Energy in terraced houses with startlabel A+ | B42: 2171 Terraced houses - startlabel A+ | C42: 1 | D42: 2035 | E42: 0.452 | F42: 0.452 | G42: M terraced houses | H42: 0.0339 | I42: 0.452 | J42: M terraced houses
A43: Energy in terraced houses with startlabel DC and B | B43: 2170 Terraced houses - startlabel B or DC retrofitted to B | C43: 1 | D43: 2035 | E43: 1.1347 | F43: 1.1347 | G43: M terraced houses | H43: 0.0851 | I43: 1.1344 | J43: M terraced houses
A44: Energy in terraced houses with startlabel DC and B | B44: 2175 Terraced houses - startlabel DC | C44: 1 | D44: 2035 | F44: 0.3193 | G44: M terraced houses | I44: 0.3196 | J44: M terraced houses
A45: Energy in terraced houses with startlabel DC and B | B45: 2399 Terraced houses - startlabel DC/B retrofitted to A | C45: 1 | D45: 2035 | F45: 0 | G45: M terraced houses | I45: 0 | J45: M terraced houses
A46: Energy in terraced houses with startlabel GFE | B46: 2404 Terraced houses - startlabel GFE retrofitted to DC | C46: 1 | D46: 2035 | F46: 0.2564 | G46: M terraced houses | I46: 0.2564 | J46: M terraced houses
A47: Energy in terraced houses with startlabel GFE | B47: 2405 Terraced houses - startlabel GFE retrofitted to B | C47: 1 | D47: 2035 | F47: 0 | G47: M terraced houses | I47: 0 | J47: M terraced houses
A48: LULUCF | B48: 2157 REF LULUCF CO2 | C48: 1 | D48: 2035 | E48: 10 | G48: Mton | H48: 10 | J48: Mton
A49: apartments | B49: 2172 Apartments - startlabel B or DC retrofitted to B | C49: 1 | D49: 2035 | F49: 1.2454 | G49: M apartments | I49: 1.2451 | J49: M apartments
A50: apartments | B50: 2178 Apartments - startlabel DC | C50: 1 | D50: 2035 | F50: 0.3249 | G50: M apartments | I50: 0.3252 | J50: M apartments
A51: apartments | B51: 2179 Apartments - startlabel DC/B retrofitted to A | C51: 1 | D51: 2035 | G51: M apartments | I51: 0 | J51: M apartments
A52: apartments | B52: 2180 Apartments - startlabel A/A+ | C52: 1 | D52: 2035 | F52: 0.8384 | G52: M apartments | I52: 0.8384 | J52: M apartments
A53: apartments | B53: 2400 Apartments - startlabel GFE retrofitted to DC | C53: 1 | D53: 2035 | F53: 0.6792 | G53: M apartments | I53: 0.6792 | J53: M apartments
A54: apartments | B54: 2401 Apartments - startlabel GFE retrofitted to B | C54: 1 | D54: 2035 | F54: 0 | G54: M apartments | I54: 0 | J54: M apartments
A55: Aromatics production | B55: 2507 REF overall aromatics demand | C55: 1 | D55: 2035 | E55: 3.8065 | F55: 3.8065 | G55: Mton aromatics | H55: 3.8065 | I55: 3.8068 | J55: Mton aromatics
A56: AVI | B56: 1721 REF AVI | C56: 1 | D56: 2035 | E56: 0.875 | F56: 0.0445 | G56: PJ | H56: 0.0277 | I56: 0.0073 | J56: GW
A57: AVI | B57: 1798 AVI CCS | C57: 1 | D57: 2035 | F57: 0.8305 | G57: PJ | I57: 0.0308 | J57: GW
A58: Bus transport | B58: 1650 Hybrid bus | C58: 1 | D58: 2035 | F58: 0.0001 | G58: Bn vtgkm bus | I58: 0 | J58: Mvtg
A59: Bus transport | B59: 1651 REF Fuel cell bus | C59: 1 | D59: 2035 | E59: 0.0071 | G59: Bn vtgkm bus | H59: 0.0005 | J59: Mvtg
A60: Bus transport | B60: 1652 CNG bus | C60: 1 | D60: 2035 | F60: 0.0005 | G60: Bn vtgkm bus | I60: 0 | J60: Mvtg
A61: Bus transport | B61: 1653 REF BEV bus | C61: 1 | D61: 2035 | E61: 0.274 | F61: 0.2807 | G61: Bn vtgkm bus | H61: 0.0205 | I61: 0.0041 | J61: Mvtg
A62: Bus transport | B62: 2430 REF ICE bus | C62: 1 | D62: 2035 | E62: 0.4137 | F62: 0.4136 | G62: Bn vtgkm bus | H62: 0.031 | I62: 0.006 | J62: Mvtg
A63: Data centers | B63: 2480 REF data center | C63: 1 | D63: 2035 | E63: 2.052 | F63: 2.052 | G63: km2 GFA | H63: 2.052 | I63: 2.052 | J63: km2 GFA
A64: Generic services buildings | B64: 2185 Offices - B label | C64: 1 | D64: 2035 | F64: 12.4562 | G64: km2 GFA | I64: 12.4562 | J64: km2 GFA
A65: Generic services buildings | B65: 2187 Offices - DC label | C65: 1 | D65: 2035 | F65: 17.0056 | G65: km2 GFA | I65: 17.0056 | J65: km2 GFA
A66: Generic services buildings | B66: 2188 Offices - A label | C66: 1 | D66: 2035 | F66: 9.7464 | G66: km2 GFA | I66: 9.7464 | J66: km2 GFA
A67: Generic services buildings | B67: 2189 Offices - A+ label | C67: 1 | D67: 2035 | F67: 35.5723 | G67: km2 GFA | I67: 35.5723 | J67: km2 GFA
A68: Generic services buildings | B68: 2191 Energy in education - DC label | C68: 1 | D68: 2035 | F68: 14.2298 | G68: km2 GFA | I68: 14.2297 | J68: km2 GFA
A69: Generic services buildings | B69: 2192 Energy in education - B label | C69: 1 | D69: 2035 | F69: 5.7003 | G69: km2 GFA | I69: 5.7003 | J69: km2 GFA
A70: Generic services buildings | B70: 2193 Energy in education - A label | C70: 1 | D70: 2035 | F70: 1.5737 | G70: km2 GFA | I70: 1.5737 | J70: km2 GFA
A71: Generic services buildings | B71: 2194 Energy in education - A+ label | C71: 1 | D71: 2035 | F71: 9.9946 | G71: km2 GFA | I71: 9.9946 | J71: km2 GFA
A72: Generic services buildings | B72: 2196 Energy in industrial halls - DC label | C72: 1 | D72: 2035 | F72: 128.1773 | G72: km2 GFA | I72: 128.1773 | J72: km2 GFA
A73: Generic services buildings | B73: 2197 Energy in industrial halls - B label | C73: 1 | D73: 2035 | F73: 27.2023 | G73: km2 GFA | I73: 27.2023 | J73: km2 GFA
A74: Generic services buildings | B74: 2198 Energy in industrial halls - A label | C74: 1 | D74: 2035 | F74: 0.0009 | G74: km2 GFA | I74: 0.0008 | J74: km2 GFA
A75: Generic services buildings | B75: 2199 Energy in industrial halls - A+ label | C75: 1 | D75: 2035 | F75: 28.8066 | G75: km2 GFA | I75: 28.8066 | J75: km2 GFA
... A83: Generic services buildings | B83: 2209 Energy in rest services - A+ label | C83: 1 | D83: 2035 | F83: 56.6901 | G83: km2 GFA | I83: 56.6901 | J83: km2 GFA
A84: Indirect CO2 in the agricultural sector | B84: 2504 Indirect CO2 in the agricultural sector | C84: 1 | D84: 2035 | E84: 1 | G84: Mton CO2 | J84: Mton CO2
A85: Indirect CO2 in the chemical sector | B85: 2370 Indirect CO2 emissions in the chemical industry | C85: 1 | D85: 2035 | E85: 1 | G85: Mton CO2 | J85: Mton CO2
A86: Indirect CO2 in the residential sector | B86: 2503 Indirect CO2 in the residential sector | C86: 1 | D86: 2035 | E86: 1 | G86: Mton CO2 | J86: Mton CO2
A87: Indirecte CO2 | B87: 1794 indirecte CO2 emissies | C87: 1 | D87: 2035 | E87: 1 | G87: Mton CO2 | J87: Mton CO2
A88: Inland navigation freight | B88: 2431 REF ICE inland navigation freight | C88: 1 | D88: 2035 | E88: 56.3774 | F88: 56.3773 | G88: Gtkm | H88: 6.0621 | I88: 6.0621 | J88: 1000 vessels
A89: Inland navigation freight | B89: 2432 ICE inland navigation freight - 15% fuel reduction | C89: 1 | D89: 2035 | F89: 0.0001 | G89: Gtkm | I89: 0 | J89: 1000 vessels
A90: Light Duty Vehicle Transport | B90: 1834 CNG van | C90: 1 | D90: 2035 | F90: 0 | G90: Bn vtgkm LDV | I90: 0 | J90: Mvtg
A91: Light Duty Vehicle Transport | B91: 1837 PI van | C91: 1 | D91: 2035 | F91: 0.0001 | G91: Bn vtgkm LDV | I91: 0 | J91: Mvtg
A92: Light Duty Vehicle Transport | B92: 1841 REF ICE van | C92: 1 | D92: 2035 | E92: 17.2572 | F92: 13.1874 | G92: Bn vtgkm LDV | H92: 1.2943 | I92: 0.528 | J92: Mvtg
A93: Light Duty Vehicle Transport | B93: 2428 REF BEV van | C93: 1 | D93: 2035 | E93: 4.8284 | F93: 8.8981 | G93: Bn vtgkm LDV | H93: 0.3621 | I93: 0.3554 | J93: Mvtg
A94: Lubricant use mobility | B94: 2510 REF lubricant use mobility | C94: 1 | D94: 2035 | E94: 2.7 | F94: 2.7 | G94: PJ | J94: PJ
A95: luchtvaart | B95: 1995 Luchtvaart kerosine consumptie | C95: 1 | D95: 2035 | E95: 145.38 | F95: 145.38 | G95: PJ | H95: 145.38 | I95: 145.38 | J95: PJ
A96: Maritime fuel equivalent demand | B96: 1996 Marine fuel vessel | C96: 1 | D96: 2035 | E96: 408.5 | F96: 285 | G96: PJ | H96: 408.5 | I96: 308.24 | J96: PJ
A97: Maritime fuel equivalent demand | B97: 2383 Methanol vessel | C97: 1 | D97: 2035 | F97: 0.199 | G97: PJ | I97: 0.1991 | J97: PJ
A98: Maritime fuel equivalent demand | B98: 2385 LNG vessel | C98: 1 | D98: 2035 | F98: 123.301 | G98: PJ | I98: 123.301 | J98: PJ
A99: Mton ceramics production | B99: 2367 REF Ceramics production in conventional kilns | C99: 1 | D99: 2035 | E99: 2.6234 | F99: 2.6234 | G99: Mton ceramics | H99: 2.6234 | I99: 2.6234 | J99: Mton ceramics
A100: Mton Chlorine production | B100: 2243 REF Membrane Electrolysis_chlorine | C100: 1 | D100: 2035 | E100: 0.9882 | F100: 0.9882 | G100: Mton Chlorine | H100: 0.9882 | I100: 1.7227 | J100: Mton Chlorine
A101: Mton glass production | B101: 2364 REF Glass production conventional furnaces | C101: 1 | D101: 2035 | E101: 0.8632 | F101: 0.8632 | G101: Mton glass | H101: 0.8632 | I101: 0.8632 | J101: Mton glass
A102: Mton glass production | B102: 2365 Glass production with electric cold-top furnaces | C102: 1 | D102: 2035 | F102: 0 | G102: Mton glass | I102: 0 | J102: Mton glass
A103: Mton methanol production | B103: 2358 REF methanol conventional applications | C103: 1 | D103: 2035 | E103: 0.44 | F103: 0.44 | G103: Mton methanol | H103: 0.44 | I103: 0.4913 | J103: Mton methanol
A104: Mton NH3 productie | B104: 1375 REF ammoniak productie | C104: 1 | D104: 2035 | E104: 2.1455 | F104: 2.1402 | G104: Mton NH3 productie | H104: 2.1455 | I104: 2.3901 | J104: Mton NH3
A105: Mton NH3 productie | B105: 2166 Electrolyse H-B NH3 | C105: 1 | D105: 2035 | G105: Mton NH3 productie | I105: 0 | J105: Mton NH3
A106: Mton NH3 productie | B106: 2461 External NH3 for fertilizer industry | C106: 1 | D106: 2035 | F106: 0.0053 | G106: Mton NH3 | I106: 2.1434 | J106: Mton NH3
A107: Mton OBKG CH4 energie | B107: 1734 REF OBG CH4 emissies Energie | C107: 1 | D107: 2035 | E107: 5 | G107: Mton OBKG CH4 | J107: Mton OBKG CH4 ETS
A108: Mton OBKG CH4 gebouwde omgeving | B108: 2369 REF OGHG CH4 emissions households | C108: 1 | D108: 2035 | E108: 5 | G108: Mton OBKG CH4 | J108: Mton OBKG CH4 nETS
A109: Mton OBKG CH4 industrie | B109: 1735 REF O-GHG CH4 emissions waste | C109: 1 | D109: 2035 | E109: 5 | G109: Mton OBKG CH4 | J109: Mton OBKG CH4 ETS
A110: Mton OBKG CH4 landbouw | B110: 1739 REF OBG CH4 emissies landbouw | C110: 1 | D110: 2035 | E110: 15 | G110: Mton OBKG CH4 | J110: Mton OBKG CH4 nETS
A111: Mton OBKG CH4 mobiliteit | B111: 1737 REF OBG CH4 emissies verkeer | C111: 1 | D111: 2035 | E111: 5 | G111: Mton OBKG CH4 | J111: Mton OBKG CH4 ETS
A112: Mton OBKG F gss industrie | B112: 1728 REF OBG F-gas emissies Industrie | C112: 1 | D112: 2035 | E112: 5 | G112: Mton OBKG F gassen | J112: Mton OBKG F gss ETS
A113: Mton OBKG F gss mobiliteit | B113: 1727 REF OBG F-gas emissions mobility | C113: 1 | D113: 2035 | E113: 5 | G113: Mton OBKG F gassen | J113: Mton OBKG F gss nETS
A114: Mton OBKG N2O energie | B114: 1729 REF OBG N2O emissies Energie | C114: 1 | D114: 2035 | E114: 5 | G114: Mton OBKG N2O | J114: Mton OBKG N2O ETS
A115: Mton OBKG N2O industrie | B115: 1730 REF O-GHG N2O emissions chemical | C115: 1 | D115: 2035 | E115: 5 | G115: Mton OBKG N2O | J115: Mton OBKG N2O ETS
A116: Mton OBKG N2O landbouw | B116: 1733 REF OBG N2O emissies landbouw | C116: 1 | D116: 2035 | E116: 10 | G116: Mton OBKG N2O | J116: Mton OBKG N2O nETS
A117: Mton OBKG N2O mobiliteit | B117: 1731 REF OBG N2O emissies verkeer | C117: 1 | D117: 2035 | E117: 5 | G117: Mton OBKG N2O | J117: Mton OBKG N2O ETS
A118: Mton salt production | B118: 2237 REF process_salt | C118: 1 | D118: 2035 | E118: 7.0954 | F118: 7.0954 | G118: Mton salt | H118: 7.0954 | I118: 7.7695 | J118: Mton salt
A119: Mton staal | B119: 1763 REF BOF steel making 2017 | C119: 1 | D119: 2035 | E119: 6.21 | F119: 2.71 | G119: Mton staal | H119: 6.21 | I119: 3.6617 | J119: Mton staal
...

Sheet Energy balance options
A2: Energy balance of all options and all energy carriers. Unit: PJ, but Mton CO2 for CO2flow. '+' is input, '-' is output.
P3: NG use [PJ] | S3: Correction chemie | V3: Corrected NG use [PJ]
B4: Identifier | C4: Sector | D4: Energy Input(+)/Ouput(-) [PJ]
A5: Option | B5: Energy carrier | F5: Production | G5: Consumption | O5: Sector
A6: 913 Mono manure AD Green gas | B6: Aardgas | C6: Landbouw | D6: -14.999909 | F6: =IF(D6<0,D6,"") -> -14.999909 | G6: =IF(D6>0,D6,"") | O6: Landbouw | P6: =SUMIFS($D$7:$D$4000,$C$7:$C$4000,$O6,$B$7:$B$4000,"aardgas") -> 20.002627 | S6: 1394 REF NonEn Chemie ebalans | T6: =SUMIFS($D$7:$D$4000,$A$7:$A$4000,$S6,$B$7:$B$4000,"Aardgas") -> 0 | V6: =P6 -> 20.002627
A7: 913 Mono manure AD Green gas | B7: Biogas | C7: Landbouw | F7: =IF(D7<0,D7,"") | G7: =IF(D7>0,D7,"") | O7: Overige landbouw | P7: =SUMIFS($D$7:$D$4000,$C$7:$C$4000,$O7,$B$7:$B$4000,"aardgas") -> 0 | S7: 1780 REF non energetisch en ovg omz chemie | T7: =SUMIFS($D$7:$D$4000,$A$7:$A$4000,$S7,$B$7:$B$4000,"Aardgas") -> 5.569212 | V7: =P7 -> 0
A8: 913 Mono manure AD Green gas | B8: E-inhoud mest | C8: Landbouw | D8: 14.999909 | F8: =IF(D8<0,D8,"") | G8: =IF(D8>0,D8,"") -> 14.999909 | O8: Huishoudens | P8: =SUMIFS($D$7:$D$4000,$C$7:$C$4000,$O8,$B$7:$B$4000,"aardgas") -> 224.8005 | S8: 2161 Non energetisch en ovg omz chemie - bio | T8: =SUMIFS($D$7:$D$4000,$A$7:$A$4000,$S8,$B$7:$B$4000,"Aardgas") -> 0 | V8: =P8 -> 224.8005
A9: 985 Lignocellulosic ethanol production | B9: Bio-ethanol | C9: Raffinaderijen | D9: -3.3420919e-06 | F9: =IF(D9<0,D9,"") -> -3.3420919e-06 | G9: =IF(D9>0,D9,"") | O9: HDO | P9: =SUMIFS($D$7:$D$4000,$C$7:$C$4000,$O9,$B$7:$B$4000,"aardgas") -> 65.719411 | S9: 2356 REF methanol from NG | T9: =SUMIFS($D$7:$D$4000,$A$7:$A$4000,$S9,$B$7:$B$4000,"Aardgas") -> 12.749463 | V9: =P9 -> 65.719411
A10: 985 Lignocellulosic ethanol production | B10: Biomassa (hout) | C10: Raffinaderijen | D10: 9.099403e-06 | F10: =IF(D10<0,D10,"") | G10: =IF(D10>0,D10,"") -> 9.099403e-06 | O10: Bunkers | P10: =SUMIFS($D$7:$D$4000,$C$7:$C$4000,$O10,$B$7:$B$4000,"aardgas") -> 0 | S10: 2379 Non energetisch en ovg omz chemie - external heat | T10: =SUMIFS($D$7:$D$4000,$A$7:$A$4000,$S10,$B$7:$B$4000,"Aardgas") -> 0 | V10: =P10 -> 0
A11: 985 Lignocellulosic ethanol production | B11: Elektriciteit | C11: Raffinaderijen | D11: -3.9679289e-07 | F11: =IF(D11<0,D11,"") -> -3.9679289e-07 | G11: =IF(D11>0,D11,"") | O11: Elektriciteitsopwekking | P11: =SUMIFS($D$7:$D$4000,$C$7:$C$4000,$O11,$B$7:$B$4000,"aardgas") -> 96.549437 | V11: =P11 -> 96.549437
A12: 986 Ethanol uit biomassa (starch) 2011 | B12: Bio-ethanol | C12: Raffinaderijen | F12: =IF(D12<0,D12,"") | G12: =IF(D12>0,D12,"") | O12: Warmteopwekking (centraal) | P12: =SUMIFS($D$7:$D$4000,$C$7:$C$4000,$O12,$B$7:$B$4000,"aardgas") -> 19.264158 | V12: =P12 -> 19.264158
A13: 986 Ethanol uit biomassa (starch) 2011 | B13: Biomassa (zetmeel) | C13: Raffinaderijen | F13: =IF(D13<0,D13,"") | G13: =IF(D13>0,D13,"") | O13: Basic metal non-ferro | P13: =SUMIFS($D$7:$D$4000,$C$7:$C$4000,$O13,$B$7:$B$4000,"aardgas") -> 0.62987196 | V13: =P13 -> 0.62987196
A14: 987 Ethanol uit biomassa (suiker) 2011 | B14: Bio-ethanol | C14: Raffinaderijen | D14: -3.9487323e-06 | F14: =IF(D14<0,D14,"") -> -3.9487323e-06 | G14: =IF(D14>0,D14,"") | O14: Basismetaal ferro | P14: =SUMIFS($D$7:$D$4000,$C$7:$C$4000,$O14,$B$7:$B$4000,"aardgas") -> 32.192778 | V14: =P14 -> 32.192778
A15: 987 Ethanol uit biomassa (suiker) 2011 | B15: Biomassa (suikers) | C15: Raffinaderijen | D15: 8.833853e-06 | F15: =IF(D15<0,D15,"") | G15: =IF(D15>0,D15,"") -> 8.833853e-06 | O15: Chemie | P15: =SUMIFS($D$7:$D$4000,$C$7:$C$4000,$O15,$B$7:$B$4000,"aardgas") -> 26.77583 | V15: =P15-SUM(T6:T10) -> 8.4571551
A16: 993 H2 uit olievergassing met CCS 2011 | B16: CO2Flow | C16: H2 voorziening | F16: =IF(D16<0,D16,"") | G16: =IF(D16>0,D16,"") | O16: Food and Beverage Industry | P16: =SUMIFS($D$7:$D$4000,$C$7:$C$4000,$O16,$B$7:$B$4000,"aardgas") -> 7.1722837 | V16: =P16 -> 7.1722837
A17: 993 H2 uit olievergassing met CCS 2011 | B17: Elektriciteit | C17: H2 voorziening | F17: =IF(D17<0,D17,"") | G17: =IF(D17>0,D17,"") | O17: Gasvoorziening | P17: =SUMIFS($D$7:$D$4000,$C$7:$C$4000,$O17,$B$7:$B$4000,"aardgas") -> 5.6393808e-05 | V17: =P17 -> 5.6393808e-05
A18: 993 H2 uit olievergassing met CCS 2011 | B18: Olie | C18: H2 voorziening | F18: =IF(D18<0,D18,"") | G18: =IF(D18>0,D18,"") | O18: H2 voorziening | P18: =SUMIFS($D$7:$D$4000,$C$7:$C$4000,$O18,$B$7:$B$4000,"aardgas") -> 78.453321 | V18: =P18 -> 78.453321
A19: 993 H2 uit olievergassing met CCS 2011 | B19: Waterstof | C19: H2 voorziening | F19: =IF(D19<0,D19,"") | G19: =IF(D19>0,D19,"") | O19: Industrie | P19: =SUMIFS($D$7:$D$4000,$C$7:$C$4000,$O19,$B$7:$B$4000,"aardgas") -> 35.642607 | V19: =P19 -> 35.642607
A20: 996 H2 uit biomassavergassing CCS 2011 | B20: Biomassa (hout) | C20: H2 voorziening | F20: =IF(D20<0,D20,"") | G20: =IF(D20>0,D20,"") | O20: Kunstmestindustrie | P20: =SUMIFS($D$7:$D$4000,$C$7:$C$4000,$O20,$B$7:$B$4000,"aardgas") -> 59.829772 | V20: =P20 -> 59.829772
A21: 996 H2 uit biomassavergassing CCS 2011 | B21: CO2Flow | C21: H2 voorziening | F21: =IF(D21<0,D21,"") | G21: =IF(D21>0,D21,"") | O21: Raffinaderijen | P21: =SUMIFS($D$7:$D$4000,$C$7:$C$4000,$O21,$B$7:$B$4000,"aardgas") -> 11.052244 | V21: =P21 -> 11.052244
A22: 996 H2 uit biomassavergassing CCS 2011 | B22: Elektriciteit | C22: H2 voorziening | F22: =IF(D22<0,D22,"") | G22: =IF(D22>0,D22,"") | O22: Waste | P22: =SUMIFS($D$7:$D$4000,$C$7:$C$4000,$O22,$B$7:$B$4000,"aardgas") -> 0.0036721374 | V22: =P22 -> 0.0036721374
A23: 996 H2 uit biomassavergassing CCS 2011 | B23: Waterstof | C23: H2 voorziening | F23: =IF(D23<0,D23,"") | G23: =IF(D23>0,D23,"") | O23: Verkeer | P23: =SUMIFS($D$7:$D$4000,$C$7:$C$4000,$O23,$B$7:$B$4000,"aardgas") -> 2.4315968 | V23: =P23 -> 2.4315968
A24: 998 H2 uit biomassavergassing 2011 | B24: Biomassa (hout) | C24: H2 voorziening | D24: 1.8932093e-05 | F24: =IF(D24<0,D24,"") | G24: =IF(D24>0,D24,"") -> 1.8932093e-05 | O24: MWT | P24: =SUMIFS($D$7:$D$4000,$C$7:$C$4000,$O24,$B$7:$B$4000,"aardgas") -> 0 | V24: =P24 -> 0
A25: 998 H2 uit biomassavergassing 2011 | B25: Elektriciteit | C25: H2 voorziening | D25: 1.1576299e-06 | F25: =IF(D25<0,D25,"") | G25: =IF(D25>0,D25,"") -> 1.1576299e-06
A26: 998 H2 uit biomassavergassing 2011 | B26: Waterstof | C26: H2 voorziening | D26: -1.3819046e-05 | F26: =IF(D26<0,D26,"") -> -1.3819046e-05 | G26: =IF(D26>0,D26,"")
A27: 999 H2 uit SMR met CCS 2011 | B27: Aardgas | C27: H2 voorziening | F27: =IF(D27<0,D27,"") | G27: =IF(D27>0,D27,"")
A28: 999 H2 uit SMR met CCS 2011 | B28: CO2Flow | C28: H2 voorziening | F28: =IF(D28<0,D28,"") | G28: =IF(D28>0,D28,"")
A29: 999 H2 uit SMR met CCS 2011 | B29: Waterstof | C29: H2 voorziening | F29: =IF(D29<0,D29,"") | G29: =IF(D29>0,D29,"")
A30: 1003 Micro-WKK Brandstofcel 2011 (WB nieuwbouw) | B30: Elektriciteit | C30: Huishoudens | D30: -2.0253418e-07 | F30: =IF(D30<0,D30,"") -> -2.0253418e-07 | G30: =IF(D30>0,D30,"")
A31: 1003 Micro-WKK Brandstofcel 2011 (WB nieuwbouw) | B31: Warmte | C31: Huishoudens | D31: -3.024147e-07 | F31: =IF(D31<0,D31,"") -> -3.024147e-07 | G31: =IF(D31>0,D31,"")
A32: 1003 Micro-WKK Brandstofcel 2011 (WB nieuwbouw) | B32: Waterstof | C32: Huishoudens | D32: 4.8668062e-07 | F32: =IF(D32<0,D32,"") | G32: =IF(D32>0,D32,"") -> 4.8668062e-07
A33: 1010 Micro-WKK Brandstofcel 2011 (WB bestaande bouw) | B33: Elektriciteit | C33: Huishoudens | F33: =IF(D33<0,D33,"") | G33: =IF(D33>0,D33,"")
A34: 1010 Micro-WKK Brandstofcel 2011 (WB bestaande bouw) | B34: Warmte | C34: Huishoudens | F34: =IF(D34<0,D34,"") | G34: =IF(D34>0,D34,"")
A35: 1010 Micro-WKK Brandstofcel 2011 (WB bestaande bouw) | B35: Waterstof | C35: Huishoudens | F35: =IF(D35<0,D35,"") | G35: =IF(D35>0,D35,"")
A36: 1012 Solar-PV Residential | B36: Elektriciteit | C36: Huishoudens | D36: -30.326279 | F36: =IF(D36<0,D36,"") -> -30.326279 | G36: =IF(D36>0,D36,"")
A37: 1012 Solar-PV Residential | B37: Zon | C37: Huishoudens | D37: 30.326279 | F37: =IF(D37<0,D37,"") | G37: =IF(D37>0,D37,"") -> 30.326279
A38: 1013 Biomassavergassing met CCS 7000u 2011 | B38: Biomassa (hout) | C38: Elektriciteitsopwekking | D38: 2.0531186e-05 | F38: =IF(D38<0,D38,"") | G38: =IF(D38>0,D38,"") -> 2.0531186e-05
A39: 1013 Biomassavergassing met CCS 7000u 2011 | B39: CO2Flow | C39: Elektriciteitsopwekking | D39: -2.025198e-06 | F39: =IF(D39<0,D39,"") -> -2.025198e-06 | G39: =IF(D39>0,D39,"")
A40: 1013 Biomassavergassing met CCS 7000u 2011 | B40: Elektriciteit | C40: Elektriciteitsopwekking | D40: -1.2125396e-06 | F40: =IF(D40<0,D40,"") -> -1.2125396e-06 | G40: =IF(D40>0,D40,"")
A41: 1016 ATR with CC | B41: Aardgas | C41: H2 voorziening | D41: 13.154776 | F41: =IF(D41<0,D41,"") | G41: =IF(D41>0,D41,"") -> 13.154776
A42: 1016 ATR with CC | B42: CO2Flow | C42: H2 voorziening | D42: -0.68499555 | F42: =IF(D42<0,D42,"") -> -0.68499555 | G42: =IF(D42>0,D42,"")
A43: 1016 ATR with CC | B43: Elektriciteit | C43: H2 voorziening | D43: 0.54811571 | F43: =IF(D43<0,D43,"") | G43: =IF(D43>0,D43,"") -> 0.54811571
A44: 1016 ATR with CC | B44: Waterstof | C44: H2 voorziening | D44: -10.962314 | F44: =IF(D44<0,D44,"") -> -10.962314 | G44: =IF(D44>0,D44,"")
A45: 1017 Kolenvergassing CCS 7000u eDesign 2011 | B45: CO2Flow | C45: Elektriciteitsopwekking | F45: =IF(D45<0,D45,"") | G45: =IF(D45>0,D45,"")
A46: 1017 Kolenvergassing CCS 7000u eDesign 2011 | B46: Elektriciteit | C46: Elektriciteitsopwekking | F46: =IF(D46<0,D46,"") | G46: =IF(D46>0,D46,"")
A47: 1017 Kolenvergassing CCS 7000u eDesign 2011 | B47: Kolen | C47: Elektriciteitsopwekking | F47: =IF(D47<0,D47,"") | G47: =IF(D47>0,D47,"")
A48: 1020 Solar thermal - Services | B48: Warmte | C48: HDO | D48: -0.0013633231 | F48: =IF(D48<0,D48,"") -> -0.0013633231 | G48: =IF(D48>0,D48,"")
A49: 1020 Solar thermal - Services | B49: Zon thermisch | C49: HDO | D49: 0.0013633231 | F49: =IF(D49<0,D49,"") | G49: =IF(D49>0,D49,"") -> 0.0013633231
A50: 1021 Micro WKK brandstofcel Utiliteitsbouw eDesign 2011 | B50: Elektriciteit | C50: HDO | D50: -1.6054678e-07 | F50: =IF(D50<0,D50,"") -> -1.6054678e-07 | G50: =IF(D50>0,D50,"")
A51: 1021 Micro WKK brandstofcel Utiliteitsbouw eDesign 2011 | B51: Warmte | C51: HDO | D51: -2.3418511e-07 | F51: =IF(D51<0,D51,"") -> -2.3418511e-07 | G51: =IF(D51>0,D51,"")
A52: 1021 Micro WKK brandstofcel Utiliteitsbouw eDesign 2011 | B52: Waterstof | C52: HDO | D52: 3.7003776e-07 | F52: =IF(D52<0,D52,"") | G52: =IF(D52>0,D52,"") -> 3.7003776e-07
A53: 1022 Soil heat pump - Services | B53: Elektriciteit | C53: HDO | D53: 4.1408401e-05 | F53: =IF(D53<0,D53,"") | G53: =IF(D53>0,D53,"") -> 4.1408401e-05
A54: 1022 Soil heat pump - Services | B54: Omgevingswarmte | C54: HDO | D54: 7.3425054e-05 | F54: =IF(D54<0,D54,"") | G54: =IF(D54>0,D54,"") -> 7.3425054e-05
A55: 1022 Soil heat pump - Services | B55: Warmte | C55: HDO | D55: -0.00011253718 | F55: =IF(D55<0,D55,"") -> -0.00011253718 | G55: =IF(D55>0,D55,"")
A56: 1023 Ground water heat pump - Services | B56: Aardgas | C56: HDO | D56: 0.19446466 | F56: =IF(D56<0,D56,"") | G56: =IF(D56>0,D56,"") -> 0.19446466
A57: 1023 Ground water heat pump - Services | B57: Elektriciteit | C57: HDO | D57: 3.3197678 | F57: =IF(D57<0,D57,"") | G57: =IF(D57>0,D57,"") -> 3.3197678
A58: 1023 Ground water heat pump - Services | B58: Omgevingswarmte | C58: HDO | D58: 14.929367 | F58: =IF(D58<0,D58,"") | G58: =IF(D58>0,D58,"") -> 14.929367
A59: 1023 Ground water heat pump - Services | B59: Warmte | C59: HDO | D59: -18.443155 | F59: =IF(D59<0,D59,"") -> -18.443155 | G59: =IF(D59>0,D59,"")
A60: 1024 Hybride WP ketel Utiliteitsbouw eDesign 2011 | B60: Aardgas | C60: HDO | F60: =IF(D60<0,D60,"") | G60: =IF(D60>0,D60,"")
A61: 1024 Hybride WP ketel Utiliteitsbouw eDesign 2011 | B61: Elektriciteit | C61: HDO | F61: =IF(D61<0,D61,"") | G61: =IF(D61>0,D61,"")
A62: 1024 Hybride WP ketel Utiliteitsbouw eDesign 2011 | B62: Omgevingswarmte | C62: HDO | D62: 1.8203577e-06 | F62: =IF(D62<0,D62,"") | G62: =IF(D62>0,D62,"") -> 1.8203577e-06
A63: 1024 Hybride WP ketel Utiliteitsbouw eDesign 2011 | B63: Warmte | C63: HDO | D63: -1.642413e-07 | F63: =IF(D63<0,D63,"") -> -1.642413e-07 | G63: =IF(D63>0,D63,"")
A64: 1027 REF HR-107 - Services | B64: Aardgas | C64: HDO | D64: 23.402685 | F64: =IF(D64<0,D64,"") | G64: =IF(D64>0,D64,"") -> 23.402685
A65: 1027 REF HR-107 - Services | B65: Warmte | C65: HDO | D65: -21.593238 | F65: =IF(D65<0,D65,"") -> -21.593238 | G65: =IF(D65>0,D65,"")
A66: 1029 Solar thermal - Newly built - Residential | B66: Warmte | C66: Huishoudens | D66: -0.0061403542 | F66: =IF(D66<0,D66,"") -> -0.0061403542 | G66: =IF(D66>0,D66,"")
A67: 1029 Solar thermal - Newly built - Residential | B67: Zon thermisch | C67: Huishoudens | D67: 0.0061403542 | F67: =IF(D67<0,D67,"") | G67: =IF(D67>0,D67,"") -> 0.0061403542
A68: 1035 REF HR-107 - Existing - Residential | B68: Aardgas | C68: Huishoudens | D68: 195.97316 | F68: =IF(D68<0,D68,"") | G68: =IF(D68>0,D68,"") -> 195.97316
A69: 1035 REF HR-107 - Existing - Residential | B69: Warmte | C69: Huishoudens | D69: -182.9331 | F69: =IF(D69<0,D69,"") -> -182.9331 | G69: =IF(D69>0,D69,"")
A70: 1037 REF HR-107 - Newly built - Residential | B70: Aardgas | C70: Huishoudens | D70: 28.817742 | F70: =IF(D70<0,D70,"") | G70: =IF(D70>0,D70,"") -> 28.817742
A71: 1037 REF HR-107 - Newly built - Residential | B71: Warmte | C71: Huishoudens | D71: -29.057134 | F71: =IF(D71<0,D71,"") -> -29.057134 | G71: =IF(D71>0,D71,"")
A72: 1039 Solar thermal - Existing - Residential | B72: Warmte | C72: Huishoudens | D72: -0.18151226 | F72: =IF(D72<0,D72,"") -> -0.18151226 | G72: =IF(D72>0,D72,"")
A73: 1039 Solar thermal - Existing - Residential | B73: Zon thermisch | C73: Huishoudens | D73: 0.18151226 | F73: =IF(D73<0,D73,"") | G73: =IF(D73>0,D73,"") -> 0.18151226
... A77: 1043 REF H2 uit SMR 2011 | B77: Waterstof | C77: H2 voorziening | D77: -6.1632287e-05 | F77: =IF(D77<0,D77,"") -> -6.1632287e-05 | G77: =IF(D77>0,D77,"")
A78: 1044 Ketels SHT kolen eDesign 2011 | B78: HeatHT400 | C78: Industrie | F78: =IF(D78<0,D78,"") | G78: =IF(D78>0,D78,"")
A79: 1044 Ketels SHT kolen eDesign 2011 | B79: Kolen | C79: Industrie | F79: =IF(D79<0,D79,"") | G79: =IF(D79>0,D79,"")
A80: 1045 Hydrogen Medium Temp Boilers - Industry | B80: Heat200to400 | C80: Industrie | D80: -3.1980031e-05 | F80: =IF(D80<0,D80,"") -> -3.1980031e-05 | G80: =IF(D80>0,D80,"")
A81: 1045 Hydrogen Medium Temp Boilers - Industry | B81: Waterstof | C81: Industrie | D81: 3.5493134e-05 | F81: =IF(D81<0,D81,"") | G81: =IF(D81>0,D81,"") -> 3.5493134e-05
A82: 1046 Hot water electric boiler - Industry | B82: Elektriciteit | C82: Industrie | D82: 0.0002864567 | F82: =IF(D82<0,D82,"") | G82: =IF(D82>0,D82,"") -> 0.0002864567
A83: 1046 Hot water electric boiler - Industry | B83: Warmte | C83: Industrie | D83: -0.00028362092 | F83: =IF(D83<0,D83,"") -> -0.00028362092 | G83: =IF(D83>0,D83,"")
A84: 1047 Electric Industrial Heat Pump - Industry | B84: Elektriciteit | C84: Industrie | D84: 3.0567026 | F84: =IF(D84<0,D84,"") | G84: =IF(D84>0,D84,"") -> 3.0567026
A85: 1047 Electric Industrial Heat Pump - Industry | B85: Omgevingswarmte | C85: Industrie | D85: 7.6417591 | F85: =IF(D85<0,D85,"") | G85: =IF(D85>0,D85,"") -> 7.6417591
A86: 1047 Electric Industrial Heat Pump - Industry | B86: Warmte | C86: Industrie | D86: -10.698459 | F86: =IF(D86<0,D86,"") -> -10.698459 | G86: =IF(D86>0,D86,"")
A87: 1048 Natural Gas Industrial Heat Pump - Industry | B87: Aardgas | C87: Industrie | F87: =IF(D87<0,D87,"") | G87: =IF(D87>0,D87,"")
A88: 1048 Natural Gas Industrial Heat Pump - Industry | B88: Omgevingswarmte | C88: Industrie | F88: =IF(D88<0,D88,"") | G88: =IF(D88>0,D88,"")
A89: 1048 Natural Gas Industrial Heat Pump - Industry | B89: Warmte | C89: Industrie | F89: =IF(D89<0,D89,"") | G89: =IF(D89>0,D89,"")
A90: 1049 WKK biomassa (vloeibaar) eDesign 2011 | B90: Biomassa (natte stromen) | C90: Industrie | F90: =IF(D90<0,D90,"") | G90: =IF(D90>0,D90,"")
A91: 1049 WKK biomassa (vloeibaar) eDesign 2011 | B91: Elektriciteit | C91: Industrie | F91: =IF(D91<0,D91,"") | G91: =IF(D91>0,D91,"")
A92: 1049 WKK biomassa (vloeibaar) eDesign 2011 | B92: Warmte | C92: Industrie | F92: =IF(D92<0,D92,"") | G92: =IF(D92>0,D92,"")
A93: 1050 WKK biomassa (vloeibaar) CCS eDesign 2011 | B93: Biomassa (natte stromen) | C93: Industrie | F93: =IF(D93<0,D93,"") | G93: =IF(D93>0,D93,"")
A94: 1050 WKK biomassa (vloeibaar) CCS eDesign 2011 | B94: CO2Flow | C94: Industrie | F94: =IF(D94<0,D94,"") | G94: =IF(D94>0,D94,"")
A95: 1050 WKK biomassa (vloeibaar) CCS eDesign 2011 | B95: Elektriciteit | C95: Industrie | F95: =IF(D95<0,D95,"") | G95: =IF(D95>0,D95,"")
A96: 1050 WKK biomassa (vloeibaar) CCS eDesign 2011 | B96: Warmte | C96: Industrie | F96: =IF(D96<0,D96,"") | G96: =IF(D96>0,D96,"")
A97: 1051 WKK biomassa (vast) CCS eDesign 2011 | B97: Biomassa (hout) | C97: Industrie | F97: =IF(D97<0,D97,"") | G97: =IF(D97>0,D97,"")
A98: 1051 WKK biomassa (vast) CCS eDesign 2011 | B98: CO2Flow | C98: Industrie | F98: =IF(D98<0,D98,"") | G98: =IF(D98>0,D98,"")
... A107: 1053 WKK biomassa (vast) Industrie | B107: Heat200to400 | C107: Industrie | F107: =IF(D107<0,D107,"") | G107: =IF(D107>0,D107,"")
A108: 1054 WKK gas eDesign 2011 | B108: Aardgas | C108: Industrie | D108: 1.2086321 | F108: =IF(D108<0,D108,"") | G108: =IF(D108>0,D108,"") -> 1.2086321
A109: 1054 WKK gas eDesign 2011 | B109: Elektriciteit | C109: Industrie | D109: -0.30157228 | F109: =IF(D109<0,D109,"") -> -0.30157228 | G109: =IF(D109>0,D109,"")
A110: 1054 WKK gas eDesign 2011 | B110: Heat200to400 | C110: Industrie | D110: -0.72580129 | F110: =IF(D110<0,D110,"") -> -0.72580129 | G110: =IF(D110>0,D110,"")
A111: 1055 Ketels LT biomassa CCS eDesign 2011 | B111: Biomassa (hout) | C111: Industrie | F111: =IF(D111<0,D111,"") | G111: =IF(D111>0,D111,"")
A112: 1055 Ketels LT biomassa CCS eDesign 2011 | B112: CO2Flow | C112: Industrie | F112: =IF(D112<0,D112,"") | G112: =IF(D112>0,D112,"")
...

Sheet Prod-Cons 2nd energy carriers
A2: Production and consumption of secondary energy carriers. '+' is input, '-' is output. Figures are including infrastructure losses
B4: PJ | D4: TWh
A5: Energy carrier | B5: Production | C5: Consumption | D5: Production | E5: Consumption
A6: Elektriciteit | B6: =SUMIF('Energy balance options'!$B$6:$B$3000,'Prod-Cons 2nd energy carriers'!$A6,'Energy balance options'!F$6:F$3000) -> -568.68438 | C6: =SUMIF('Energy balance options'!$B$6:$B$3000,'Prod-Cons 2nd energy carriers'!$A6,'Energy balance options'!G$6:G$3000) -> 568.6844 | D6: =B6/3.6 -> -157.96788 | E6: =C6/3.6 -> 157.96789
A7: warmte | B7: =SUMIF('Energy balance options'!$B$6:$B$3000,'Prod-Cons 2nd energy carriers'!$A7,'Energy balance options'!F$6:F$3000) -> -505.21682 | C7: =SUMIF('Energy balance options'!$B$6:$B$3000,'Prod-Cons 2nd energy carriers'!$A7,'Energy balance options'!G$6:G$3000) -> 505.21682 | D7: =B7/3.6 -> -140.33801 | E7: =C7/3.6 -> 140.338
A8: Waterstof | B8: =SUMIF('Energy balance options'!$B$6:$B$3000,'Prod-Cons 2nd energy carriers'!$A8,'Energy balance options'!F$6:F$3000) -> -72.229946 | C8: =SUMIF('Energy balance options'!$B$6:$B$3000,'Prod-Cons 2nd energy carriers'!$A8,'Energy balance options'!G$6:G$3000) -> 72.229941 | D8: =B8/3.6 -> -20.063874 | E8: =C8/3.6 -> 20.063872
A9: Aardgas | B9: =SUMIF('Energy balance options'!$B$6:$B$3000,'Prod-Cons 2nd energy carriers'!$A9,'Energy balance options'!F$6:F$3000) -> -15.141348 | C9: =SUMIF('Energy balance options'!$B$6:$B$3000,'Prod-Cons 2nd energy carriers'!$A9,'Energy balance options'!G$6:G$3000) -> 680.66161 | D9: =B9/3.6 -> -4.2059301 | E9: =C9/3.6 -> 189.07267

Sheet Refinery sector
I1: Raffinaderijen
A4: Energiedrager | B4: Production | C4: Consumption | D4: Net effect | F4: Aggregation type | H4: Aggregation net consumption [PJ]
A5: Aardgas | B5: =SUMIFS('Energy balance options'!F$6:F$3000,'Energy balance options'!$B$6:$B$3000,'Refinery sector'!$A5,'Energy balance options'!$C$6:$C$3000,'Refinery sector'!$I$1) -> 0 | C5: =SUMIFS('Energy balance options'!G$6:G$3000,'Energy balance options'!$B$6:$B$3000,'Refinery sector'!$A5,'Energy balance options'!$C$6:$C$3000,'Refinery sector'!$I$1) -> 11.052244 | D5: =B5+C5 -> 11.052244 | F5: Natural gas | H5: Natural gas | I5: =SUMIF($F$5:$F$67,H5,$D$5:$D$67) -> 11.052244
A6: Ammonia | B6: =SUMIFS('Energy balance options'!F$6:F$3000,'Energy balance options'!$B$6:$B$3000,'Refinery sector'!$A6,'Energy balance options'!$C$6:$C$3000,'Refinery sector'!$I$1) -> 0 | C6: =SUMIFS('Energy balance options'!G$6:G$3000,'Energy balance options'!$B$6:$B$3000,'Refinery sector'!$A6,'Energy balance options'!$C$6:$C$3000,'Refinery sector'!$I$1) -> 0 | D6: =B6+C6 -> 0 | F6: Ammonia | H6: Ammonia | I6: =SUMIF($F$5:$F$67,H6,$D$5:$D$67) -> 0
A7: Ammonia export | B7: =SUMIFS('Energy balance options'!F$6:F$3000,'Energy balance options'!$B$6:$B$3000,'Refinery sector'!$A7,'Energy balance options'!$C$6:$C$3000,'Refinery sector'!$I$1) -> 0 | C7: =SUMIFS('Energy balance options'!G$6:G$3000,'Energy balance options'!$B$6:$B$3000,'Refinery sector'!$A7,'Energy balance options'!$C$6:$C$3000,'Refinery sector'!$I$1) -> 0 | D7: =B7+C7 -> 0 | F7: Ammonia | H7: Electricity | I7: =SUMIF($F$5:$F$67,H7,$D$5:$D$67) -> 8.375525
A8: Ammonia import | B8: =SUMIFS('Energy balance options'!F$6:F$3000,'Energy balance options'!$B$6:$B$3000,'Refinery sector'!$A8,'Energy balance options'!$C$6:$C$3000,'Refinery sector'!$I$1) -> 0 | C8: =SUMIFS('Energy balance options'!G$6:G$3000,'Energy balance options'!$B$6:$B$3000,'Refinery sector'!$A8,'Energy balance options'!$C$6:$C$3000,'Refinery sector'!$I$1) -> 0 | D8: =B8+C8 -> 0 | F8: Ammonia | H8: Heat | I8: =SUMIF($F$5:$F$67,H8,$D$5:$D$67) -> -2.1779425
A9: Aromatics | B9: =SUMIFS('Energy balance options'!F$6:F$3000,'Energy balance options'!$B$6:$B$3000,'Refinery sector'!$A9,'Energy balance options'!$C$6:$C$3000,'Refinery sector'!$I$1) -> -85.275114 | C9: =SUMIFS('Energy balance options'!G$6:G$3000,'Energy balance options'!$B$6:$B$3000,'Refinery sector'!$A9,'Energy balance options'!$C$6:$C$3000,'Refinery sector'!$I$1) -> 0 | D9: =B9+C9 -> -85.275114 | F9: Fossil feedstock | H9: Hydrogen | I9: =SUMIF($F$5:$F$67,H9,$D$5:$D$67) -> 60.954884
A10: Benzine | B10: =SUMIFS('Energy balance options'!F$6:F$3000,'Energy balance options'!$B$6:$B$3000,'Refinery sector'!$A10,'Energy balance options'!$C$6:$C$3000,'Refinery sector'!$I$1) -> -102.03557 | C10: =SUMIFS('Energy balance options'!G$6:G$3000,'Energy balance options'!$B$6:$B$3000,'Refinery sector'!$A10,'Energy balance options'!$C$6:$C$3000,'Refinery sector'!$I$1) -> 0 | D10: =B10+C10 -> -102.03557 | F10: Fossil fuel | H10: Waste gasses | I10: =SUMIF($F$5:$F$67,H10,$D$5:$D$67) -> -54.012021
A11: Bio-aromatics | B11: =SUMIFS('Energy balance options'!F$6:F$3000,'Energy balance options'!$B$6:$B$3000,'Refinery sector'!$A11,'Energy balance options'!$C$6:$C$3000,'Refinery sector'!$I$1) -> 0 | C11: =SUMIFS('Energy balance options'!G$6:G$3000,'Energy balance options'!$B$6:$B$3000,'Refinery sector'!$A11,'Energy balance options'!$C$6:$C$3000,'Refinery sector'!$I$1) -> 0 | D11: =B11+C11 -> 0 | F11: Bio feedstock | H11: Bio waste gasses | I11: =SUMIF($F$5:$F$67,H11,$D$5:$D$67) -> -0.40737171
A12: Biobenzine | B12: =SUMIFS('Energy balance options'!F$6:F$3000,'Energy balance options'!$B$6:$B$3000,'Refinery sector'!$A12,'Energy balance options'!$C$6:$C$3000,'Refinery sector'!$I$1) -> -0.00020763998 | C12: =SUMIFS('Energy balance options'!G$6:G$3000,'Energy balance options'!$B$6:$B$3000,'Refinery sector'!$A12,'Energy balance options'!$C$6:$C$3000,'Refinery sector'!$I$1) -> 0 | D12: =B12+C12 -> -0.00020763998 | F12: Biofuel | H12: Synthetic waste gasses | I12: =SUMIF($F$5:$F$67,H12,$D$5:$D$67) -> 2.4116916e-05
A13: Biobrandstoffen | B13: =SUMIFS('Energy balance options'!F$6:F$3000,'Energy balance options'!$B$6:$B$3000,'Refinery sector'!$A13,'Energy balance options'!$C$6:$C$3000,'Refinery sector'!$I$1) -> 0 | C13: =SUMIFS('Energy balance options'!G$6:G$3000,'Energy balance options'!$B$6:$B$3000,'Refinery sector'!$A13,'Energy balance options'!$C$6:$C$3000,'Refinery sector'!$I$1) -> 0 | D13: =B13+C13 -> 0 | F13: Biofuel | H13: Other oil products | I13: =SUMIF($F$5:$F$67,H13,$D$5:$D$67) -> -54.761801
A14: Biodiesel | B14: =SUMIFS('Energy balance options'!F$6:F$3000,'Energy balance options'!$B$6:$B$3000,'Refinery sector'!$A14,'Energy balance options'!$C$6:$C$3000,'Refinery sector'!$I$1) -> -16.339378 | C14: =SUMIFS('Energy balance options'!G$6:G$3000,'Energy balance options'!$B$6:$B$3000,'Refinery sector'!$A14,'Energy balance options'!$C$6:$C$3000,'Refinery sector'!$I$1) -> 0 | D14: =B14+C14 -> -16.339378 | F14: Biofuel | H14: Other bio oil products | I14: =SUMIF($F$5:$F$67,H14,$D$5:$D$67) -> 0
A15: Bio-DME | B15: =SUMIFS('Energy balance options'!F$6:F$3000,'Energy balance options'!$B$6:$B$3000,'Refinery sector'!$A15,'Energy balance options'!$C$6:$C$3000,'Refinery sector'!$I$1) -> -3.2887367e-05 | C15: =SUMIFS('Energy balance options'!G$6:G$3000,'Energy balance options'!$B$6:$B$3000,'Refinery sector'!$A15,'Energy balance options'!$C$6:$C$3000,'Refinery sector'!$I$1) -> 0 | D15: =B15+C15 -> -3.2887367e-05 | F15: Biofuel | H15: Other synthetic oil products | I15: =SUMIF($F$5:$F$67,H15,$D$5:$D$67) -> 0
A16: Bio-ethanol | B16: =SUMIFS('Energy balance options'!F$6:F$3000,'Energy balance options'!$B$6:$B$3000,'Refinery sector'!$A16,'Energy balance options'!$C$6:$C$3000,'Refinery sector'!$I$1) -> -0.00018765594 | C16: =SUMIFS('Energy balance options'!G$6:G$3000,'Energy balance options'!$B$6:$B$3000,'Refinery sector'!$A16,'Energy balance options'!$C$6:$C$3000,'Refinery sector'!$I$1) -> 2.9101907e-05 | D16: =B16+C16 -> -0.00015855403 | F16: Biofuel | H16: Plastic Pyrolysis Oil | I16: =SUMIF($F$5:$F$67,H16,$D$5:$D$67) -> 0
... A24: Biomassa (hout) | B24: =SUMIFS('Energy balance options'!F$6:F$3000,'Energy balance options'!$B$6:$B$3000,'Refinery sector'!$A24,'Energy balance options'!$C$6:$C$3000,'Refinery sector'!$I$1) -> -64.86006 | C24: =SUMIFS('Energy balance options'!G$6:G$3000,'Energy balance options'!$B$6:$B$3000,'Refinery sector'!$A24,'Energy balance options'!$C$6:$C$3000,'Refinery sector'!$I$1) -> 14.587255 | D24: =B24+C24 -> -50.272805 | F24: Biomass | H24: Synthetic feedstock | I24: =SUMIF($F$5:$F$67,H24,$D$5:$D$67) -> -1.2102414e-05
A25: Biomassa (natte stromen) | B25: =SUMIFS('Energy balance options'!F$6:F$3000,'Energy balance options'!$B$6:$B$3000,'Refinery sector'!$A25,'Energy balance options'!$C$6:$C$3000,'Refinery sector'!$I$1) -> 0 | C25: =SUMIFS('Energy balance options'!G$6:G$3000,'Energy balance options'!$B$6:$B$3000,'Refinery sector'!$A25,'Energy balance options'!$C$6:$C$3000,'Refinery sector'!$I$1) -> 0 | D25: =B25+C25 -> 0 | F25: Biomass
A26: Biomassa (suikers) | B26: =SUMIFS('Energy balance options'!F$6:F$3000,'Energy balance options'!$B$6:$B$3000,'Refinery sector'!$A26,'Energy balance options'!$C$6:$C$3000,'Refinery sector'!$I$1) -> 0 | C26: =SUMIFS('Energy balance options'!G$6:G$3000,'Energy balance options'!$B$6:$B$3000,'Refinery sector'!$A26,'Energy balance options'!$C$6:$C$3000,'Refinery sector'!$I$1) -> 8.833853e-06 | D26: =B26+C26 -> 8.833853e-06 | F26: Biomass | H26: Total net | I26: =SUM(I5:I24) -> 140.52776
A27: Biomassa (UCO buitenland) | B27: =SUMIFS('Energy balance options'!F$6:F$3000,'Energy balance options'!$B$6:$B$3000,'Refinery sector'!$A27,'Energy balance options'!$C$6:$C$3000,'Refinery sector'!$I$1) -> 0 | C27: =SUMIFS('Energy balance options'!G$6:G$3000,'Energy balance options'!$B$6:$B$3000,'Refinery sector'!$A27,'Energy balance options'!$C$6:$C$3000,'Refinery sector'!$I$1) -> 23.5048 | D27: =B27+C27 -> 23.5048 | F27: Biomass
A28: Biomethanol | B28: =SUMIFS('Energy balance options'!F$6:F$3000,'Energy balance options'!$B$6:$B$3000,'Refinery sector'!$A28,'Energy balance options'!$C$6:$C$3000,'Refinery sector'!$I$1) -> 0 | C28: =SUMIFS('Energy balance options'!G$6:G$3000,'Energy balance options'!$B$6:$B$3000,'Refinery sector'!$A28,'Energy balance options'!$C$6:$C$3000,'Refinery sector'!$I$1) -> 3.3150389e-05 | D28: =B28+C28 -> 3.3150389e-05 | F28: Bio waste gasses
A29: Bio-methanol for shipping | B29: =SUMIFS('Energy balance options'!F$6:F$3000,'Energy balance options'!$B$6:$B$3000,'Refinery sector'!$A29,'Energy balance options'!$C$6:$C$3000,'Refinery sector'!$I$1) -> 0 | C29: =SUMIFS('Energy balance options'!G$6:G$3000,'Energy balance options'!$B$6:$B$3000,'Refinery sector'!$A29,'Energy balance options'!$C$6:$C$3000,'Refinery sector'!$I$1) -> 0 | D29: =B29+C29 -> 0 | F29: Biofuel | H29: CO2 captured | I29: Mton
A30: Bionaphta | B30: =SUMIFS('Energy balance options'!F$6:F$3000,'Energy balance options'!$B$6:$B$3000,'Refinery sector'!$A30,'Energy balance options'!$C$6:$C$3000,'Refinery sector'!$I$1) -> -3.546793 | C30: =SUMIFS('Energy balance options'!G$6:G$3000,'Energy balance options'!$B$6:$B$3000,'Refinery sector'!$A30,'Energy balance options'!$C$6:$C$3000,'Refinery sector'!$I$1) -> 0 | D30: =B30+C30 -> -3.546793 | F30: Bio feedstock | H30: CO2flow | I30: =-SUMIF('Energy balance options'!$B$6:$B$3000,H30,'Energy balance options'!F$6:F$3000) -> 10.62991
A31: Bio-restgassen | B31: =SUMIFS('Energy balance options'!F$6:F$3000,'Energy balance options'!$B$6:$B$3000,'Refinery sector'!$A31,'Energy balance options'!$C$6:$C$3000,'Refinery sector'!$I$1) -> -0.61819416 | C31: =SUMIFS('Energy balance options'!G$6:G$3000,'Energy balance options'!$B$6:$B$3000,'Refinery sector'!$A31,'Energy balance options'!$C$6:$C$3000,'Refinery sector'!$I$1) -> 0.2107893 | D31: =B31+C31 -> -0.40740486 | F31: Bio waste gasses
A32: Diesel | B32: =SUMIFS('Energy balance options'!F$6:F$3000,'Energy balance options'!$B$6:$B$3000,'Refinery sector'!$A32,'Energy balance options'!$C$6:$C$3000,'Refinery sector'!$I$1) -> -526.50937 | C32: =SUMIFS('Energy balance options'!G$6:G$3000,'Energy balance options'!$B$6:$B$3000,'Refinery sector'!$A32,'Energy balance options'!$C$6:$C$3000,'Refinery sector'!$I$1) -> 0 | D32: =B32+C32 -> -526.50937 | F32: Fossil fuel
A33: Elektriciteit | B33: =SUMIFS('Energy balance options'!F$6:F$3000,'Energy balance options'!$B$6:$B$3000,'Refinery sector'!$A33,'Energy balance options'!$C$6:$C$3000,'Refinery sector'!$I$1) -> -4.3811504 | C33: =SUMIFS('Energy balance options'!G$6:G$3000,'Energy balance options'!$B$6:$B$3000,'Refinery sector'!$A33,'Energy balance options'!$C$6:$C$3000,'Refinery sector'!$I$1) -> 12.756675 | D33: =B33+C33 -> 8.375525 | F33: Electricity
A34: Heat100to200 | B34: =SUMIFS('Energy balance options'!F$6:F$3000,'Energy balance options'!$B$6:$B$3000,'Refinery sector'!$A34,'Energy balance options'!$C$6:$C$3000,'Refinery sector'!$I$1) -> -1.2476184 | C34: =SUMIFS('Energy balance options'!G$6:G$3000,'Energy balance options'!$B$6:$B$3000,'Refinery sector'!$A34,'Energy balance options'!$C$6:$C$3000,'Refinery sector'!$I$1) -> 1.247604 | D34: =B34+C34 -> -1.434721e-05 | F34: Heat
A35: Heat200to400 | B35: =SUMIFS('Energy balance options'!F$6:F$3000,'Energy balance options'!$B$6:$B$3000,'Refinery sector'!$A35,'Energy balance options'!$C$6:$C$3000,'Refinery sector'!$I$1) -> -79.037463 | C35: =SUMIFS('Energy balance options'!G$6:G$3000,'Energy balance options'!$B$6:$B$3000,'Refinery sector'!$A35,'Energy balance options'!$C$6:$C$3000,'Refinery sector'!$I$1) -> 79.037416 | D35: =B35+C35 -> -4.7327278e-05 | F35: Heat
A36: HeatDir200to400 | B36: =SUMIFS('Energy balance options'!F$6:F$3000,'Energy balance options'!$B$6:$B$3000,'Refinery sector'!$A36,'Energy balance options'!$C$6:$C$3000,'Refinery sector'!$I$1) -> 0 | C36: =SUMIFS('Energy balance options'!G$6:G$3000,'Energy balance options'!$B$6:$B$3000,'Refinery sector'!$A36,'Energy balance options'!$C$6:$C$3000,'Refinery sector'!$I$1) -> 0 | D36: =B36+C36 -> 0 | F36: Heat
A37: HeatHT400 | B37: =SUMIFS('Energy balance options'!F$6:F$3000,'Energy balance options'!$B$6:$B$3000,'Refinery sector'!$A37,'Energy balance options'!$C$6:$C$3000,'Refinery sector'!$I$1) -> 0 | C37: =SUMIFS('Energy balance options'!G$6:G$3000,'Energy balance options'!$B$6:$B$3000,'Refinery sector'!$A37,'Energy balance options'!$C$6:$C$3000,'Refinery sector'!$I$1) -> 0 | D37: =B37+C37 -> 0 | F37: Heat
A38: HeatLessThan200 | B38: =SUMIFS('Energy balance options'!F$6:F$3000,'Energy balance options'!$B$6:$B$3000,'Refinery sector'!$A38,'Energy balance options'!$C$6:$C$3000,'Refinery sector'!$I$1) -> 0 | C38: =SUMIFS('Energy balance options'!G$6:G$3000,'Energy balance options'!$B$6:$B$3000,'Refinery sector'!$A38,'Energy balance options'!$C$6:$C$3000,'Refinery sector'!$I$1) -> 0 | D38: =B38+C38 -> 0 | F38: Heat
A39: HeatMoreThan200 | B39: =SUMIFS('Energy balance options'!F$6:F$3000,'Energy balance options'!$B$6:$B$3000,'Refinery sector'!$A39,'Energy balance options'!$C$6:$C$3000,'Refinery sector'!$I$1) -> 0 | C39: =SUMIFS('Energy balance options'!G$6:G$3000,'Energy balance options'!$B$6:$B$3000,'Refinery sector'!$A39,'Energy balance options'!$C$6:$C$3000,'Refinery sector'!$I$1) -> 0 | D39: =B39+C39 -> 0 | F39: Heat
A40: HFO | B40: =SUMIFS('Energy balance options'!F$6:F$3000,'Energy balance options'!$B$6:$B$3000,'Refinery sector'!$A40,'Energy balance options'!$C$6:$C$3000,'Refinery sector'!$I$1) -> -243.62142 | C40: =SUMIFS('Energy balance options'!G$6:G$3000,'Energy balance options'!$B$6:$B$3000,'Refinery sector'!$A40,'Energy balance options'!$C$6:$C$3000,'Refinery sector'!$I$1) -> 0 | D40: =B40+C40 -> -243.62142 | F40: Fossil fuel
A41: Industrial Waste Heat | B41: =SUMIFS('Energy balance options'!F$6:F$3000,'Energy balance options'!$B$6:$B$3000,'Refinery sector'!$A41,'Energy balance options'!$C$6:$C$3000,'Refinery sector'!$I$1) -> -4.5320708e-05 | C41: =SUMIFS('Energy balance options'!G$6:G$3000,'Energy balance options'!$B$6:$B$3000,'Refinery sector'!$A41,'Energy balance options'!$C$6:$C$3000,'Refinery sector'!$I$1) -> 4.9352221e-05 | D41: =B41+C41 -> 4.0315123e-06 | F41: Heat
A42: Kerosine | B42: =SUMIFS('Energy balance options'!F$6:F$3000,'Energy balance options'!$B$6:$B$3000,'Refinery sector'!$A42,'Energy balance options'!$C$6:$C$3000,'Refinery sector'!$I$1) -> -236.4061 | C42: =SUMIFS('Energy balance options'!G$6:G$3000,'Energy balance options'!$B$6:$B$3000,'Refinery sector'!$A42,'Energy balance options'!$C$6:$C$3000,'Refinery sector'!$I$1) -> 0 | D42: =B42+C42 -> -236.4061 | F42: Fossil fuel
... A67: Waterstof | B67: =SUMIFS('Energy balance options'!F$6:F$3000,'Energy balance options'!$B$6:$B$3000,'Refinery sector'!$A67,'Energy balance options'!$C$6:$C$3000,'Refinery sector'!$I$1) -> 0 | C67: =SUMIFS('Energy balance options'!G$6:G$3000,'Energy balance options'!$B$6:$B$3000,'Refinery sector'!$A67,'Energy balance options'!$C$6:$C$3000,'Refinery sector'!$I$1) -> 60.954884 | D67: =B67+C67 -> 60.954884 | F67: Hydrogen

Sheet Emission per option-sector
A2: Emissions per option [Mton]. The sector the option is part of is indicated. Note there is a total, energy related and there is non-energy/correction. This non-energy/correction is used to compensate/cancel out the energy related.
B4: Identifier | C4: Sector | D4: Total [Mton] | E4: Total Energy Carrier Related [Mton] | F4: Non-energy or other correction [Mton]
A5: Option | B5: Emission Type
A6: 913 Mono manure AD Green gas | B6: Broeikasgassen | C6: Landbouw | D6: -0.98423359 | E6: -0.84899484
A7: 913 Mono manure AD Green gas | B7: CO2 | C7: Landbouw | D7: -0.84899484 | E7: -0.84899484
A8: 913 Mono manure AD Green gas | B8: CH4 | C8: Landbouw | D8: -0.19010704
A9: 913 Mono manure AD Green gas | B9: N2O | C9: Landbouw | D9: 0.054868291
A10: 1016 ATR with CC | B10: Broeikasgassen | C10: H2 voorziening | D10: 0.74456033 | E10: 0.74456033
A11: 1016 ATR with CC | B11: CO2 | C11: H2 voorziening | D11: 0.74456033 | E11: 0.74456033
A12: 1023 Ground water heat pump - Services | B12: Broeikasgassen | C12: HDO | D12: 0.011006699 | E12: 0.011006699
A13: 1023 Ground water heat pump - Services | B13: CO2 | C13: HDO | D13: 0.011006699 | E13: 0.011006699
A14: 1027 REF HR-107 - Services | B14: Broeikasgassen | C14: HDO | D14: 1.324592 | E14: 1.324592
A15: 1027 REF HR-107 - Services | B15: CO2 | C15: HDO | D15: 1.324592 | E15: 1.324592
A16: 1035 REF HR-107 - Existing - Residential | B16: Broeikasgassen | C16: Huishoudens | D16: 11.092081 | E16: 11.092081
A17: 1035 REF HR-107 - Existing - Residential | B17: CO2 | C17: Huishoudens | D17: 11.092081 | E17: 11.092081
A18: 1037 REF HR-107 - Newly built - Residential | B18: Broeikasgassen | C18: Huishoudens | D18: 1.6310842 | E18: 1.6310842
A19: 1037 REF HR-107 - Newly built - Residential | B19: CO2 | C19: Huishoudens | D19: 1.6310842 | E19: 1.6310842
A20: 1043 REF H2 uit SMR 2011 | B20: Broeikasgassen | C20: H2 voorziening | D20: 4.6549118e-06 | E20: 4.6549118e-06
A21: 1043 REF H2 uit SMR 2011 | B21: CO2 | C21: H2 voorziening | D21: 4.6549118e-06 | E21: 4.6549118e-06
... A63: 1248 REF WKK gas Landbouw ebalans | B63: CO2 | C63: Landbouw | D63: 1.2040394e-06 | E63: 1.2040394e-06
A64: 1248 REF WKK gas Landbouw ebalans | B64: CH4 | C64: Landbouw | D64: 2.4495023e-07
A65: 1270 CAES ontlader | B65: Broeikasgassen | C65: Elektriciteitsopwekking | D65: 2.0788978e-06 | E65: 2.0788978e-06
A66: 1270 CAES ontlader | B66: CO2 | C66: Elektriciteitsopwekking | D66: 2.0788978e-06 | E66: 2.0788978e-06
A67: 1273 REF diesel | B67: Broeikasgassen | C67: Verkeer | D67: 0.00017487865 | E67: 0.00017487865
A68: 1273 REF diesel | B68: CO2 | C68: Verkeer | D68: 0.00017487865 | E68: 0.00017487865
A69: 1274 REF benzine | B69: Broeikasgassen | C69: Verkeer | D69: 1.606556 | E69: 1.606556
A70: 1274 REF benzine | B70: CO2 | C70: Verkeer | D70: 1.606556 | E70: 1.606556
A71: 1284 REF OvOmz raffinaderijen ebalans | B71: Broeikasgassen | C71: Raffinaderijen | D71: 1.1352162 | E71: 1.1352162
A72: 1284 REF OvOmz raffinaderijen ebalans | B72: CO2 | C72: Raffinaderijen | D72: 1.1352162 | E72: 1.1352162
A73: 1286 REF Ketels aardgas raffinaderijen ebalans | B73: Broeikasgassen | C73: Raffinaderijen | D73: 6.6208652e-06 | E73: 6.6208652e-06
A74: 1286 REF Ketels aardgas raffinaderijen ebalans | B74: CO2 | C74: Raffinaderijen | D74: 6.6208652e-06 | E74: 6.6208652e-06
A75: 1289 REF Ketels rest raffinaderijen ebalans | B75: Broeikasgassen | C75: Raffinaderijen | D75: 2.1987094e-06 | E75: 2.1987094e-06
A76: 1289 REF Ketels rest raffinaderijen ebalans | B76: CO2 | C76: Raffinaderijen | D76: 2.1987094e-06 | E76: 2.1987094e-06
... A80: 1351 REF ICE personenauto | B80: CO2 | C80: Verkeer | D80: 6.3761278 | E80: 6.3761278
A81: 1351 REF ICE personenauto | B81: CH4 | C81: Verkeer | D81: zero
A82: 1351 REF ICE personenauto | B82: N2O | C82: Verkeer | D82: 0.11063776
A83: 1352 REF PI hybride auto | B83: Broeikasgassen | C83: Verkeer | D83: 6.8549497e-07 | E83: 6.5753303e-07
A84: 1352 REF PI hybride auto | B84: CO2 | C84: Verkeer | D84: 6.5753303e-07 | E84: 6.5753303e-07
A85: 1352 REF PI hybride auto | B85: CH4 | C85: Verkeer | D85: zero
A86: 1352 REF PI hybride auto | B86: N2O | C86: Verkeer | D86: 2.5877218e-08
A87: 1354 CNG auto | B87: Broeikasgassen | C87: Verkeer | D87: 1.2523035e-05 | E87: 1.2304751e-05
A88: 1354 CNG auto | B88: CO2 | C88: Verkeer | D88: 1.2304751e-05 | E88: 1.2304751e-05
A89: 1354 CNG auto | B89: CH4 | C89: Verkeer | D89: zero
A90: 1354 CNG auto | B90: N2O | C90: Verkeer | D90: 1.8046329e-07
A91: 1357 Diesel hybrid car with high fuel reduction | B91: Broeikasgassen | C91: Verkeer | D91: 2.6326155e-07 | E91: 2.6326155e-07
A92: 1357 Diesel hybrid car with high fuel reduction | B92: CO2 | C92: Verkeer | D92: 2.6326155e-07 | E92: 2.6326155e-07
A93: 1358 PI auto | B93: Broeikasgassen | C93: Verkeer | D93: 3.9475711e-07 | E93: 3.9475711e-07
A94: 1358 PI auto | B94: CO2 | C94: Verkeer | D94: 3.9475711e-07 | E94: 3.9475711e-07
A95: 1359 Flex ketel restgassen | B95: Broeikasgassen | C95: Industrie | D95: 0.0080386715 | E95: 0.0080386715
A96: 1359 Flex ketel restgassen | B96: CO2 | C96: Industrie | D96: 0.0080386715 | E96: 0.0080386715
A97: 1360 Flex WKK restgassen | B97: Broeikasgassen | C97: Industrie | D97: 1.2079606e-06 | E97: 1.2079606e-06
A98: 1360 Flex WKK restgassen | B98: CO2 | C98: Industrie | D98: 1.2079606e-06 | E98: 1.2079606e-06
A99: 1363 E85 flex-fuel car | B99: Broeikasgassen | C99: Verkeer | D99: 0.053681891 | E99: 0.049580336
A100: 1363 E85 flex-fuel car | B100: CO2 | C100: Verkeer | D100: 0.049580336 | E100: 0.049580336
A101: 1363 E85 flex-fuel car | B101: CH4 | C101: Verkeer | D101: zero
A102: 1363 E85 flex-fuel car | B102: N2O | C102: Verkeer | D102: 0.0036416645
A103: 1364 REF HDV vracht | B103: Broeikasgassen | C103: Verkeer | D103: 7.7049501 | E103: 7.6820342
A104: 1364 REF HDV vracht | B104: CO2 | C104: Verkeer | D104: 7.6820342 | E104: 7.6820342
A105: 1364 REF HDV vracht | B105: CH4 | C105: Verkeer | D105: zero
A106: 1364 REF HDV vracht | B106: N2O | C106: Verkeer | D106: 0.022502644
A107: 1365 LNG truck | B107: Broeikasgassen | C107: Verkeer | D107: 9.6891803e-07 | E107: 8.7654716e-07
A108: 1365 LNG truck | B108: CO2 | C108: Verkeer | D108: 8.7654716e-07 | E108: 8.7654716e-07
A109: 1365 LNG truck | B109: CH4 | C109: Verkeer | D109: 9.2370874e-08
A110: 1371 Natural Gas Medium Temp Boilers - Chemical | B110: Broeikasgassen | C110: Chemie | D110: 1.1014048e-05 | E110: 1.1014048e-05
A111: 1371 Natural Gas Medium Temp Boilers - Chemical | B111: CO2 | C111: Chemie | D111: 1.1014048e-05 | E111: 1.1014048e-05
A112: 1372 Natural Gas Medium Temp Boilers - Refineries | B112: Broeikasgassen | C112: Raffinaderijen | D112: 0.045470939 | E112: 0.045470939
A113: 1372 Natural Gas Medium Temp Boilers - Refineries | B113: CO2 | C113: Raffinaderijen | D113: 0.045470939 | E113: 0.045470939
A114: 1373 Natural Gas CHP - Chemical | B114: Broeikasgassen | C114: Chemie | D114: 1.0452837e-05 | E114: 1.0452837e-05
A115: 1373 Natural Gas CHP - Chemical | B115: CO2 | C115: Chemie | D115: 1.0452837e-05 | E115: 1.0452837e-05
A116: 1374 Natural Gas CHP - Refineries | B116: Broeikasgassen | C116: Raffinaderijen | D116: 0.58000582 | E116: 0.58000582
A117: 1374 Natural Gas CHP - Refineries | B117: CO2 | C117: Raffinaderijen | D117: 0.58000582 | E117: 0.58000582
A118: 1375 REF ammoniak productie | B118: Broeikasgassen | C118: Kunstmestindustrie | D118: 3.5640512 | E118: 3.3137791
A119: 1375 REF ammoniak productie | B119: CO2 | C119: Kunstmestindustrie | D119: 3.3137791 | E119: 3.3137791
A120: 1375 REF ammoniak productie | B120: N2O | C120: Kunstmestindustrie | D120: 0.25027213
A121: 1377 REF Aardgas naar feedstock NH3 | B121: Broeikasgassen | C121: Kunstmestindustrie | D121: -4.7999267e-09 | E121: -4.7999267e-09
A122: 1377 REF Aardgas naar feedstock NH3 | B122: CO2 | C122: Kunstmestindustrie | D122: -4.7999267e-09 | E122: -4.7999267e-09
A123: 1387 REF Natural Gas CHP - Basic metals | B123: Broeikasgassen | C123: Basismetaal ferro | D123: 2.1560096e-05 | E123: 2.1560096e-05
A124: 1387 REF Natural Gas CHP - Basic metals | B124: CO2 | C124: Basismetaal ferro | D124: 2.1560096e-05 | E124: 2.1560096e-05
A125: 1388 Natural Gas Medium Temp Boilers - Basic Metals | B125: Broeikasgassen | C125: Basismetaal ferro | D125: 1.8714484e-05 | E125: 1.8714484e-05
A126: 1388 Natural Gas Medium Temp Boilers - Basic Metals | B126: CO2 | C126: Basismetaal ferro | D126: 1.8714484e-05 | E126: 1.8714484e-05
A127: 1391 REF WKK rest chemie ebalans | B127: Broeikasgassen | C127: Chemie | D127: 5.2015517e-06 | E127: 5.2015517e-06
A128: 1391 REF WKK rest chemie ebalans | B128: CO2 | C128: Chemie | D128: 5.2015517e-06 | E128: 5.2015517e-06
A129: 1392 REF Ketels rest chemie ebalans | B129: Broeikasgassen | C129: Chemie | D129: 2.16803e-05 | E129: 2.16803e-05
A130: 1392 REF Ketels rest chemie ebalans | B130: CO2 | C130: Chemie | D130: 2.16803e-05 | E130: 2.16803e-05
A131: 1395 REF WKK rest Basismetaal ebalans | B131: Broeikasgassen | C131: Basismetaal ferro | D131: -0.0079804417 | E131: -0.0079804417
A132: 1395 REF WKK rest Basismetaal ebalans | B132: CO2 | C132: Basismetaal ferro | D132: -0.0079804417 | E132: -0.0079804417
... A146: 1509 E85 flex-fuel car with high efficiency | B146: CO2 | C146: Verkeer | D146: 1.5630109e-07 | E146: 1.5630109e-07
A147: 1509 E85 flex-fuel car with high efficiency | B147: CH4 | C147: Verkeer | D147: zero
A148: 1509 E85 flex-fuel car with high efficiency | B148: N2O | C148: Verkeer | D148: 5.7000608e-08
A149: 1512 CO2 opslag after capture | B149: Broeikasgassen | C149: Gasvoorziening | D149: -10.500001
A150: 1512 CO2 opslag after capture | B150: CO2 | C150: Gasvoorziening | D150: -10.500001
A151: 1583 Natural Gas CHP with CCS - Industry | B151: Broeikasgassen | C151: Industrie | D151: 2.2362963e-05 | E151: 2.2362963e-05
A152: 1583 Natural Gas CHP with CCS - Industry | B152: CO2 | C152: Industrie | D152: 2.2362963e-05 | E152: 2.2362963e-05
A153: 1586 Natural Gas Low Temp Boilers with CCS - Industry | B153: Broeikasgassen | C153: Industrie | D153: 0.15187421 | E153: 0.15187421
A154: 1586 Natural Gas Low Temp Boilers with CCS - Industry | B154: CO2 | C154: Industrie | D154: 0.15187421 | E154: 0.15187421
A155: 1589 Natural Gas Medium Temp Boilers with CCS - Industry | B155: Broeikasgassen | C155: Industrie | D155: 0.031868128 | E155: 0.031868128
A156: 1589 Natural Gas Medium Temp Boilers with CCS - Industry | B156: CO2 | C156: Industrie | D156: 0.031868128 | E156: 0.031868128
A157: 1592 NG DF 200-400C- Industry | B157: Broeikasgassen | C157: Industrie | D157: 0.0010236239 | E157: 0.0010236239
A158: 1592 NG DF 200-400C- Industry | B158: CO2 | C158: Industrie | D158: 0.0010236239 | E158: 0.0010236239
A159: 1594 H2 uit SMR met CCS plus | B159: Broeikasgassen | C159: H2 voorziening | D159: 4.712839e-06 | E159: 4.712839e-06
...

Sheet CO2 emissions per sector
A2: CO2 emissions per sector. [Mton CO2-eq]
A4: Uncorrected, so all CO2 storage is allocated to the sector 'gasvoorziening', of which option 1512 is part | H4: Total CO2 stored | I4: =-SUMIFS('Emission per option-sector'!D6:D500,'Emission per option-sector'!A6:A500,"1512 CO2 opslag after capture",'Emission per option-sector'!B6:B500,"CO2") -> 10.500001 | L4: Corrected, so all CO2 storage is allocated to the sectors, based on the storage/capture ratio | S4: KEV2020 CO2 emissions (incl. Indirect)
R5: 2030
A6: Sector | B6: CO2 | C6: CO2, aviation | D6: CO2, shipping | E6: CO2, LULUCF | H6: Total CO2 capture | I6: Of which CCS | K6: Main Sector | L6: Sector | M6: CO2 | N6: CO2, aviation | O6: CO2, shipping | P6: CO2, LULUCF | R6: CO2 | S6: CO2, aviation | T6: CO2, shipping | U6: CO2, LULUCF
A7: Landbouw | B7: =SUMIFS('Emission per option-sector'!$D$6:$D$600,'Emission per option-sector'!$C$6:$C$600,'CO2 emissions per sector'!$A7,'Emission per option-sector'!$B$6:$B$600,B$6) -> 0.46117297 | C7: =SUMIFS('Emission per option-sector'!$D$6:$D$600,'Emission per option-sector'!$C$6:$C$600,'CO2 emissions per sector'!$A7,'Emission per option-sector'!$B$6:$B$600,C$6) -> 0 | D7: =SUMIFS('Emission per option-sector'!$D$6:$D$600,'Emission per option-sector'!$C$6:$C$600,'CO2 emissions per sector'!$A7,'Emission per option-sector'!$B$6:$B$600,D$6) -> 0 | E7: =SUMIFS('Emission per option-sector'!$D$6:$D$600,'Emission per option-sector'!$C$6:$C$600,'CO2 emissions per sector'!$A7,'Emission per option-sector'!$B$6:$B$600,E$6) -> 0 | H7: =-SUMIFS('Energy balance options'!$F$7:$F$4000,'Energy balance options'!$C$7:$C$4000,'CO2 emissions per sector'!$A7,'Energy balance options'!$B$7:$B$4000,"CO2flow") -> 0 | I7: =$I$4*H7/$H$28 -> 0 | K7: KIP agriculture | L7: Landbouw | M7: =B7-I7 -> 0.46117297 | N7: =C7 -> 0 | O7: =D7 -> 0 | P7: =E7 -> 0 | R7: 6.3079026
A8: Overige landbouw | B8: =SUMIFS('Emission per option-sector'!$D$6:$D$600,'Emission per option-sector'!$C$6:$C$600,'CO2 emissions per sector'!$A8,'Emission per option-sector'!$B$6:$B$600,B$6) -> 0 | C8: =SUMIFS('Emission per option-sector'!$D$6:$D$600,'Emission per option-sector'!$C$6:$C$600,'CO2 emissions per sector'!$A8,'Emission per option-sector'!$B$6:$B$600,C$6) -> 0 | D8: =SUMIFS('Emission per option-sector'!$D$6:$D$600,'Emission per option-sector'!$C$6:$C$600,'CO2 emissions per sector'!$A8,'Emission per option-sector'!$B$6:$B$600,D$6) -> 0 | E8: =SUMIFS('Emission per option-sector'!$D$6:$D$600,'Emission per option-sector'!$C$6:$C$600,'CO2 emissions per sector'!$A8,'Emission per option-sector'!$B$6:$B$600,E$6) -> 0 | H8: =-SUMIFS('Energy balance options'!$F$7:$F$4000,'Energy balance options'!$C$7:$C$4000,'CO2 emissions per sector'!$A8,'Energy balance options'!$B$7:$B$4000,"CO2flow") -> 0 | I8: =$I$4*H8/$H$28 -> 0 | K8: KIP agriculture | L8: Overige landbouw | M8: =B8-I8 -> 0 | N8: =C8 -> 0 | O8: =D8 -> 0 | P8: =E8 -> 0 | R8: 0
A9: Huishoudens | B9: =SUMIFS('Emission per option-sector'!$D$6:$D$600,'Emission per option-sector'!$C$6:$C$600,'CO2 emissions per sector'!$A9,'Emission per option-sector'!$B$6:$B$600,B$6) -> 13.08703 | C9: =SUMIFS('Emission per option-sector'!$D$6:$D$600,'Emission per option-sector'!$C$6:$C$600,'CO2 emissions per sector'!$A9,'Emission per option-sector'!$B$6:$B$600,C$6) -> 0 | D9: =SUMIFS('Emission per option-sector'!$D$6:$D$600,'Emission per option-sector'!$C$6:$C$600,'CO2 emissions per sector'!$A9,'Emission per option-sector'!$B$6:$B$600,D$6) -> 0 | E9: =SUMIFS('Emission per option-sector'!$D$6:$D$600,'Emission per option-sector'!$C$6:$C$600,'CO2 emissions per sector'!$A9,'Emission per option-sector'!$B$6:$B$600,E$6) -> 0 | H9: =-SUMIFS('Energy balance options'!$F$7:$F$4000,'Energy balance options'!$C$7:$C$4000,'CO2 emissions per sector'!$A9,'Energy balance options'!$B$7:$B$4000,"CO2flow") -> 0 | I9: =$I$4*H9/$H$28 -> 0 | K9: KIP built environment | L9: Huishoudens | M9: =B9-I9 -> 13.08703 | N9: =C9 -> 0 | O9: =D9 -> 0 | P9: =E9 -> 0 | R9: 13.533992
A10: HDO | B10: =SUMIFS('Emission per option-sector'!$D$6:$D$600,'Emission per option-sector'!$C$6:$C$600,'CO2 emissions per sector'!$A10,'Emission per option-sector'!$B$6:$B$600,B$6) -> 3.7198044 | C10: =SUMIFS('Emission per option-sector'!$D$6:$D$600,'Emission per option-sector'!$C$6:$C$600,'CO2 emissions per sector'!$A10,'Emission per option-sector'!$B$6:$B$600,C$6) -> 0 | D10: =SUMIFS('Emission per option-sector'!$D$6:$D$600,'Emission per option-sector'!$C$6:$C$600,'CO2 emissions per sector'!$A10,'Emission per option-sector'!$B$6:$B$600,D$6) -> 0 | E10: =SUMIFS('Emission per option-sector'!$D$6:$D$600,'Emission per option-sector'!$C$6:$C$600,'CO2 emissions per sector'!$A10,'Emission per option-sector'!$B$6:$B$600,E$6) -> 0 | H10: =-SUMIFS('Energy balance options'!$F$7:$F$4000,'Energy balance options'!$C$7:$C$4000,'CO2 emissions per sector'!$A10,'Energy balance options'!$B$7:$B$4000,"CO2flow") -> 0 | I10: =$I$4*H10/$H$28 -> 0 | K10: KIP built environment | L10: HDO | M10: =B10-I10 -> 3.7198044 | N10: =C10 -> 0 | O10: =D10 -> 0 | P10: =E10 -> 0 | R10: 4.4538084
A11: Bunkers | B11: =SUMIFS('Emission per option-sector'!$D$6:$D$600,'Emission per option-sector'!$C$6:$C$600,'CO2 emissions per sector'!$A11,'Emission per option-sector'!$B$6:$B$600,B$6) -> 0 | C11: =SUMIFS('Emission per option-sector'!$D$6:$D$600,'Emission per option-sector'!$C$6:$C$600,'CO2 emissions per sector'!$A11,'Emission per option-sector'!$B$6:$B$600,C$6) -> 9.9971522 | D11: =SUMIFS('Emission per option-sector'!$D$6:$D$600,'Emission per option-sector'!$C$6:$C$600,'CO2 emissions per sector'!$A11,'Emission per option-sector'!$B$6:$B$600,D$6) -> 32.547891 | E11: =SUMIFS('Emission per option-sector'!$D$6:$D$600,'Emission per option-sector'!$C$6:$C$600,'CO2 emissions per sector'!$A11,'Emission per option-sector'!$B$6:$B$600,E$6) -> 0 | H11: =-SUMIFS('Energy balance options'!$F$7:$F$4000,'Energy balance options'!$C$7:$C$4000,'CO2 emissions per sector'!$A11,'Energy balance options'!$B$7:$B$4000,"CO2flow") -> 0 | I11: =$I$4*H11/$H$28 -> 0 | K11: KIP bunkers | L11: Bunkers | M11: =B11-I11 -> 0 | N11: =C11 -> 9.9971522 | O11: =D11 -> 32.547891 | P11: =E11 -> 0 | S11: =14466.5918905326/1000 -> 14.466592 | T11: =36300.7824324009/1000 -> 36.300782
A12: Elektriciteitsopwekking | B12: =SUMIFS('Emission per option-sector'!$D$6:$D$600,'Emission per option-sector'!$C$6:$C$600,'CO2 emissions per sector'!$A12,'Emission per option-sector'!$B$6:$B$600,B$6) -> 5.4646982 | C12: =SUMIFS('Emission per option-sector'!$D$6:$D$600,'Emission per option-sector'!$C$6:$C$600,'CO2 emissions per sector'!$A12,'Emission per option-sector'!$B$6:$B$600,C$6) -> 0 | D12: =SUMIFS('Emission per option-sector'!$D$6:$D$600,'Emission per option-sector'!$C$6:$C$600,'CO2 emissions per sector'!$A12,'Emission per option-sector'!$B$6:$B$600,D$6) -> 0 | E12: =SUMIFS('Emission per option-sector'!$D$6:$D$600,'Emission per option-sector'!$C$6:$C$600,'CO2 emissions per sector'!$A12,'Emission per option-sector'!$B$6:$B$600,E$6) -> 0 | H12: =-SUMIFS('Energy balance options'!$F$7:$F$4000,'Energy balance options'!$C$7:$C$4000,'CO2 emissions per sector'!$A12,'Energy balance options'!$B$7:$B$4000,"CO2flow") -> 3.5081879e-05 | I12: =$I$4*H12/$H$28 -> 3.4653138e-05 | K12: KIP energy | L12: Elektriciteitsopwekking | M12: =B12-I12 -> 5.4646635 | N12: =C12 -> 0 | O12: =D12 -> 0 | P12: =E12 -> 0 | R12: 18.561762
A13: Warmteopwekking (centraal) | B13: =SUMIFS('Emission per option-sector'!$D$6:$D$600,'Emission per option-sector'!$C$6:$C$600,'CO2 emissions per sector'!$A13,'Emission per option-sector'!$B$6:$B$600,B$6) -> 1.0903514 | C13: =SUMIFS('Emission per option-sector'!$D$6:$D$600,'Emission per option-sector'!$C$6:$C$600,'CO2 emissions per sector'!$A13,'Emission per option-sector'!$B$6:$B$600,C$6) -> 0 | D13: =SUMIFS('Emission per option-sector'!$D$6:$D$600,'Emission per option-sector'!$C$6:$C$600,'CO2 emissions per sector'!$A13,'Emission per option-sector'!$B$6:$B$600,D$6) -> 0 | E13: =SUMIFS('Emission per option-sector'!$D$6:$D$600,'Emission per option-sector'!$C$6:$C$600,'CO2 emissions per sector'!$A13,'Emission per option-sector'!$B$6:$B$600,E$6) -> 0 | H13: =-SUMIFS('Energy balance options'!$F$7:$F$4000,'Energy balance options'!$C$7:$C$4000,'CO2 emissions per sector'!$A13,'Energy balance options'!$B$7:$B$4000,"CO2flow") -> 0 | I13: =$I$4*H13/$H$28 -> 0 | K13: KIP energy | L13: Warmteopwekking (centraal) | M13: =B13-I13 -> 1.0903514 | N13: =C13 -> 0 | O13: =D13 -> 0 | P13: =E13 -> 0 | R13: 0
A14: Basic metal non-ferro | B14: =SUMIFS('Emission per option-sector'!$D$6:$D$600,'Emission per option-sector'!$C$6:$C$600,'CO2 emissions per sector'!$A14,'Emission per option-sector'!$B$6:$B$600,B$6) -> 0.035650747 | C14: =SUMIFS('Emission per option-sector'!$D$6:$D$600,'Emission per option-sector'!$C$6:$C$600,'CO2 emissions per sector'!$A14,'Emission per option-sector'!$B$6:$B$600,C$6) -> 0 | D14: =SUMIFS('Emission per option-sector'!$D$6:$D$600,'Emission per option-sector'!$C$6:$C$600,'CO2 emissions per sector'!$A14,'Emission per option-sector'!$B$6:$B$600,D$6) -> 0 | E14: =SUMIFS('Emission per option-sector'!$D$6:$D$600,'Emission per option-sector'!$C$6:$C$600,'CO2 emissions per sector'!$A14,'Emission per option-sector'!$B$6:$B$600,E$6) -> 0 | H14: =-SUMIFS('Energy balance options'!$F$7:$F$4000,'Energy balance options'!$C$7:$C$4000,'CO2 emissions per sector'!$A14,'Energy balance options'!$B$7:$B$4000,"CO2flow") -> 0 | I14: =$I$4*H14/$H$28 -> 0 | K14: KIP industry | L14: Basic metal non-ferro | M14: =B14-I14 -> 0.035650747 | N14: =C14 -> 0 | O14: =D14 -> 0 | P14: =E14 -> 0 | R14: 0.18106797
A15: Basismetaal ferro | B15: =SUMIFS('Emission per option-sector'!$D$6:$D$600,'Emission per option-sector'!$C$6:$C$600,'CO2 emissions per sector'!$A15,'Emission per option-sector'!$B$6:$B$600,B$6) -> 5.07156 | C15: =SUMIFS('Emission per option-sector'!$D$6:$D$600,'Emission per option-sector'!$C$6:$C$600,'CO2 emissions per sector'!$A15,'Emission per option-sector'!$B$6:$B$600,C$6) -> 0 | D15: =SUMIFS('Emission per option-sector'!$D$6:$D$600,'Emission per option-sector'!$C$6:$C$600,'CO2 emissions per sector'!$A15,'Emission per option-sector'!$B$6:$B$600,D$6) -> 0 | E15: =SUMIFS('Emission per option-sector'!$D$6:$D$600,'Emission per option-sector'!$C$6:$C$600,'CO2 emissions per sector'!$A15,'Emission per option-sector'!$B$6:$B$600,E$6) -> 0 | H15: =-SUMIFS('Energy balance options'!$F$7:$F$4000,'Energy balance options'!$C$7:$C$4000,'CO2 emissions per sector'!$A15,'Energy balance options'!$B$7:$B$4000,"CO2flow") -> 1.3766777 | I15: =$I$4*H15/$H$28 -> 1.3598532 | K15: KIP industry | L15: Basismetaal ferro | M15: =B15-I15 -> 3.7117068 | N15: =C15 -> 0 | O15: =D15 -> 0 | P15: =E15 -> 0 | R15: 7.4996169
A16: Chemie | B16: =SUMIFS('Emission per option-sector'!$D$6:$D$600,'Emission per option-sector'!$C$6:$C$600,'CO2 emissions per sector'!$A16,'Emission per option-sector'!$B$6:$B$600,B$6) -> 12.723749 | C16: =SUMIFS('Emission per option-sector'!$D$6:$D$600,'Emission per option-sector'!$C$6:$C$600,'CO2 emissions per sector'!$A16,'Emission per option-sector'!$B$6:$B$600,C$6) -> 0 | D16: =SUMIFS('Emission per option-sector'!$D$6:$D$600,'Emission per option-sector'!$C$6:$C$600,'CO2 emissions per sector'!$A16,'Emission per option-sector'!$B$6:$B$600,D$6) -> 0 | E16: =SUMIFS('Emission per option-sector'!$D$6:$D$600,'Emission per option-sector'!$C$6:$C$600,'CO2 emissions per sector'!$A16,'Emission per option-sector'!$B$6:$B$600,E$6) -> 0 | H16: =-SUMIFS('Energy balance options'!$F$7:$F$4000,'Energy balance options'!$C$7:$C$4000,'CO2 emissions per sector'!$A16,'Energy balance options'!$B$7:$B$4000,"CO2flow") -> 5.6136744e-05 | I16: =$I$4*H16/$H$28 -> 5.5450689e-05 | K16: KIP industry | L16: Chemie | M16: =B16-I16 -> 12.723694 | N16: =C16 -> 0 | O16: =D16 -> 0 | P16: =E16 -> 0 | R16: =20.3380756129652+0.7416208-R21 -> 15.61621
A17: Food and Beverage Industry | B17: =SUMIFS('Emission per option-sector'!$D$6:$D$600,'Emission per option-sector'!$C$6:$C$600,'CO2 emissions per sector'!$A17,'Emission per option-sector'!$B$6:$B$600,B$6) -> 0.45064763 | C17: =SUMIFS('Emission per option-sector'!$D$6:$D$600,'Emission per option-sector'!$C$6:$C$600,'CO2 emissions per sector'!$A17,'Emission per option-sector'!$B$6:$B$600,C$6) -> 0 | D17: =SUMIFS('Emission per option-sector'!$D$6:$D$600,'Emission per option-sector'!$C$6:$C$600,'CO2 emissions per sector'!$A17,'Emission per option-sector'!$B$6:$B$600,D$6) -> 0 | E17: =SUMIFS('Emission per option-sector'!$D$6:$D$600,'Emission per option-sector'!$C$6:$C$600,'CO2 emissions per sector'!$A17,'Emission per option-sector'!$B$6:$B$600,E$6) -> 0 | H17: =-SUMIFS('Energy balance options'!$F$7:$F$4000,'Energy balance options'!$C$7:$C$4000,'CO2 emissions per sector'!$A17,'Energy balance options'!$B$7:$B$4000,"CO2flow") -> 0 | I17: =$I$4*H17/$H$28 -> 0 | K17: KIP industry | L17: Food and Beverage Industry | M17: =B17-I17 -> 0.45064763 | N17: =C17 -> 0 | O17: =D17 -> 0 | P17: =E17 -> 0 | R17: 3.2411075
A18: Gasvoorziening | B18: =SUMIFS('Emission per option-sector'!$D$6:$D$600,'Emission per option-sector'!$C$6:$C$600,'CO2 emissions per sector'!$A18,'Emission per option-sector'!$B$6:$B$600,B$6) -> -10.500002 | C18: =SUMIFS('Emission per option-sector'!$D$6:$D$600,'Emission per option-sector'!$C$6:$C$600,'CO2 emissions per sector'!$A18,'Emission per option-sector'!$B$6:$B$600,C$6) -> 0 | D18: =SUMIFS('Emission per option-sector'!$D$6:$D$600,'Emission per option-sector'!$C$6:$C$600,'CO2 emissions per sector'!$A18,'Emission per option-sector'!$B$6:$B$600,D$6) -> 0 | E18: =SUMIFS('Emission per option-sector'!$D$6:$D$600,'Emission per option-sector'!$C$6:$C$600,'CO2 emissions per sector'!$A18,'Emission per option-sector'!$B$6:$B$600,E$6) -> 0 | H18: =-SUMIFS('Energy balance options'!$F$7:$F$4000,'Energy balance options'!$C$7:$C$4000,'CO2 emissions per sector'!$A18,'Energy balance options'!$B$7:$B$4000,"CO2flow") -> 3.6230016e-06 | I18: =$I$4*H18/$H$28 -> 3.5787244e-06 | K18: KIP industry | L18: Gasvoorziening | M18: =B18-I18+I4 -> -5.3821573e-06 | N18: =C18 -> 0 | O18: =D18 -> 0 | P18: =E18 -> 0 | R18: 1.2362754
A19: H2 voorziening | B19: =SUMIFS('Emission per option-sector'!$D$6:$D$600,'Emission per option-sector'!$C$6:$C$600,'CO2 emissions per sector'!$A19,'Emission per option-sector'!$B$6:$B$600,B$6) -> 4.4404581 | C19: =SUMIFS('Emission per option-sector'!$D$6:$D$600,'Emission per option-sector'!$C$6:$C$600,'CO2 emissions per sector'!$A19,'Emission per option-sector'!$B$6:$B$600,C$6) -> 0 | D19: =SUMIFS('Emission per option-sector'!$D$6:$D$600,'Emission per option-sector'!$C$6:$C$600,'CO2 emissions per sector'!$A19,'Emission per option-sector'!$B$6:$B$600,D$6) -> 0 | E19: =SUMIFS('Emission per option-sector'!$D$6:$D$600,'Emission per option-sector'!$C$6:$C$600,'CO2 emissions per sector'!$A19,'Emission per option-sector'!$B$6:$B$600,E$6) -> 0 | H19: =-SUMIFS('Energy balance options'!$F$7:$F$4000,'Energy balance options'!$C$7:$C$4000,'CO2 emissions per sector'!$A19,'Energy balance options'!$B$7:$B$4000,"CO2flow") -> 2.7405315 | I19: =$I$4*H19/$H$28 -> 2.7070391 | K19: KIP industry | L19: H2 voorziening | M19: =B19-I19 -> 1.733419 | N19: =C19 -> 0 | O19: =D19 -> 0 | P19: =E19 -> 0 | R19: 0
A20: Industrie | B20: =SUMIFS('Emission per option-sector'!$D$6:$D$600,'Emission per option-sector'!$C$6:$C$600,'CO2 emissions per sector'!$A20,'Emission per option-sector'!$B$6:$B$600,B$6) -> 2.8409481 | C20: =SUMIFS('Emission per option-sector'!$D$6:$D$600,'Emission per option-sector'!$C$6:$C$600,'CO2 emissions per sector'!$A20,'Emission per option-sector'!$B$6:$B$600,C$6) -> 0 | D20: =SUMIFS('Emission per option-sector'!$D$6:$D$600,'Emission per option-sector'!$C$6:$C$600,'CO2 emissions per sector'!$A20,'Emission per option-sector'!$B$6:$B$600,D$6) -> 0 | E20: =SUMIFS('Emission per option-sector'!$D$6:$D$600,'Emission per option-sector'!$C$6:$C$600,'CO2 emissions per sector'!$A20,'Emission per option-sector'!$B$6:$B$600,E$6) -> 0 | H20: =-SUMIFS('Energy balance options'!$F$7:$F$4000,'Energy balance options'!$C$7:$C$4000,'CO2 emissions per sector'!$A20,'Energy balance options'!$B$7:$B$4000,"CO2flow") -> 0.15966311 | I20: =$I$4*H20/$H$28 -> 0.15771185 | K20: KIP industry | L20: Industrie | M20: =B20-I20 -> 2.6832363 | N20: =C20 -> 0 | O20: =D20 -> 0 | P20: =E20 -> 0 | R20: =36.80328-SUM(R14:R17,R21) -> 4.8017913
A21: Kunstmestindustrie | B21: =SUMIFS('Emission per option-sector'!$D$6:$D$600,'Emission per option-sector'!$C$6:$C$600,'CO2 emissions per sector'!$A21,'Emission per option-sector'!$B$6:$B$600,B$6) -> 3.3863651 | C21: =SUMIFS('Emission per option-sector'!$D$6:$D$600,'Emission per option-sector'!$C$6:$C$600,'CO2 emissions per sector'!$A21,'Emission per option-sector'!$B$6:$B$600,C$6) -> 0 | D21: =SUMIFS('Emission per option-sector'!$D$6:$D$600,'Emission per option-sector'!$C$6:$C$600,'CO2 emissions per sector'!$A21,'Emission per option-sector'!$B$6:$B$600,D$6) -> 0 | E21: =SUMIFS('Emission per option-sector'!$D$6:$D$600,'Emission per option-sector'!$C$6:$C$600,'CO2 emissions per sector'!$A21,'Emission per option-sector'!$B$6:$B$600,E$6) -> 0 | H21: =-SUMIFS('Energy balance options'!$F$7:$F$4000,'Energy balance options'!$C$7:$C$4000,'CO2 emissions per sector'!$A21,'Energy balance options'!$B$7:$B$4000,"CO2flow") -> 2.2455257 | I21: =$I$4*H21/$H$28 -> 2.2180828 | K21: KIP industry | L21: Kunstmestindustrie | M21: =B21-I21 -> 1.1682823 | N21: =C21 -> 0 | O21: =D21 -> 0 | P21: =E21 -> 0 | R21: 5.4634862
A22: Raffinaderijen | B22: =SUMIFS('Emission per option-sector'!$D$6:$D$600,'Emission per option-sector'!$C$6:$C$600,'CO2 emissions per sector'!$A22,'Emission per option-sector'!$B$6:$B$600,B$6) -> 6.7636811 | C22: =SUMIFS('Emission per option-sector'!$D$6:$D$600,'Emission per option-sector'!$C$6:$C$600,'CO2 emissions per sector'!$A22,'Emission per option-sector'!$B$6:$B$600,C$6) -> 0 | D22: =SUMIFS('Emission per option-sector'!$D$6:$D$600,'Emission per option-sector'!$C$6:$C$600,'CO2 emissions per sector'!$A22,'Emission per option-sector'!$B$6:$B$600,D$6) -> 0 | E22: =SUMIFS('Emission per option-sector'!$D$6:$D$600,'Emission per option-sector'!$C$6:$C$600,'CO2 emissions per sector'!$A22,'Emission per option-sector'!$B$6:$B$600,E$6) -> 0 | H22: =-SUMIFS('Energy balance options'!$F$7:$F$4000,'Energy balance options'!$C$7:$C$4000,'CO2 emissions per sector'!$A22,'Energy balance options'!$B$7:$B$4000,"CO2flow") -> 0.00010958848 | I22: =$I$4*H22/$H$28 -> 0.00010824919 | K22: KIP industry | L22: Raffinaderijen | M22: =B22-I22 -> 6.7635729 | N22: =C22 -> 0 | O22: =D22 -> 0 | P22: =E22 -> 0 | R22: 10.244651
A23: Waste | B23: =SUMIFS('Emission per option-sector'!$D$6:$D$600,'Emission per option-sector'!$C$6:$C$600,'CO2 emissions per sector'!$A23,'Emission per option-sector'!$B$6:$B$600,B$6) -> 1.9435273 | C23: =SUMIFS('Emission per option-sector'!$D$6:$D$600,'Emission per option-sector'!$C$6:$C$600,'CO2 emissions per sector'!$A23,'Emission per option-sector'!$B$6:$B$600,C$6) -> 0 | D23: =SUMIFS('Emission per option-sector'!$D$6:$D$600,'Emission per option-sector'!$C$6:$C$600,'CO2 emissions per sector'!$A23,'Emission per option-sector'!$B$6:$B$600,D$6) -> 0 | E23: =SUMIFS('Emission per option-sector'!$D$6:$D$600,'Emission per option-sector'!$C$6:$C$600,'CO2 emissions per sector'!$A23,'Emission per option-sector'!$B$6:$B$600,E$6) -> 0 | H23: =-SUMIFS('Energy balance options'!$F$7:$F$4000,'Energy balance options'!$C$7:$C$4000,'CO2 emissions per sector'!$A23,'Energy balance options'!$B$7:$B$4000,"CO2flow") -> 4.1073077 | I23: =$I$4*H23/$H$28 -> 4.0571117 | K23: KIP industry | L23: Waste | M23: =B23-I23 -> -2.1135844 | N23: =C23 -> 0 | O23: =D23 -> 0 | P23: =E23 -> 0 | R23: 2.5970308
A24: Verkeer | B24: =SUMIFS('Emission per option-sector'!$D$6:$D$600,'Emission per option-sector'!$C$6:$C$600,'CO2 emissions per sector'!$A24,'Emission per option-sector'!$B$6:$B$600,B$6) -> 20.202974 | C24: =SUMIFS('Emission per option-sector'!$D$6:$D$600,'Emission per option-sector'!$C$6:$C$600,'CO2 emissions per sector'!$A24,'Emission per option-sector'!$B$6:$B$600,C$6) -> 0 | D24: =SUMIFS('Emission per option-sector'!$D$6:$D$600,'Emission per option-sector'!$C$6:$C$600,'CO2 emissions per sector'!$A24,'Emission per option-sector'!$B$6:$B$600,D$6) -> 0 | E24: =SUMIFS('Emission per option-sector'!$D$6:$D$600,'Emission per option-sector'!$C$6:$C$600,'CO2 emissions per sector'!$A24,'Emission per option-sector'!$B$6:$B$600,E$6) -> 0 | H24: =-SUMIFS('Energy balance options'!$F$7:$F$4000,'Energy balance options'!$C$7:$C$4000,'CO2 emissions per sector'!$A24,'Energy balance options'!$B$7:$B$4000,"CO2flow") -> 0 | I24: =$I$4*H24/$H$28 -> 0 | K24: KIP transport | L24: Verkeer | M24: =B24-I24 -> 20.202974 | N24: =C24 -> 0 | O24: =D24 -> 0 | P24: =E24 -> 0 | R24: 28.06465
A25: MWT | B25: =SUMIFS('Emission per option-sector'!$D$6:$D$600,'Emission per option-sector'!$C$6:$C$600,'CO2 emissions per sector'!$A25,'Emission per option-sector'!$B$6:$B$600,B$6) -> 2.7663131 | C25: =SUMIFS('Emission per option-sector'!$D$6:$D$600,'Emission per option-sector'!$C$6:$C$600,'CO2 emissions per sector'!$A25,'Emission per option-sector'!$B$6:$B$600,C$6) -> 0 | D25: =SUMIFS('Emission per option-sector'!$D$6:$D$600,'Emission per option-sector'!$C$6:$C$600,'CO2 emissions per sector'!$A25,'Emission per option-sector'!$B$6:$B$600,D$6) -> 0 | E25: =SUMIFS('Emission per option-sector'!$D$6:$D$600,'Emission per option-sector'!$C$6:$C$600,'CO2 emissions per sector'!$A25,'Emission per option-sector'!$B$6:$B$600,E$6) -> 0 | H25: =-SUMIFS('Energy balance options'!$F$7:$F$4000,'Energy balance options'!$C$7:$C$4000,'CO2 emissions per sector'!$A25,'Energy balance options'!$B$7:$B$4000,"CO2flow") -> 0 | I25: =$I$4*H25/$H$28 -> 0 | K25: KIP transport | L25: MWT | M25: =B25-I25 -> 2.7663131 | N25: =C25 -> 0 | O25: =D25 -> 0 | P25: =E25 -> 0 | R25: 3.1654286
A26: LULUCF | B26: =SUMIFS('Emission per option-sector'!$D$6:$D$600,'Emission per option-sector'!$C$6:$C$600,'CO2 emissions per sector'!$A26,'Emission per option-sector'!$B$6:$B$600,B$6) -> 3.0839998 | C26: =SUMIFS('Emission per option-sector'!$D$6:$D$600,'Emission per option-sector'!$C$6:$C$600,'CO2 emissions per sector'!$A26,'Emission per option-sector'!$B$6:$B$600,C$6) -> 0 | D26: =SUMIFS('Emission per option-sector'!$D$6:$D$600,'Emission per option-sector'!$C$6:$C$600,'CO2 emissions per sector'!$A26,'Emission per option-sector'!$B$6:$B$600,D$6) -> 0 | E26: =SUMIFS('Emission per option-sector'!$D$6:$D$600,'Emission per option-sector'!$C$6:$C$600,'CO2 emissions per sector'!$A26,'Emission per option-sector'!$B$6:$B$600,E$6) -> 0 | H26: =-SUMIFS('Energy balance options'!$F$7:$F$4000,'Energy balance options'!$C$7:$C$4000,'CO2 emissions per sector'!$A26,'Energy balance options'!$B$7:$B$4000,"CO2flow") -> 0 | I26: =$I$4*H26/$H$28 -> 0 | K26: LULUCF | L26: LULUCF | M26: =B26-I26 -> 3.0839998 | N26: =C26 -> 0 | O26: =D26 -> 0 | P26: =E26 -> 0 | U26: =3620.35486192498/1000 -> 3.6203549
A28: Total | B28: =SUM(B7:B26) -> 77.032929 | C28: =SUM(C7:C26) -> 9.9971522 | D28: =SUM(D7:D26) -> 32.547891 | E28: =SUM(E7:E26) -> 0 | H28: =SUM(H7:H26) -> 10.62991 | I28: =SUM(I7:I26) -> 10.500001 | L28: Total | M28: =SUM(M7:M26) -> 77.032929 | N28: =SUM(N7:N26) -> 9.9971522 | O28: =SUM(O7:O26) -> 32.547891 | P28: =SUM(P7:P26) -> 0 | R28: =SUM(R7:R26) -> 124.96878 | S28: =SUM(S7:S26) -> 14.466592 | T28: =SUM(T7:T26) -> 36.300782 | U28: =SUM(U7:U26) -> 3.6203549
A31: non-CO2 emissions per sector. [Mton CO2-eq]
K32: KIP agriculture | L32: KIP built environment | M32: KIP bunkers | N32: KIP energy | O32: KIP industry | P32: KIP transport | Q32: LULUCF
A33: Sector | B33: CH4 | C33: N2O | D33: F-gassen | J33: CO2 emissions per main sector | K33: =SUMIF($K$7:$K$26,K$32,$M$7:$M$26) -> 0.46117297 | L33: =SUMIF($K$7:$K$26,L$32,$M$7:$M$26) -> 16.806835 | M33: =SUMIF($K$7:$K$26,M$32,$M$7:$M$26) -> 0 | N33: =SUMIF($K$7:$K$26,N$32,$M$7:$M$26) -> 6.5550149 | O33: =SUMIF($K$7:$K$26,O$32,$M$7:$M$26) -> 27.15662 | P33: =SUMIF($K$7:$K$26,P$32,$M$7:$M$26) -> 22.969287 | Q33: =SUMIF($K$7:$K$26,Q$32,$M$7:$M$26) -> 3.0839998
A34: Landbouw | B34: =SUMIFS('Emission per option-sector'!$D$6:$D$600,'Emission per option-sector'!$C$6:$C$600,$A34,'Emission per option-sector'!$B$6:$B$600,'CO2 emissions per sector'!B$33) -> 5.408995 | C34: =SUMIFS('Emission per option-sector'!$D$6:$D$600,'Emission per option-sector'!$C$6:$C$600,$A34,'Emission per option-sector'!$B$6:$B$600,'CO2 emissions per sector'!C$33) -> 2.9935852 | D34: =SUMIFS('Emission per option-sector'!$D$6:$D$600,'Emission per option-sector'!$C$6:$C$600,$A34,'Emission per option-sector'!$B$6:$B$600,'CO2 emissions per sector'!D$33) -> 0 | J34: CCS per main sector | K34: =SUMIF($K$7:$K$26,K$32,$I$7:$I$26) -> 0 | L34: =SUMIF($K$7:$K$26,L$32,$I$7:$I$26) -> 0 | M34: =SUMIF($K$7:$K$26,M$32,$I$7:$I$26) -> 0 | N34: =SUMIF($K$7:$K$26,N$32,$I$7:$I$26) -> 3.4653138e-05 | O34: =SUMIF($K$7:$K$26,O$32,$I$7:$I$26) -> 10.499966 | P34: =SUMIF($K$7:$K$26,P$32,$I$7:$I$26) -> 0 | Q34: =SUMIF($K$7:$K$26,Q$32,$I$7:$I$26) -> 0
A35: Overige landbouw | B35: =SUMIFS('Emission per option-sector'!$D$6:$D$500,'Emission per option-sector'!$C$6:$C$500,$A35,'Emission per option-sector'!$B$6:$B$500,'CO2 emissions per sector'!B$33) -> 0 | C35: =SUMIFS('Emission per option-sector'!$D$6:$D$500,'Emission per option-sector'!$C$6:$C$500,$A35,'Emission per option-sector'!$B$6:$B$500,'CO2 emissions per sector'!C$33) -> 0 | D35: =SUMIFS('Emission per option-sector'!$D$6:$D$500,'Emission per option-sector'!$C$6:$C$500,$A35,'Emission per option-sector'!$B$6:$B$500,'CO2 emissions per sector'!D$33) -> 0
A36: Huishoudens | B36: =SUMIFS('Emission per option-sector'!$D$6:$D$500,'Emission per option-sector'!$C$6:$C$500,$A36,'Emission per option-sector'!$B$6:$B$500,'CO2 emissions per sector'!B$33) -> 0.37213799 | C36: =SUMIFS('Emission per option-sector'!$D$6:$D$500,'Emission per option-sector'!$C$6:$C$500,$A36,'Emission per option-sector'!$B$6:$B$500,'CO2 emissions per sector'!C$33) -> 0 | D36: =SUMIFS('Emission per option-sector'!$D$6:$D$500,'Emission per option-sector'!$C$6:$C$500,$A36,'Emission per option-sector'!$B$6:$B$500,'CO2 emissions per sector'!D$33) -> 0
A37: HDO | B37: =SUMIFS('Emission per option-sector'!$D$6:$D$500,'Emission per option-sector'!$C$6:$C$500,$A37,'Emission per option-sector'!$B$6:$B$500,'CO2 emissions per sector'!B$33) -> 0 | C37: =SUMIFS('Emission per option-sector'!$D$6:$D$500,'Emission per option-sector'!$C$6:$C$500,$A37,'Emission per option-sector'!$B$6:$B$500,'CO2 emissions per sector'!C$33) -> 0 | D37: =SUMIFS('Emission per option-sector'!$D$6:$D$500,'Emission per option-sector'!$C$6:$C$500,$A37,'Emission per option-sector'!$B$6:$B$500,'CO2 emissions per sector'!D$33) -> 0
A38: Bunkers | B38: =SUMIFS('Emission per option-sector'!$D$6:$D$500,'Emission per option-sector'!$C$6:$C$500,$A38,'Emission per option-sector'!$B$6:$B$500,'CO2 emissions per sector'!B$33) -> 0 | C38: =SUMIFS('Emission per option-sector'!$D$6:$D$500,'Emission per option-sector'!$C$6:$C$500,$A38,'Emission per option-sector'!$B$6:$B$500,'CO2 emissions per sector'!C$33) -> 0 | D38: =SUMIFS('Emission per option-sector'!$D$6:$D$500,'Emission per option-sector'!$C$6:$C$500,$A38,'Emission per option-sector'!$B$6:$B$500,'CO2 emissions per sector'!D$33) -> 0
A39: Elektriciteitsopwekking | B39: =SUMIFS('Emission per option-sector'!$D$6:$D$500,'Emission per option-sector'!$C$6:$C$500,$A39,'Emission per option-sector'!$B$6:$B$500,'CO2 emissions per sector'!B$33) -> 0 | C39: =SUMIFS('Emission per option-sector'!$D$6:$D$500,'Emission per option-sector'!$C$6:$C$500,$A39,'Emission per option-sector'!$B$6:$B$500,'CO2 emissions per sector'!C$33) -> 0 | D39: =SUMIFS('Emission per option-sector'!$D$6:$D$500,'Emission per option-sector'!$C$6:$C$500,$A39,'Emission per option-sector'!$B$6:$B$500,'CO2 emissions per sector'!D$33) -> 0
A40: Warmteopwekking (centraal) | B40: =SUMIFS('Emission per option-sector'!$D$6:$D$500,'Emission per option-sector'!$C$6:$C$500,$A40,'Emission per option-sector'!$B$6:$B$500,'CO2 emissions per sector'!B$33) -> 0 | C40: =SUMIFS('Emission per option-sector'!$D$6:$D$500,'Emission per option-sector'!$C$6:$C$500,$A40,'Emission per option-sector'!$B$6:$B$500,'CO2 emissions per sector'!C$33) -> 0 | D40: =SUMIFS('Emission per option-sector'!$D$6:$D$500,'Emission per option-sector'!$C$6:$C$500,$A40,'Emission per option-sector'!$B$6:$B$500,'CO2 emissions per sector'!D$33) -> 0
A41: Basic metal non-ferro | B41: =SUMIFS('Emission per option-sector'!$D$6:$D$500,'Emission per option-sector'!$C$6:$C$500,$A41,'Emission per option-sector'!$B$6:$B$500,'CO2 emissions per sector'!B$33) -> 0 | C41: =SUMIFS('Emission per option-sector'!$D$6:$D$500,'Emission per option-sector'!$C$6:$C$500,$A41,'Emission per option-sector'!$B$6:$B$500,'CO2 emissions per sector'!C$33) -> 0 | D41: =SUMIFS('Emission per option-sector'!$D$6:$D$500,'Emission per option-sector'!$C$6:$C$500,$A41,'Emission per option-sector'!$B$6:$B$500,'CO2 emissions per sector'!D$33) -> 0
A42: Basismetaal ferro | B42: =SUMIFS('Emission per option-sector'!$D$6:$D$500,'Emission per option-sector'!$C$6:$C$500,$A42,'Emission per option-sector'!$B$6:$B$500,'CO2 emissions per sector'!B$33) -> 0 | C42: =SUMIFS('Emission per option-sector'!$D$6:$D$500,'Emission per option-sector'!$C$6:$C$500,$A42,'Emission per option-sector'!$B$6:$B$500,'CO2 emissions per sector'!C$33) -> 0 | D42: =SUMIFS('Emission per option-sector'!$D$6:$D$500,'Emission per option-sector'!$C$6:$C$500,$A42,'Emission per option-sector'!$B$6:$B$500,'CO2 emissions per sector'!D$33) -> 0
A43: Chemie | B43: =SUMIFS('Emission per option-sector'!$D$6:$D$500,'Emission per option-sector'!$C$6:$C$500,$A43,'Emission per option-sector'!$B$6:$B$500,'CO2 emissions per sector'!B$33) -> 0 | C43: =SUMIFS('Emission per option-sector'!$D$6:$D$500,'Emission per option-sector'!$C$6:$C$500,$A43,'Emission per option-sector'!$B$6:$B$500,'CO2 emissions per sector'!C$33) -> 0.37459323 | D43: =SUMIFS('Emission per option-sector'!$D$6:$D$500,'Emission per option-sector'!$C$6:$C$500,$A43,'Emission per option-sector'!$B$6:$B$500,'CO2 emissions per sector'!D$33) -> 0
A44: Food and Beverage Industry | B44: =SUMIFS('Emission per option-sector'!$D$6:$D$500,'Emission per option-sector'!$C$6:$C$500,$A44,'Emission per option-sector'!$B$6:$B$500,'CO2 emissions per sector'!B$33) -> 0 | C44: =SUMIFS('Emission per option-sector'!$D$6:$D$500,'Emission per option-sector'!$C$6:$C$500,$A44,'Emission per option-sector'!$B$6:$B$500,'CO2 emissions per sector'!C$33) -> 0 | D44: =SUMIFS('Emission per option-sector'!$D$6:$D$500,'Emission per option-sector'!$C$6:$C$500,$A44,'Emission per option-sector'!$B$6:$B$500,'CO2 emissions per sector'!D$33) -> 0
A45: Gasvoorziening | B45: =SUMIFS('Emission per option-sector'!$D$6:$D$500,'Emission per option-sector'!$C$6:$C$500,$A45,'Emission per option-sector'!$B$6:$B$500,'CO2 emissions per sector'!B$33) -> 0 | C45: =SUMIFS('Emission per option-sector'!$D$6:$D$500,'Emission per option-sector'!$C$6:$C$500,$A45,'Emission per option-sector'!$B$6:$B$500,'CO2 emissions per sector'!C$33) -> 0 | D45: =SUMIFS('Emission per option-sector'!$D$6:$D$500,'Emission per option-sector'!$C$6:$C$500,$A45,'Emission per option-sector'!$B$6:$B$500,'CO2 emissions per sector'!D$33) -> 0
A46: H2 voorziening | B46: =SUMIFS('Emission per option-sector'!$D$6:$D$500,'Emission per option-sector'!$C$6:$C$500,$A46,'Emission per option-sector'!$B$6:$B$500,'CO2 emissions per sector'!B$33) -> 0 | C46: =SUMIFS('Emission per option-sector'!$D$6:$D$500,'Emission per option-sector'!$C$6:$C$500,$A46,'Emission per option-sector'!$B$6:$B$500,'CO2 emissions per sector'!C$33) -> 0 | D46: =SUMIFS('Emission per option-sector'!$D$6:$D$500,'Emission per option-sector'!$C$6:$C$500,$A46,'Emission per option-sector'!$B$6:$B$500,'CO2 emissions per sector'!D$33) -> 0
... A53: LULUCF | B53: =SUMIFS('Emission per option-sector'!$D$6:$D$500,'Emission per option-sector'!$C$6:$C$500,$A53,'Emission per option-sector'!$B$6:$B$500,'CO2 emissions per sector'!B$33) -> 0 | C53: =SUMIFS('Emission per option-sector'!$D$6:$D$500,'Emission per option-sector'!$C$6:$C$500,$A53,'Emission per option-sector'!$B$6:$B$500,'CO2 emissions per sector'!C$33) -> 0 | D53: =SUMIFS('Emission per option-sector'!$D$6:$D$500,'Emission per option-sector'!$C$6:$C$500,$A53,'Emission per option-sector'!$B$6:$B$500,'CO2 emissions per sector'!D$33) -> 0
A55: Total | B55: =SUM(B34:B53) -> 6.7038762 | C55: =SUM(C34:C53) -> 3.9184315 | D55: =SUM(D34:D53) -> 0.68684857

Sheet Capacity per option
B1: 2030
A2: Capacity per option. Note the units. Mton means the installation can if operated 100% produce x Mton per year, idem for the unit PJ.
A5: Option | B5: Capacity
A6: 913 Mono manure AD Green gas | B6: 1472.3381
A7: 985 Lignocellulosic ethanol production | B7: 3.0068617e-06
A8: 987 Ethanol uit biomassa (suiker) 2011 | B8: 1.4809979e-06
A9: 998 H2 uit biomassavergassing 2011 | B9: 2.386886e-05
A10: 1003 Micro-WKK Brandstofcel 2011 (WB nieuwbouw) | B10: 2.7656913e-06
A11: 1012 Solar-PV Residential | B11: 9.8301053
A12: 1013 Biomassavergassing met CCS 7000u 2011 | B12: 1.1742872e-07
A13: 1016 ATR with CC | B13: 12.003734
A14: 1020 Solar thermal - Services | B14: 0.014183517
A15: 1021 Micro WKK brandstofcel Utiliteitsbouw eDesign 2011 | B15: 2.4020965e-06
A16: 1022 Soil heat pump - Services | B16: 0.00049308666
A17: 1023 Ground water heat pump - Services | B17: 80.781017
... A536: 2521 Biomethanol via direct gasification with ext H2 | B536: 0.00016892264

Sheet Cost per option
A2: Cost per option per year and break down in components [M€/yr]
D4: Variable OandM cost | E4: Energy cost | F4: CAPEX | G4: Fixed OandM cost
B5: Total [M€/yr] | C5: =SUM(B11:B800) -> 86110.97 | D5: =SUM(C11:C800) -> 2310.9879 | E5: =SUM(D11:D800) -> 736.10296 | F5: =SUM(E11:E800) -> 30710.846 | G5: =SUM(F11:F800) -> 45113.562
B6: Total from sheet summary | C6: =Summary!C7 -> 86376.288
B7: Total investments [M€] | C7: =SUM(G11:G800) -> 567154.23
A10: Option | B10: Total | C10: Variable O&M cost | D10: Energy cost | E10: CAPEX | F10: Fixed O&M cost | G10: Investment cost
A11: 913 Mono manure AD Green gas | B11: -185.81887 | C11: -25.469845 | D11: 0 | E11: -160.34902 | F11: 0 | G11: 0 | H11: 0
A12: 985 Lignocellulosic ethanol production | B12: 0.00012674794 | C12: 0 | D12: 1.4164956e-05 | E12: 4.5624271e-05 | F12: 1.9683371e-05 | G12: 0.00031421966 | H12: 0.00031421966
A13: 987 Ethanol uit biomassa (suiker) 2011 | B13: 5.6754974e-05 | C13: 0 | D13: 0 | E13: 1.1717994e-06 | F13: 6.9327574e-06 | G13: 0.00011067254 | H13: 0.00011067254
A14: 998 H2 uit biomassavergassing 2011 | B14: 3.922425e-05 | C14: 0 | D14: 0 | E14: -0.00023616787 | F14: 0.00013010709 | G14: 0.0020769921 | H14: 0.0020769921
A15: 1003 Micro-WKK Brandstofcel 2011 (WB nieuwbouw) | B15: 0.00014992844 | C15: 0 | D15: 0 | E15: 4.5748901e-05 | F15: 9.0256775e-05 | G15: 0.0011383334 | H15: 0.0011383334
A16: 1012 Solar-PV Residential | B16: 142.26559 | C16: 0 | D16: 0 | E16: -384.87167 | F16: 415.56556 | G16: 7880.1132 | H16: 7880.1132
A17: 1013 Biomassavergassing met CCS 7000u 2011 | B17: 0.00026478994 | C17: 0 | D17: 0.00013251966 | E17: 5.7133242e-05 | F17: 7.5137037e-05 | G17: 0.0014247772 | H17: 0.0014247772
A18: 1016 ATR with CC | B18: -105.72042 | C18: 22.33681 | D18: 0 | E18: -171.95012 | F18: 28.648398 | G18: 457.33478 | H18: 457.33478
A19: 1020 Solar thermal - Services | B19: 0.0079899198 | C19: 0 | D19: 0 | E19: -0.014573924 | F19: 0.021578896 | G19: 0.27215661 | H19: 0.27215661
A20: 1021 Micro WKK brandstofcel Utiliteitsbouw eDesign 2011 | B20: 0.00014993682 | C20: 0 | D20: 0 | E20: 4.3611219e-05 | F20: 9.4233205e-05 | G20: 0.00083549198 | H20: 0.00083549198
A21: 1022 Soil heat pump - Services | B21: 0.0029896487 | C21: 0 | D21: 0 | E21: -0.00066110171 | F21: 0.0025800894 | G21: 0.032540514 | H21: 0.032540514
A22: 1023 Ground water heat pump - Services | B22: 303.75689 | C22: 0.33020097 | D22: 0 | E22: -152.94722 | F22: 296.91625 | G22: 3744.7568 | H22: 3744.7568
... A533: 2521 Biomethanol via direct gasification with ext H2 | B533: 0.002787418 | C533: 0 | D533: 0 | E533: 0.0016437778 | F533: 0.0005735262 | G533: 0.0091556072 | H533: 0.0091556072
B900: Total | C900: Levy cost | D900: Variable O&M cost | E900: Energy cost | F900: CAPEX | G900: Fixed O&M cost | H900: Investment cost

Sheet Cost per sector
A2: Cost per sector [M€/yr]
D4: Variable OandM cost | E4: Energy cost | F4: CAPEX | G4: Fixed OandM cost
B5: Total [M€/yr] | C5: =SUM(B11:B35) -> 86110.97 | D5: =SUM(C11:C35) -> 2310.9879 | E5: =SUM(D11:D35) -> 736.10296 | F5: =SUM(E11:E35) -> 30710.846 | G5: =SUM(F11:F35) -> 45113.562
B7: Total investments [M€] | C7: =SUM(G11:G35) -> 7239.4709
A10: Sector | B10: Total | C10: Levy cost | D10: Variable O&M cost | E10: Energy cost | F10: CAPEX | G10: Fixed O&M cost | H10: Investment cost
A11: Raffinaderijen | B11: 575.79464 | C11: 202.91043 | D11: 7.9465623 | E11: -600.46398 | F11: 537.84317 | G11: 427.55847 | H11: 10131.281
A12: Waste | B12: 105.93033 | C12: 58.305819 | D12: 1.7666203 | E12: 1.2233935 | F12: 32.291197 | G12: 12.343302 | H12: 502.02789
A13: Gasvoorziening | B13: 2157.1961 | C13: -315.00007 | D13: 0.00010213762 | E13: 9.5241546e-05 | F13: 1731.661 | G13: 740.53498 | H13: 32629.683
A14: H2 voorziening | B14: -556.86185 | C14: 133.21374 | D14: 4.8442802e-05 | E14: -858.19367 | F14: 107.46754 | G14: 60.650487 | H14: 1972.3333
A15: Warmteopwekking (centraal) | B15: 354.69045 | C15: 32.710541 | D15: 4.7902133 | E15: 119.90196 | F15: 129.06521 | G15: 68.222538 | H15: 2469.6784
A16: Elektriciteitsopwekking | B16: 2104.0821 | C16: 163.94095 | D16: 640.59955 | E16: -4012.0509 | F16: 4066.1541 | G16: 1245.4384 | H16: 80146.529
A17: Landbouw | B17: 1021.6715 | C17: 13.835189 | D17: 2.1398553e-06 | E17: 605.21249 | F17: 316.00908 | G17: 86.614705 | H17: 5616.8526
A18: Huishoudens | B18: 9287.1478 | C18: 392.61091 | D18: 0 | E18: 3447.1398 | F18: 5064.3096 | G18: 383.08748 | H18: 90869.28
A19: HDO | B19: 5286.0004 | C19: 111.59413 | D19: 0.00016943888 | E19: 2034.6604 | F19: 2853.394 | G19: 286.35172 | H19: 51734.879
A20: Verkeer | B20: 35023.406 | C20: 606.08921 | D20: 0 | E20: 4947.4383 | F20: 26016.039 | G20: 3453.84 | H20: 228229.22
A21: MWT | B21: 2361.5636 | C21: 82.989392 | D21: 0 | E21: 550.93256 | F21: 1727.6416 | G21: 0 | H21: 21789.301
A22: Bunkers | B22: 10587.452 | C22: 0 | D22: 0 | E22: 8779.8527 | F22: 1807.5998 | G22: 0 | H22: 28856.003
... A29: LULUCF | B29: 92.520036 | C29: 92.519993 | D29: 4.2904231e-05 | E29: 0 | F29: 0 | G29: 0 | H29: 0

Sheet Energy savings options
A2: Energy savings per option per energy carrier [PJ]
A4: Option | B4: Energy carrier | C4: Sector | D4: Sector
A5: 1633 Electricity savings level 1 - Basic metals ferro | B5: Elektriciteit | C5: Basismetaal ferro | D5: 0.45561539
A6: 2442 Electricity savings level 2 - Fertilizer | B6: Elektriciteit | C6: Kunstmestindustrie | D6: 0.60277528
A7: 2444 Electricity savings level 2 - Basic metals ferro | B7: Elektriciteit | C7: Basismetaal ferro | D7: 0.97097938
A8: 2445 Electricity savings level 3 - Fertilizer | B8: Elektriciteit | C8: Kunstmestindustrie | D8: 0.33542598
A9: 2449 Heat savings - Insulation package - Agriculture | B9: Warmte | C9: Landbouw | D9: 1.3026314
A10: 2450 Heat savings - 2e scherm - Agriculture | B10: Warmte | C10: Landbouw | D10: 1.4808824
A11: 2452 Heat savings - selective ventilation - Agriculture | B11: Warmte | C11: Landbouw | D11: 1.4907692
A12: 2439 Electricity savings level 2 - Chemical | B12: Elektriciteit | C12: Chemie | D12: 0.47509982
A13: 2440 Electricity savings level 3 - Chemical | B13: Elektriciteit | C13: Chemie | D13: 2.1788061
A14: 2442 Electricity savings level 2 - Fertilizer | B14: Elektriciteit | C14: Kunstmestindustrie | D14: 0.68771388
A15: 2444 Electricity savings level 2 - Basic metals ferro | B15: Elektriciteit | C15: Basismetaal ferro | D15: 1.0131959
A16: 2445 Electricity savings level 3 - Fertilizer | B16: Elektriciteit | C16: Kunstmestindustrie | D16: 0.38269166
... A29: 2459 Electricity savings - LED lightning - Agriculture | B29: Elektriciteit | C29: Landbouw | D29: 10.66

Sheet Interregional Flows
A2: Annual flow between regions for natural gas, electricity and hydrogen [PJ] | G2: Capacities between regions for natural gas, electricity and hydrogen [GW]. For electricity the capacity can be used bidirectional
A5: Energy carrier | B5: Region A | C5: Region B | D5: Flow [PJ] | G5: Energy carrier | H5: Region A | I5: Region B | J5: Network type | K5: Capacity [GW]
A6: Aardgas | B6: Import | C6: Regio1 | D6: 665.52022

Sheet Regional Service Demand
A2: Service demands (activities) | B2: Activity specific units (ie Mton staal), but in case PJ, it might mean simply one unit of activity, for example 1.0 ''PJ" for AVI means all (=1,0 in this case) municipal solid waste is combusted.
A4: Service demand | B4: Region | C4: Option | D4: v | E4: zj | F4: Activity Baseline | G4: Activitity Run | H4: Unit Activity | I4: Capacity Baseline | J4: Capacity Run | K4: Unit Capacity | L4: Unit Capacity
A5: Energy in education | B5: Regio1 | C5: 2190 Energy in education - GFE label | D5: 1 | E5: 2035 | F5: 0.840559 | G5: 0.000544 | H5: km2 GFA | I5: 0.063043 | J5: 0.000534 | K5: km2 GFA | L5: Mton
A6: Energy in education | B6: Regio1 | C6: 2191 Energy in education - DC label | D6: 1 | E6: 2035 | G6: 14.229764 | H6: km2 GFA | J6: 14.229746 | K6: km2 GFA | L6: Mton
A7: Energy in education | B7: Regio1 | C7: 2192 Energy in education - B label | D7: 1 | E7: 2035 | G7: 5.700279 | H7: km2 GFA | J7: 5.700257 | K7: km2 GFA
A8: Energy in education | B8: Regio1 | C8: 2193 Energy in education - A label | D8: 1 | E8: 2035 | G8: 1.573728 | H8: km2 GFA | J8: 1.573698 | K8: km2 GFA
A9: Energy in education | B9: Regio1 | C9: 2194 Energy in education - A+ label | D9: 1 | E9: 2035 | G9: 9.994588 | H9: km2 GFA | J9: 9.994551 | K9: km2 GFA
A10: Energy in hospitals | B10: Regio1 | C10: 2201 Energy in hospitals - DC label | D10: 1 | E10: 2035 | G10: 11.027204 | H10: km2 GFA | J10: 11.027196 | K10: km2 GFA
A11: Energy in hospitals | B11: Regio1 | C11: 2202 Energy in hospitals - B label | D11: 1 | E11: 2035 | G11: 3.895234 | H11: km2 GFA | J11: 3.895224 | K11: km2 GFA
A12: Energy in hospitals | B12: Regio1 | C12: 2203 Energy in hospitals - A label | D12: 1 | E12: 2035 | G12: 1.33248 | H12: km2 GFA | J12: 1.332468 | K12: km2 GFA
A13: Energy in hospitals | B13: Regio1 | C13: 2204 Energy in hospitals - A+ label | D13: 1 | E13: 2035 | G13: 7.125997 | H13: km2 GFA | J13: 7.125982 | K13: km2 GFA
A14: Energy in industrial halls | B14: Regio1 | C14: 2196 Energy in industrial halls - DC label | D14: 1 | E14: 2035 | G14: 128.17735 | H14: km2 GFA | J14: 128.17733 | K14: km2 GFA
A15: Energy in industrial halls | B15: Regio1 | C15: 2197 Energy in industrial halls - B label | D15: 1 | E15: 2035 | G15: 27.202296 | H15: km2 GFA | J15: 27.202268 | K15: km2 GFA
A16: Energy in industrial halls | B16: Regio1 | C16: 2198 Energy in industrial halls - A label | D16: 1 | E16: 2035 | G16: 0.000851 | H16: km2 GFA | J16: 0.000813 | K16: km2 GFA
A17: Energy in industrial halls | B17: Regio1 | C17: 2199 Energy in industrial halls - A+ label | D17: 1 | E17: 2035 | G17: 28.806605 | H17: km2 GFA | J17: 28.806559 | K17: km2 GFA
A18: Energy in offices | B18: Regio1 | C18: 2185 Offices - B label | D18: 1 | E18: 2035 | G18: 12.456222 | H18: km2 GFA | J18: 12.45621 | K18: km2 GFA
... A28: Energy in apartments with startlabel DC and B | B28: Regio1 | C28: 2178 Apartments - startlabel DC | D28: 1 | E28: 2035 | G28: 0.324917 | H28: M apartments | J28: 0.325242 | K28: M apartments
A29: Energy in apartments with startlabel DC and B | B29: Regio1 | C29: 2179 Apartments - startlabel DC/B retrofitted to A | D29: 1 | E29: 2035 | H29: M apartments | J29: 1e-06 | K29: M apartments
A30: Energy in apartments with startlabel GFE | B30: Regio1 | C30: 2400 Apartments - startlabel GFE retrofitted to DC | D30: 1 | E30: 2035 | G30: 0.67923 | H30: M apartments | J30: 0.67923 | K30: M apartments
A31: Energy in apartments with startlabel GFE | B31: Regio1 | C31: 2401 Apartments - startlabel GFE retrofitted to B | D31: 1 | E31: 2035 | G31: 2e-06 | H31: M apartments | J31: 3e-06 | K31: M apartments
A32: Energy in other dwellings with startlabel A | B32: Regio1 | C32: 2183 Other dwelllings - startlabel A | D32: 1 | E32: 2035 | G32: 0.45339 | H32: M other dwellings | J32: 0.45339 | K32: M other dwellings
A33: Energy in other dwellings with startlabel A | B33: Regio1 | C33: 2396 Other dwelllings - startlabel A retrofitted to A+ | D33: 1 | E33: 2035 | G33: 1e-06 | H33: M other dwellings | J33: 3e-06 | K33: M other dwellings
A34: Energy in other dwellings with startlabel A+ | B34: Regio1 | C34: 2184 Other dwelllings - startlabel A+ | D34: 1 | E34: 2035 | G34: 0.526108 | H34: M other dwellings | J34: 0.526107 | K34: M other dwellings
A35: Energy in other dwellings with startlabel DC and B | B35: Regio1 | C35: 2173 Other dwelllings - startlabel B or DC retrofitted to B | D35: 1 | E35: 2035 | G35: 1.084324 | H35: M other dwellings | J35: 1.084039 | K35: M other dwellings
A36: Energy in other dwellings with startlabel DC and B | B36: Regio1 | C36: 2182 Other dwelllings - startlabel DC | D36: 1 | E36: 2035 | G36: 0.284586 | H36: M other dwellings | J36: 0.28487 | K36: M other dwellings
A37: Energy in other dwellings with startlabel DC and B | B37: Regio1 | C37: 2398 Other dwelllings - startlabel DC/B retrofitted to A | D37: 1 | E37: 2035 | G37: 0 | H37: M other dwellings | J37: 1e-06 | K37: M other dwellings
A38: Energy in other dwellings with startlabel GFE | B38: Regio1 | C38: 2402 Other dwelllings - startlabel GFE retrofitted to DC | D38: 1 | E38: 2035 | G38: 0.605567 | H38: M other dwellings | J38: 0.605567 | K38: M other dwellings
A39: Energy in other dwellings with startlabel GFE | B39: Regio1 | C39: 2403 Other dwelllings - startlabel GFE retrofitted to B | D39: 1 | E39: 2035 | H39: M other dwellings | J39: 0 | K39: M other dwellings
A40: Energy in terraced houses with startlabel A | B40: Regio1 | C40: 2176 Terraced houses - startlabel A | D40: 1 | E40: 2035 | G40: 0.362519 | H40: M terraced houses | J40: 0.362519 | K40: M terraced houses
A41: Energy in terraced houses with startlabel A | B41: Regio1 | C41: 2397 Terraced houses - startlabel A retrofitted to A+ | D41: 1 | E41: 2035 | G41: 0 | H41: M terraced houses | J41: 1e-06 | K41: M terraced houses
A42: Energy in terraced houses with startlabel A+ | B42: Regio1 | C42: 2171 Terraced houses - startlabel A+ | D42: 1 | E42: 2035 | F42: 0.45201 | G42: 0.452012 | H42: M terraced houses | I42: 0.033902 | J42: 0.45201 | K42: M terraced houses
A43: Energy in terraced houses with startlabel DC and B | B43: Regio1 | C43: 2170 Terraced houses - startlabel B or DC retrofitted to B | D43: 1 | E43: 2035 | F43: 1.134688 | G43: 1.134686 | H43: M terraced houses | I43: 0.085104 | J43: 1.134367 | K43: M terraced houses
A44: Energy in terraced houses with startlabel DC and B | B44: Regio1 | C44: 2175 Terraced houses - startlabel DC | D44: 1 | E44: 2035 | G44: 0.319301 | H44: M terraced houses | J44: 0.31962 | K44: M terraced houses
A45: Energy in terraced houses with startlabel DC and B | B45: Regio1 | C45: 2399 Terraced houses - startlabel DC/B retrofitted to A | D45: 1 | E45: 2035 | G45: 0 | H45: M terraced houses | J45: 1e-06 | K45: M terraced houses
A46: Energy in terraced houses with startlabel GFE | B46: Regio1 | C46: 2404 Terraced houses - startlabel GFE retrofitted to DC | D46: 1 | E46: 2035 | G46: 0.256447 | H46: M terraced houses | J46: 0.256447 | K46: M terraced houses
A47: Energy in terraced houses with startlabel GFE | B47: Regio1 | C47: 2405 Terraced houses - startlabel GFE retrofitted to B | D47: 1 | E47: 2035 | G47: 1e-06 | H47: M terraced houses | J47: 2e-06 | K47: M terraced houses
A48: LULUCF | B48: Regio1 | C48: 2157 REF LULUCF CO2 | D48: 1 | E48: 2035 | F48: 10 | H48: Mton | I48: 10 | K48: Mton
A49: apartments | B49: Regio1 | C49: 2172 Apartments - startlabel B or DC retrofitted to B | D49: 1 | E49: 2035 | G49: 1.245432 | H49: M apartments | J49: 1.245107 | K49: M apartments
A50: apartments | B50: Regio1 | C50: 2178 Apartments - startlabel DC | D50: 1 | E50: 2035 | G50: 0.324917 | H50: M apartments | J50: 0.325242 | K50: M apartments
A51: apartments | B51: Regio1 | C51: 2179 Apartments - startlabel DC/B retrofitted to A | D51: 1 | E51: 2035 | H51: M apartments | J51: 1e-06 | K51: M apartments
A52: apartments | B52: Regio1 | C52: 2180 Apartments - startlabel A/A+ | D52: 1 | E52: 2035 | G52: 0.838356 | H52: M apartments | J52: 0.838355 | K52: M apartments
A53: apartments | B53: Regio1 | C53: 2400 Apartments - startlabel GFE retrofitted to DC | D53: 1 | E53: 2035 | G53: 0.67923 | H53: M apartments | J53: 0.67923 | K53: M apartments
A54: apartments | B54: Regio1 | C54: 2401 Apartments - startlabel GFE retrofitted to B | D54: 1 | E54: 2035 | G54: 2e-06 | H54: M apartments | J54: 3e-06 | K54: M apartments
A55: Aromatics production | B55: Regio1 | C55: 2507 REF overall aromatics demand | D55: 1 | E55: 2035 | F55: 3.806507 | G55: 3.806508 | H55: Mton aromatics | I55: 3.806507 | J55: 3.806752 | K55: Mton aromatics
A56: AVI | B56: Regio1 | C56: 1721 REF AVI | D56: 1 | E56: 2035 | F56: 0.875 | G56: 0.044522 | H56: PJ | I56: 0.027746 | J56: 0.007315 | K56: GW
A57: AVI | B57: Regio1 | C57: 1798 AVI CCS | D57: 1 | E57: 2035 | G57: 0.830478 | H57: PJ | J57: 0.030758 | K57: GW
A58: Bus transport | B58: Regio1 | C58: 1650 Hybrid bus | D58: 1 | E58: 2035 | G58: 7.1e-05 | H58: Bn vtgkm bus | J58: 1e-06 | K58: Mvtg
A59: Bus transport | B59: Regio1 | C59: 1651 REF Fuel cell bus | D59: 1 | E59: 2035 | F59: 0.007101 | H59: Bn vtgkm bus | I59: 0.000533 | K59: Mvtg
A60: Bus transport | B60: Regio1 | C60: 1652 CNG bus | D60: 1 | E60: 2035 | G60: 0.000459 | H60: Bn vtgkm bus | J60: 7e-06 | K60: Mvtg
A61: Bus transport | B61: Regio1 | C61: 1653 REF BEV bus | D61: 1 | E61: 2035 | F61: 0.273952 | G61: 0.280654 | H61: Bn vtgkm bus | I61: 0.020547 | J61: 0.004067 | K61: Mvtg
A62: Bus transport | B62: Regio1 | C62: 2430 REF ICE bus | D62: 1 | E62: 2035 | F62: 0.413733 | G62: 0.413605 | H62: Bn vtgkm bus | I62: 0.031031 | J62: 0.005994 | K62: Mvtg
A63: Data centers | B63: Regio1 | C63: 2480 REF data center | D63: 1 | E63: 2035 | F63: 2.051977 | G63: 2.051978 | H63: km2 GFA | I63: 2.051977 | J63: 2.051977 | K63: km2 GFA
A64: Generic services buildings | B64: Regio1 | C64: 2185 Offices - B label | D64: 1 | E64: 2035 | G64: 12.456222 | H64: km2 GFA | J64: 12.45621 | K64: km2 GFA
A65: Generic services buildings | B65: Regio1 | C65: 2187 Offices - DC label | D65: 1 | E65: 2035 | G65: 17.005565 | H65: km2 GFA | J65: 17.005556 | K65: km2 GFA
A66: Generic services buildings | B66: Regio1 | C66: 2188 Offices - A label | D66: 1 | E66: 2035 | G66: 9.746404 | H66: km2 GFA | J66: 9.746387 | K66: km2 GFA
A67: Generic services buildings | B67: Regio1 | C67: 2189 Offices - A+ label | D67: 1 | E67: 2035 | G67: 35.572294 | H67: km2 GFA | J67: 35.572274 | K67: km2 GFA
A68: Generic services buildings | B68: Regio1 | C68: 2191 Energy in education - DC label | D68: 1 | E68: 2035 | G68: 14.229764 | H68: km2 GFA | J68: 14.229746 | K68: km2 GFA
A69: Generic services buildings | B69: Regio1 | C69: 2192 Energy in education - B label | D69: 1 | E69: 2035 | G69: 5.700279 | H69: km2 GFA | J69: 5.700257 | K69: km2 GFA
A70: Generic services buildings | B70: Regio1 | C70: 2193 Energy in education - A label | D70: 1 | E70: 2035 | G70: 1.573728 | H70: km2 GFA | J70: 1.573698 | K70: km2 GFA
A71: Generic services buildings | B71: Regio1 | C71: 2194 Energy in education - A+ label | D71: 1 | E71: 2035 | G71: 9.994588 | H71: km2 GFA | J71: 9.994551 | K71: km2 GFA
A72: Generic services buildings | B72: Regio1 | C72: 2196 Energy in industrial halls - DC label | D72: 1 | E72: 2035 | G72: 128.17735 | H72: km2 GFA | J72: 128.17733 | K72: km2 GFA
A73: Generic services buildings | B73: Regio1 | C73: 2197 Energy in industrial halls - B label | D73: 1 | E73: 2035 | G73: 27.202296 | H73: km2 GFA | J73: 27.202268 | K73: km2 GFA
A74: Generic services buildings | B74: Regio1 | C74: 2198 Energy in industrial halls - A label | D74: 1 | E74: 2035 | G74: 0.000851 | H74: km2 GFA | J74: 0.000813 | K74: km2 GFA
A75: Generic services buildings | B75: Regio1 | C75: 2199 Energy in industrial halls - A+ label | D75: 1 | E75: 2035 | G75: 28.806605 | H75: km2 GFA | J75: 28.806559 | K75: km2 GFA
... A83: Generic services buildings | B83: Regio1 | C83: 2209 Energy in rest services - A+ label | D83: 1 | E83: 2035 | G83: 56.690106 | H83: km2 GFA | J83: 56.690083 | K83: km2 GFA
A84: Indirect CO2 in the agricultural sector | B84: Regio1 | C84: 2504 Indirect CO2 in the agricultural sector | D84: 1 | E84: 2035 | F84: 1 | H84: Mton CO2 | K84: Mton CO2
A85: Indirect CO2 in the chemical sector | B85: Regio1 | C85: 2370 Indirect CO2 emissions in the chemical industry | D85: 1 | E85: 2035 | F85: 1 | H85: Mton CO2 | K85: Mton CO2
A86: Indirect CO2 in the residential sector | B86: Regio1 | C86: 2503 Indirect CO2 in the residential sector | D86: 1 | E86: 2035 | F86: 1 | H86: Mton CO2 | K86: Mton CO2
A87: Indirecte CO2 | B87: Regio1 | C87: 1794 indirecte CO2 emissies | D87: 1 | E87: 2035 | F87: 1 | H87: Mton CO2 | K87: Mton CO2
A88: Inland navigation freight | B88: Regio1 | C88: 2431 REF ICE inland navigation freight | D88: 1 | E88: 2035 | F88: 56.377354 | G88: 56.377298 | H88: Gtkm | I88: 6.062081 | J88: 6.062075 | K88: 1000 vessels
A89: Inland navigation freight | B89: Regio1 | C89: 2432 ICE inland navigation freight - 15% fuel reduction | D89: 1 | E89: 2035 | G89: 6.2e-05 | H89: Gtkm | J89: 6e-06 | K89: 1000 vessels
A90: Light Duty Vehicle Transport | B90: Regio1 | C90: 1834 CNG van | D90: 1 | E90: 2035 | G90: 9e-06 | H90: Bn vtgkm LDV | J90: 0 | K90: Mvtg
A91: Light Duty Vehicle Transport | B91: Regio1 | C91: 1837 PI van | D91: 1 | E91: 2035 | G91: 0.000142 | H91: Bn vtgkm LDV | J91: 6e-06 | K91: Mvtg
A92: Light Duty Vehicle Transport | B92: Regio1 | C92: 1841 REF ICE van | D92: 1 | E92: 2035 | F92: 17.257167 | G92: 13.187373 | H92: Bn vtgkm LDV | I92: 1.29432 | J92: 0.528023 | K92: Mvtg
A93: Light Duty Vehicle Transport | B93: Regio1 | C93: 2428 REF BEV van | D93: 1 | E93: 2035 | F93: 4.828405 | G93: 8.898068 | H93: Bn vtgkm LDV | I93: 0.362139 | J93: 0.355394 | K93: Mvtg
A94: Lubricant use mobility | B94: Regio1 | C94: 2510 REF lubricant use mobility | D94: 1 | E94: 2035 | F94: 2.7 | G94: 2.700004 | H94: PJ | K94: PJ
A95: luchtvaart | B95: Regio1 | C95: 1995 Luchtvaart kerosine consumptie | D95: 1 | E95: 2035 | F95: 145.38001 | G95: 145.38001 | H95: PJ | I95: 145.38001 | J95: 145.38001 | K95: PJ
A96: Maritime fuel equivalent demand | B96: Regio1 | C96: 1996 Marine fuel vessel | D96: 1 | E96: 2035 | F96: 408.5 | G96: 285 | H96: PJ | I96: 408.5 | J96: 308.24001 | K96: PJ
A97: Maritime fuel equivalent demand | B97: Regio1 | C97: 2383 Methanol vessel | D97: 1 | E97: 2035 | G97: 0.199049 | H97: PJ | J97: 0.199084 | K97: PJ
A98: Maritime fuel equivalent demand | B98: Regio1 | C98: 2385 LNG vessel | D98: 1 | E98: 2035 | G98: 123.30096 | H98: PJ | J98: 123.30097 | K98: PJ
A99: Mton ceramics production | B99: Regio1 | C99: 2367 REF Ceramics production in conventional kilns | D99: 1 | E99: 2035 | F99: 2.623425 | G99: 2.623427 | H99: Mton ceramics | I99: 2.623425 | J99: 2.623426 | K99: Mton ceramics
A100: Mton Chlorine production | B100: Regio1 | C100: 2243 REF Membrane Electrolysis_chlorine | D100: 1 | E100: 2035 | F100: 0.988194 | G100: 0.988194 | H100: Mton Chlorine | I100: 0.988194 | J100: 1.722681 | K100: Mton Chlorine
A101: Mton glass production | B101: Regio1 | C101: 2364 REF Glass production conventional furnaces | D101: 1 | E101: 2035 | F101: 0.863221 | G101: 0.86322 | H101: Mton glass | I101: 0.863221 | J101: 0.863234 | K101: Mton glass
A102: Mton glass production | B102: Regio1 | C102: 2365 Glass production with electric cold-top furnaces | D102: 1 | E102: 2035 | G102: 1e-06 | H102: Mton glass | J102: 4e-06 | K102: Mton glass
A103: Mton methanol production | B103: Regio1 | C103: 2358 REF methanol conventional applications | D103: 1 | E103: 2035 | F103: 0.439997 | G103: 0.439997 | H103: Mton methanol | I103: 0.439997 | J103: 0.491258 | K103: Mton methanol
A104: Mton NH3 productie | B104: Regio1 | C104: 1375 REF ammoniak productie | D104: 1 | E104: 2035 | F104: 2.145516 | G104: 2.140168 | H104: Mton NH3 productie | I104: 2.145516 | J104: 2.390091 | K104: Mton NH3
A105: Mton NH3 productie | B105: Regio1 | C105: 2166 Electrolyse H-B NH3 | D105: 1 | E105: 2035 | H105: Mton NH3 productie | J105: 2e-06 | K105: Mton NH3
A106: Mton NH3 productie | B106: Regio1 | C106: 2461 External NH3 for fertilizer industry | D106: 1 | E106: 2035 | G106: 0.005349 | H106: Mton NH3 | J106: 2.143362 | K106: Mton NH3
A107: Mton OBKG CH4 energie | B107: Regio1 | C107: 1734 REF OBG CH4 emissies Energie | D107: 1 | E107: 2035 | F107: 5 | H107: Mton OBKG CH4 | K107: Mton OBKG CH4 ETS
A108: Mton OBKG CH4 gebouwde omgeving | B108: Regio1 | C108: 2369 REF OGHG CH4 emissions households | D108: 1 | E108: 2035 | F108: 5 | H108: Mton OBKG CH4 | K108: Mton OBKG CH4 nETS
A109: Mton OBKG CH4 industrie | B109: Regio1 | C109: 1735 REF O-GHG CH4 emissions waste | D109: 1 | E109: 2035 | F109: 5 | H109: Mton OBKG CH4 | K109: Mton OBKG CH4 ETS
A110: Mton OBKG CH4 landbouw | B110: Regio1 | C110: 1739 REF OBG CH4 emissies landbouw | D110: 1 | E110: 2035 | F110: 15 | H110: Mton OBKG CH4 | K110: Mton OBKG CH4 nETS
A111: Mton OBKG CH4 mobiliteit | B111: Regio1 | C111: 1737 REF OBG CH4 emissies verkeer | D111: 1 | E111: 2035 | F111: 5 | H111: Mton OBKG CH4 | K111: Mton OBKG CH4 ETS
A112: Mton OBKG F gss industrie | B112: Regio1 | C112: 1728 REF OBG F-gas emissies Industrie | D112: 1 | E112: 2035 | F112: 5 | H112: Mton OBKG F gassen | K112: Mton OBKG F gss ETS
A113: Mton OBKG F gss mobiliteit | B113: Regio1 | C113: 1727 REF OBG F-gas emissions mobility | D113: 1 | E113: 2035 | F113: 5 | H113: Mton OBKG F gassen | K113: Mton OBKG F gss nETS
A114: Mton OBKG N2O energie | B114: Regio1 | C114: 1729 REF OBG N2O emissies Energie | D114: 1 | E114: 2035 | F114: 5 | H114: Mton OBKG N2O | K114: Mton OBKG N2O ETS
A115: Mton OBKG N2O industrie | B115: Regio1 | C115: 1730 REF O-GHG N2O emissions chemical | D115: 1 | E115: 2035 | F115: 5 | H115: Mton OBKG N2O | K115: Mton OBKG N2O ETS
A116: Mton OBKG N2O landbouw | B116: Regio1 | C116: 1733 REF OBG N2O emissies landbouw | D116: 1 | E116: 2035 | F116: 10 | H116: Mton OBKG N2O | K116: Mton OBKG N2O nETS
A117: Mton OBKG N2O mobiliteit | B117: Regio1 | C117: 1731 REF OBG N2O emissies verkeer | D117: 1 | E117: 2035 | F117: 5 | H117: Mton OBKG N2O | K117: Mton OBKG N2O ETS
A118: Mton salt production | B118: Regio1 | C118: 2237 REF process_salt | D118: 1 | E118: 2035 | F118: 7.09544 | G118: 7.095442 | H118: Mton salt | I118: 7.09544 | J118: 7.769507 | K118: Mton salt
...

Sheet Rg Electricity Balance Options
A2: Energy balance of all options of ELECTRICITY. Unit: PJ. '+' is input, '-' is output.
A4: Production | B4: =SUMIF($S$11:$S$225,$A4,B$11:B$225) -> -568.68165 | C4: =SUMIF($S$11:$S$225,$A4,C$11:C$225) -> 0 | D4: =SUMIF($S$11:$S$225,$A4,D$11:D$225) -> 0 | E4: =SUMIF($S$11:$S$225,$A4,E$11:E$225) -> 0 | F4: =SUMIF($S$11:$S$225,$A4,F$11:F$225) -> 0 | G4: =SUMIF($S$11:$S$225,$A4,G$11:G$225) -> 0 | H4: =SUMIF($S$11:$S$225,$A4,H$11:H$225) -> 0 | I4: =SUMIF($S$11:$S$225,$A4,I$11:I$225) -> 0 | ... O4: =SUMIF($S$11:$S$225,$A4,O$11:O$225) -> 0
A5: Consumption | B5: =SUMIF($S$11:$S$225,$A5,B$11:B$225) -> 473.33961 | C5: =SUMIF($S$11:$S$225,$A5,C$11:C$225) -> 0 | D5: =SUMIF($S$11:$S$225,$A5,D$11:D$225) -> 0 | E5: =SUMIF($S$11:$S$225,$A5,E$11:E$225) -> 0 | F5: =SUMIF($S$11:$S$225,$A5,F$11:F$225) -> 0 | G5: =SUMIF($S$11:$S$225,$A5,G$11:G$225) -> 0 | H5: =SUMIF($S$11:$S$225,$A5,H$11:H$225) -> 0 | I5: =SUMIF($S$11:$S$225,$A5,I$11:I$225) -> 0 | ... O5: =SUMIF($S$11:$S$225,$A5,O$11:O$225) -> 0
A6: Balance | B6: =SUM(B4:B5) -> -95.342043 | C6: =SUM(C4:C5) -> 0 | D6: =SUM(D4:D5) -> 0 | E6: =SUM(E4:E5) -> 0 | F6: =SUM(F4:F5) -> 0 | G6: =SUM(G4:G5) -> 0 | H6: =SUM(H4:H5) -> 0 | I6: =SUM(I4:I5) -> 0 | ... O6: =SUM(O4:O5) -> 0
A9: Region | B9: Regio1
A10: Option
A11: 985 Lignocellulosic ethanol production | B11: -3.9679289e-07 | S11: =IF(B11>0,"Consumption","Production") -> Production
A12: 998 H2 uit biomassavergassing 2011 | B12: 1.1576299e-06 | S12: =IF(B12>0,"Consumption","Production") -> Consumption
A13: 1003 Micro-WKK Brandstofcel 2011 (WB nieuwbouw) | B13: -2.0253418e-07 | S13: =IF(B13>0,"Consumption","Production") -> Production
A14: 1012 Solar-PV Residential | B14: -30.326279 | S14: =IF(B14>0,"Consumption","Production") -> Production
A15: 1013 Biomassavergassing met CCS 7000u 2011 | B15: -1.2125396e-06 | S15: =IF(B15>0,"Consumption","Production") -> Production
A16: 1016 ATR with CC | B16: 0.54811571 | S16: =IF(B16>0,"Consumption","Production") -> Consumption
A17: 1021 Micro WKK brandstofcel Utiliteitsbouw eDesign 2011 | B17: -1.6054678e-07 | S17: =IF(B17>0,"Consumption","Production") -> Production
A18: 1022 Soil heat pump - Services | B18: 4.1408401e-05 | S18: =IF(B18>0,"Consumption","Production") -> Consumption
A19: 1023 Ground water heat pump - Services | B19: 3.3197678 | S19: =IF(B19>0,"Consumption","Production") -> Consumption
A20: 1042 Wind op Zee band 1 | B20: -232.98281 | S20: =IF(B20>0,"Consumption","Production") -> Production
A21: 1046 Hot water electric boiler - Industry | B21: 0.0002864567 | S21: =IF(B21>0,"Consumption","Production") -> Consumption
A22: 1047 Electric Industrial Heat Pump - Industry | B22: 3.0567026 | S22: =IF(B22>0,"Consumption","Production") -> Consumption
... A226: 2224 Deep geothermal heat - FBI | B226: 1.4027122e-05 | S226: =IF(B226>0,"Consumption","Production") -> Consumption
A227: 2227 REF Final Electricity Demand - FBI | B227: 37.700001
A228: 2229 Connector Point - FBI electricity | B228: 1.2789769e-13
A229: 2232 Electric Heat Pump - Low Temp - FBI | B229: 0.40228804
A230: 2236 Anaerobic Digestion boilers - Low Temp - FBI | B230: 0.35364223
A231: 2237 REF process_salt | B231: 1.8448145
A232: 2241 Electric Medium Temp Boilers - Salt | B232: 4.4725652
A233: 2243 REF Membrane Electrolysis_chlorine | B233: 8.1328369
A234: 2246 Electric Medium Temp Boilers - Chlorine | B234: 0.50000989
A235: 2248 Deep geothermal heat - Chlorine | B235: 1.0945935e-05
A236: 2293 Waste Heat Industrial Heat Pump - Industry | B236: 1.9236428e-05
A237: 2294 Waste Heat Industrial Heat Pump - Chemie | B237: 2.8217904e-05
A238: 2295 Waste Heat Industrial Heat Pump - Kunstmestindustrie | B238: 6.4562107e-06
... A282: 2521 Biomethanol via direct gasification with ext H2 | B282: 1.568707e-06
A301: 2518 Mechanical recycling of plastic waste with high yield | B301: 0.00018532606 | N301: 2.4994857e-05 | O301: 0.51538234
A302: 2519 Gasification of mixed plastic waste to methanol with high yield | B302: 6.8925421e-05 | C302: 0.00012585924 | D302: 7.6142282e-05 | E302: 0.00017450587 | F302: 0.87849916 | N302: 0.00041125478 | O302: 7.7267148e-05
A303: 2520 Pyrolysis of plastic waste with hydrotreating with high yield | B303: 9.1325033e-06 | C303: 3.2132706e-06 | D303: 7.147694e-06 | E303: 3.2696622e-06 | F303: 4.7417566e-06 | N303: 8.2448532e-06 | O303: 7.6824827e-06
A304: 2521 Biomethanol via direct gasification with ext H2 | B304: 4.3616857e-07 | C304: 2.0073608e-07 | D304: 3.5826507e-07 | E304: 2.005357e-07 | F304: 3.2832157e-07 | N304: 7.9809832e-07 | O304: 4.1024478e-07
A305: 2521 Biomethanol via direct gasification with ext H2 | B305: 2.4664e-06 | C305: 9.135677e-07 | D305: 1.9428333e-06 | E305: 9.1119504e-07 | F305: 1.7770386e-06 | N305: 5.271135e-06 | O305: 2.3219276e-06
A306: 2408 Biomass gasification + FT towards diesel with CC | N306: -0.048841756 | O306: -0.04863206
A307: 2409 H2 from waste gas steam reforming with CC from flue gas | B307: -0.0034711936 | N307: -0.0003014868 | O307: -0.00053190413
A308: 2412 Nuclear energy EPR (Gen III+) - Electricity production | B308: -0.9202495 | C308: -0.73381259 | D308: -0.66164018 | E308: -0.63847457 | F308: -0.55745839 | N308: -0.47512306 | O308: -0.44253358
A309: 2361 Methanol from ext. H2 and direct air capture | B309: 2.2049499 | C309: 14.319038 | D309: 5.7257707 | E309: 45.53456 | F309: 30.007787 | N309: 62.374826 | O309: 4.6753393
A310: 2364 REF Glass production conventional furnaces | B310: 0.011453516 | D310: 0.013566239 | N310: 0.012234526
A311: 2365 Glass production with electric cold-top furnaces | B311: 1.3767024 | D311: 2.5381891 | N311: 1.8270397
A312: 2366 Glass production with efficient furnaces | B312: 0.018858164 | D312: 0.023009964 | N312: 0.020267958
A313: 2367 REF Ceramics production in conventional kilns | B313: 0.0027307473 | C313: 0.0056928264 | D313: 0.0041667455 | E313: 0.0043311496 | F313: 0.0035187668 | N313: 0.0048532458 | O313: 0.0011027914
A314: 2368 Ceramics production in electric kilns | B314: 0.39655555 | C314: 1.8430003 | D314: 0.92829654 | E314: 1.0446425 | F314: 0.6219402 | N314: 1.3701521 | O314: 0.1331198
A315: 2374 Plastic waste pyrolysis oil production | B315: 0.0040717748 | C315: 0.0040747641 | D315: 0.0039921821 | E315: 0.0039995076 | F315: 0.0040585953 | N315: 0.00403826 | O315: 0.0040533206
A316: 2376 Waste Gas 200-400C Boilers CCS- Refineries | N316: 0.0031026226 | O316: 0.0030714814
A317: 2384 NG to LNG for shipping | B317: 0.16627359 | C317: 0.18357585 | D317: 0.17630295 | E317: 0.19170528 | F317: 0.176134 | N317: 0.20879786 | O317: 0.18128141
A318: 2386 Biogas to Bio-LNG for shipping | B318: 0.030761774 | C318: 0.031326955 | D318: 0.031407925 | E318: 0.030982762 | F318: 0.03017929 | N318: 0.031424413 | O318: 0.030020598
A319: 2387 Synthetic LNG production from ext. H2 and CO2 | B319: 0.0040762003 | C319: 0.0041601567 | D319: 0.004114693 | E319: 0.0040800905 | F319: 0.0041237114 | N319: 0.0041424547 | O319: 0.0040234176

Sheet Rg Heat Balance Options
A2: Energy balance of all options of HEAT. Unit: PJ. '+' is input, '-' is output.
A4: Production | B4: =SUMIF($S$11:$S$300,$A4,B$11:B$300) -> -505.21682 | C4: =SUMIF($S$11:$S$300,$A4,C$11:C$300) -> 0 | D4: =SUMIF($S$11:$S$300,$A4,D$11:D$300) -> 0 | E4: =SUMIF($S$11:$S$300,$A4,E$11:E$300) -> 0 | F4: =SUMIF($S$11:$S$300,$A4,F$11:F$300) -> 0 | G4: =SUMIF($S$11:$S$300,$A4,G$11:G$300) -> 0 | H4: =SUMIF($S$11:$S$300,$A4,H$11:H$300) -> 0 | I4: =SUMIF($S$11:$S$300,$A4,I$11:I$300) -> 0 | ... N4: =SUMIF($S$11:$S$300,$A4,N$11:N$300) -> 0
A5: Consumption | B5: =SUMIF($S$11:$S$300,$A5,B$11:B$300) -> 505.21682 | C5: =SUMIF($S$11:$S$300,$A5,C$11:C$300) -> 0 | D5: =SUMIF($S$11:$S$300,$A5,D$11:D$300) -> 0 | E5: =SUMIF($S$11:$S$300,$A5,E$11:E$300) -> 0 | F5: =SUMIF($S$11:$S$300,$A5,F$11:F$300) -> 0 | G5: =SUMIF($S$11:$S$300,$A5,G$11:G$300) -> 0 | H5: =SUMIF($S$11:$S$300,$A5,H$11:H$300) -> 0 | I5: =SUMIF($S$11:$S$300,$A5,I$11:I$300) -> 0 | ... N5: =SUMIF($S$11:$S$300,$A5,N$11:N$300) -> 0
A6: Balance | B6: =SUM(B4:B5) -> -7.5669364e-06 | C6: =SUM(C4:C5) -> 0 | D6: =SUM(D4:D5) -> 0 | E6: =SUM(E4:E5) -> 0 | F6: =SUM(F4:F5) -> 0 | G6: =SUM(G4:G5) -> 0 | H6: =SUM(H4:H5) -> 0 | I6: =SUM(I4:I5) -> 0 | ... N6: =SUM(N4:N5) -> 0
A9: Region | B9: Regio1
A10: Option
A11: 1003 Micro-WKK Brandstofcel 2011 (WB nieuwbouw) | B11: -3.024147e-07 | S11: =IF(SUM(B11:N11)>0,"Consumption","Production") -> Production
A12: 1020 Solar thermal - Services | B12: -0.0013633231 | S12: =IF(SUM(B12:N12)>0,"Consumption","Production") -> Production
A13: 1021 Micro WKK brandstofcel Utiliteitsbouw eDesign 2011 | B13: -2.3418511e-07 | S13: =IF(SUM(B13:N13)>0,"Consumption","Production") -> Production
A14: 1022 Soil heat pump - Services | B14: -0.00011253718 | S14: =IF(SUM(B14:N14)>0,"Consumption","Production") -> Production
A15: 1023 Ground water heat pump - Services | B15: -18.443155 | S15: =IF(SUM(B15:N15)>0,"Consumption","Production") -> Production
A16: 1024 Hybride WP ketel Utiliteitsbouw eDesign 2011 | B16: -1.642413e-07 | S16: =IF(SUM(B16:N16)>0,"Consumption","Production") -> Production
A17: 1027 REF HR-107 - Services | B17: -21.593238 | S17: =IF(SUM(B17:N17)>0,"Consumption","Production") -> Production
A18: 1029 Solar thermal - Newly built - Residential | B18: -0.0061403542 | S18: =IF(SUM(B18:N18)>0,"Consumption","Production") -> Production
A19: 1035 REF HR-107 - Existing - Residential | B19: -182.9331 | S19: =IF(SUM(B19:N19)>0,"Consumption","Production") -> Production
A20: 1037 REF HR-107 - Newly built - Residential | B20: -29.057134 | S20: =IF(SUM(B20:N20)>0,"Consumption","Production") -> Production
A21: 1039 Solar thermal - Existing - Residential | B21: -0.18151226 | S21: =IF(SUM(B21:N21)>0,"Consumption","Production") -> Production
A22: 1046 Hot water electric boiler - Industry | B22: -0.00028362092 | S22: =IF(SUM(B22:N22)>0,"Consumption","Production") -> Production
... A162: 2486 Heat<100C - Heat Pump - Refinery | B162: 2.4007087e-05 | S162: =IF(SUM(B162:N162)>0,"Consumption","Production") -> Consumption
S163: =IF(SUM(B163:N163)>0,"Consumption","Production") -> Production
S164: =IF(SUM(B164:N164)>0,"Consumption","Production") -> Production
S165: =IF(SUM(B165:N165)>0,"Consumption","Production") -> Production
S166: =IF(SUM(B166:N166)>0,"Consumption","Production") -> Production
S167: =IF(SUM(B167:N167)>0,"Consumption","Production") -> Production
S168: =IF(SUM(B168:N168)>0,"Consumption","Production") -> Production
S169: =IF(SUM(B169:N169)>0,"Consumption","Production") -> Production
S170: =IF(SUM(B170:N170)>0,"Consumption","Production") -> Production
S171: =IF(SUM(B171:N171)>0,"Consumption","Production") -> Production
S172: =IF(SUM(B172:N172)>0,"Consumption","Production") -> Production
S173: =IF(SUM(B173:N173)>0,"Consumption","Production") -> Production
S174: =IF(SUM(B174:N174)>0,"Consumption","Production") -> Production
... S250: =IF(SUM(B250:N250)>0,"Consumption","Production") -> Production
A301: 2203 Energy in hospitals - A label | B301: 2.6540997e-05 | C301: 2.6404155e-05 | D301: 0.030322071 | E301: 2.3329791e-05 | F301: 4.8337796e-05
A302: 2204 Energy in hospitals - A+ label | B302: 0.11623882 | C302: 0.14573917 | D302: 0.00018376882 | E302: 0.28976899 | F302: 3.3510107
A303: 2205 Energy in rest services - GFE label | B303: 6.7593304e-06 | C303: 7.4324736e-06 | D303: 1.1452316e-05 | E303: 6.4322503e-06 | F303: 6.5228763e-06
A304: 2206 Energy in rest services - DC label | B304: 0.88536357 | C304: 1.29795 | D304: 0.35305471 | E304: 0.75025011 | F304: 29.160648
A305: 2207 Energy in rest services - B label | B305: 2.2655723e-05 | C305: 2.5141148e-05 | D305: 0.31365607 | E305: 1.9557272e-05 | F305: 4.4823394e-05
A306: 2208 Energy in rest services - A label | B306: 0.5886034 | C306: 0.86291491 | D306: 0.0010280757 | E306: 0.49874562 | F306: 19.387681
A307: 2209 Energy in rest services - A+ label | B307: 0.0020039182 | C307: 0.0029265385 | D307: 0.00079409574 | E307: 0.0017248284 | F307: 0.06530042
A308: 2219 REF Natural gas boilers - Low Temp - FBI | B308: -1.1282085e-05 | C308: -1.0998361e-05 | E308: -1.4636988e-05 | F308: -1.3554433e-05
A309: 2220 REF Natural gas CHP - Low Temp - FBI | B309: -1.0367094e-05 | C309: -9.9406424e-06 | E309: -1.2481469e-05 | F309: -1.2897329e-05
A310: 2221 REF rest boilers - Low Temp - FBI | B310: -5.3287948e-06 | C310: -5.3214982e-06 | E310: -5.7266749e-06 | F310: -5.4006369e-06
A311: 2224 Deep geothermal heat - FBI | B311: -3.0456416 | C311: -1.0271566 | E311: -11.203647 | F311: -34.192788
A312: 2228 REF Final Medium Temp Heat Demand - FBI | B312: 3.0472915 | C312: 1.0297805 | E312: 14.413051 | F312: 34.194539
A313: 2231 Electric boiler - Low Temp - FBI | B313: -0.00058726363 | C313: -0.0014095357 | E313: -0.001622961 | F313: -0.00065174971
A314: 2232 Electric Heat Pump - Low Temp - FBI | B314: -0.00099337355 | C314: -0.0011622963 | E314: -3.2076989 | F314: -0.0010337995
A315: 2233 Biomass boilers - Low Temp - FBI | B315: -3.0893561e-06 | C315: -3.0896039e-06 | E315: -3.4397451e-06 | F315: -3.4205074e-06
A316: 2234 Natural Gas boilers - Low Temp - FBI | B316: -1.3193036e-05 | C316: -1.3257779e-05 | E316: -1.6151839e-05 | F316: -1.4622852e-05
A317: 2235 Hydrogen boilers - Low Temp - FBI | B317: -5.3633816e-06 | C317: -5.3236604e-06 | E317: -5.9204799e-06 | F317: -5.4956515e-06
A318: 2236 Anaerobic Digestion biolers - Low Temp - FBI | B318: -1.741001e-05 | C318: -1.8686696e-05 | E318: -1.8418435e-05 | F318: -1.8115903e-05
A319: 2237 REF process_salt | C319: 0.12968067 | E319: 0.40861043 | F319: 0.44394893
A320: 2238 MVR brine vaporization_salt | C320: 0.7983412 | E320: 2.5226567 | F320: 2.7279996
A321: 2239 REF Natural Gas Medium Temp Boilers - Salt | B321: -7.936874e-06 | C321: -1.3133855e-05 | E321: -1.3042285e-05 | F321: -1.3656824e-05
A322: 2240 Hydrogen Medium Temp Boilers - Salt | B322: -5.5732184e-05 | C322: -0.82271524 | E322: -2.8472456 | F322: -2.6523593
A323: 2241 Electric Medium Temp Boilers - Salt | B323: -5.0074376e-05 | C323: -0.00023939554 | E323: -0.00021407688 | F323: -0.00019925718

Sheet Rg Ht100to200 Balance Options
A2: Energy balance of all options of HEAT. Unit: PJ. '+' is input, '-' is output.
A4: Production | B4: =SUMIF($S$11:$S$300,$A4,B$11:B$300) -> -92.159068 | C4: =SUMIF($S$11:$S$300,$A4,C$11:C$300) -> 0 | D4: =SUMIF($S$11:$S$300,$A4,D$11:D$300) -> 0 | E4: =SUMIF($S$11:$S$300,$A4,E$11:E$300) -> 0 | F4: =SUMIF($S$11:$S$300,$A4,F$11:F$300) -> 0 | G4: =SUMIF($S$11:$S$300,$A4,G$11:G$300) -> 0 | H4: =SUMIF($S$11:$S$300,$A4,H$11:H$300) -> 0 | I4: =SUMIF($S$11:$S$300,$A4,I$11:I$300) -> 0 | ... N4: =SUMIF($S$11:$S$300,$A4,N$11:N$300) -> 0
A5: Consumption | B5: =SUMIF($S$11:$S$300,$A5,B$11:B$300) -> 92.159052 | C5: =SUMIF($S$11:$S$300,$A5,C$11:C$300) -> 0 | D5: =SUMIF($S$11:$S$300,$A5,D$11:D$300) -> 0 | E5: =SUMIF($S$11:$S$300,$A5,E$11:E$300) -> 0 | F5: =SUMIF($S$11:$S$300,$A5,F$11:F$300) -> 0 | G5: =SUMIF($S$11:$S$300,$A5,G$11:G$300) -> 0 | H5: =SUMIF($S$11:$S$300,$A5,H$11:H$300) -> 0 | I5: =SUMIF($S$11:$S$300,$A5,I$11:I$300) -> 0 | ... N5: =SUMIF($S$11:$S$300,$A5,N$11:N$300) -> 0
A6: Balance | B6: =SUM(B4:B5) -> -1.5930366e-05 | C6: =SUM(C4:C5) -> 0 | D6: =SUM(D4:D5) -> 0 | E6: =SUM(E4:E5) -> 0 | F6: =SUM(F4:F5) -> 0 | G6: =SUM(G4:G5) -> 0 | H6: =SUM(H4:H5) -> 0 | I6: =SUM(I4:I5) -> 0 | ... N6: =SUM(N4:N5) -> 0
A9: Region | B9: Regio1
A10: Option
A11: 1060 Natural Gas Low Temp Boilers - Industry | B11: -6.6090972 | S11: =IF(SUM(B11:N11)>0,"Consumption","Production") -> Production
A12: 1064 Biomass Medium Temp Boilers - Industry | B12: -1.5518003 | S12: =IF(SUM(B12:N12)>0,"Consumption","Production") -> Production
A13: 1157 REF Final Heat Demand - Industry | B13: 13.260965 | S13: =IF(SUM(B13:N13)>0,"Consumption","Production") -> Consumption
A14: 1378 REF Final Heat Demand Not Covered By Processes - Chemical | B14: 40.284988 | S14: =IF(SUM(B14:N14)>0,"Consumption","Production") -> Consumption
A15: 1436 Hydrogen Medium Temp Boilers - Chemical | B15: -6.8893176e-05 | S15: =IF(SUM(B15:N15)>0,"Consumption","Production") -> Production
A16: 1584 Biomass Low Temp Boilers with CCS - Industry | B16: -0.00022457167 | S16: =IF(SUM(B16:N16)>0,"Consumption","Production") -> Production
A17: 1586 Natural Gas Low Temp Boilers with CCS - Industry | B17: -2.3171761 | S17: =IF(SUM(B17:N17)>0,"Consumption","Production") -> Production
A18: 1698 REF Final Heat demand Waste | B18: 5.7750001 | S18: =IF(SUM(B18:N18)>0,"Consumption","Production") -> Consumption
A19: 1778 REF Heat Demand Not Covered By Processes - Fertilizers | B19: 5.34716 | S19: =IF(SUM(B19:N19)>0,"Consumption","Production") -> Consumption
A20: 1795 Electric Medium Temp Boilers | B20: -2.7026824 | S20: =IF(SUM(B20:N20)>0,"Consumption","Production") -> Production
A21: 1799 Post-Combustion CCS in Refineries | B21: 1.0978034e-05 | S21: =IF(SUM(B21:N21)>0,"Consumption","Production") -> Consumption
A22: 2007 HEFA | B22: 0.88794618 | S22: =IF(SUM(B22:N22)>0,"Consumption","Production") -> Consumption
... A74: 2519 Gasification of mixed plastic waste to methanol with high yield | B74: -3.492245e-06 | S74: =IF(SUM(B74:N74)>0,"Consumption","Production") -> Production
S75: =IF(SUM(B75:N75)>0,"Consumption","Production") -> Production
S76: =IF(SUM(B76:N76)>0,"Consumption","Production") -> Production
S77: =IF(SUM(B77:N77)>0,"Consumption","Production") -> Production
S78: =IF(SUM(B78:N78)>0,"Consumption","Production") -> Production
S79: =IF(SUM(B79:N79)>0,"Consumption","Production") -> Production
S80: =IF(SUM(B80:N80)>0,"Consumption","Production") -> Production
S81: =IF(SUM(B81:N81)>0,"Consumption","Production") -> Production
S82: =IF(SUM(B82:N82)>0,"Consumption","Production") -> Production
S83: =IF(SUM(B83:N83)>0,"Consumption","Production") -> Production
S84: =IF(SUM(B84:N84)>0,"Consumption","Production") -> Production
S85: =IF(SUM(B85:N85)>0,"Consumption","Production") -> Production
S86: =IF(SUM(B86:N86)>0,"Consumption","Production") -> Production
... S250: =IF(SUM(B250:N250)>0,"Consumption","Production") -> Production
A301: 2203 Energy in hospitals - A label | B301: 2.6540997e-05 | C301: 2.6404155e-05 | D301: 0.030322071 | E301: 2.3329791e-05 | F301: 4.8337796e-05
A302: 2204 Energy in hospitals - A+ label | B302: 0.11623882 | C302: 0.14573917 | D302: 0.00018376882 | E302: 0.28976899 | F302: 3.3510107
A303: 2205 Energy in rest services - GFE label | B303: 6.7593304e-06 | C303: 7.4324736e-06 | D303: 1.1452316e-05 | E303: 6.4322503e-06 | F303: 6.5228763e-06
A304: 2206 Energy in rest services - DC label | B304: 0.88536357 | C304: 1.29795 | D304: 0.35305471 | E304: 0.75025011 | F304: 29.160648
A305: 2207 Energy in rest services - B label | B305: 2.2655723e-05 | C305: 2.5141148e-05 | D305: 0.31365607 | E305: 1.9557272e-05 | F305: 4.4823394e-05
A306: 2208 Energy in rest services - A label | B306: 0.5886034 | C306: 0.86291491 | D306: 0.0010280757 | E306: 0.49874562 | F306: 19.387681
A307: 2209 Energy in rest services - A+ label | B307: 0.0020039182 | C307: 0.0029265385 | D307: 0.00079409574 | E307: 0.0017248284 | F307: 0.06530042
A308: 2219 REF Natural gas boilers - Low Temp - FBI | B308: -1.1282085e-05 | C308: -1.0998361e-05 | E308: -1.4636988e-05 | F308: -1.3554433e-05
A309: 2220 REF Natural gas CHP - Low Temp - FBI | B309: -1.0367094e-05 | C309: -9.9406424e-06 | E309: -1.2481469e-05 | F309: -1.2897329e-05
A310: 2221 REF rest boilers - Low Temp - FBI | B310: -5.3287948e-06 | C310: -5.3214982e-06 | E310: -5.7266749e-06 | F310: -5.4006369e-06
A311: 2224 Deep geothermal heat - FBI | B311: -3.0456416 | C311: -1.0271566 | E311: -11.203647 | F311: -34.192788
A312: 2228 REF Final Medium Temp Heat Demand - FBI | B312: 3.0472915 | C312: 1.0297805 | E312: 14.413051 | F312: 34.194539
A313: 2231 Electric boiler - Low Temp - FBI | B313: -0.00058726363 | C313: -0.0014095357 | E313: -0.001622961 | F313: -0.00065174971
A314: 2232 Electric Heat Pump - Low Temp - FBI | B314: -0.00099337355 | C314: -0.0011622963 | E314: -3.2076989 | F314: -0.0010337995
A315: 2233 Biomass boilers - Low Temp - FBI | B315: -3.0893561e-06 | C315: -3.0896039e-06 | E315: -3.4397451e-06 | F315: -3.4205074e-06
A316: 2234 Natural Gas boilers - Low Temp - FBI | B316: -1.3193036e-05 | C316: -1.3257779e-05 | E316: -1.6151839e-05 | F316: -1.4622852e-05
A317: 2235 Hydrogen boilers - Low Temp - FBI | B317: -5.3633816e-06 | C317: -5.3236604e-06 | E317: -5.9204799e-06 | F317: -5.4956515e-06
A318: 2236 Anaerobic Digestion biolers - Low Temp - FBI | B318: -1.741001e-05 | C318: -1.8686696e-05 | E318: -1.8418435e-05 | F318: -1.8115903e-05
A319: 2237 REF process_salt | C319: 0.12968067 | E319: 0.40861043 | F319: 0.44394893
A320: 2238 MVR brine vaporization_salt | C320: 0.7983412 | E320: 2.5226567 | F320: 2.7279996
A321: 2239 REF Natural Gas Medium Temp Boilers - Salt | B321: -7.936874e-06 | C321: -1.3133855e-05 | E321: -1.3042285e-05 | F321: -1.3656824e-05
A322: 2240 Hydrogen Medium Temp Boilers - Salt | B322: -5.5732184e-05 | C322: -0.82271524 | E322: -2.8472456 | F322: -2.6523593
A323: 2241 Electric Medium Temp Boilers - Salt | B323: -5.0074376e-05 | C323: -0.00023939554 | E323: -0.00021407688 | F323: -0.00019925718

Sheet Rg Ht200to400 Balance Options
A2: Energy balance of all options of HEAT. Unit: PJ. '+' is input, '-' is output.
A4: Production | B4: =SUMIF($S$11:$S$300,$A4,B$11:B$300) -> -89.059567 | C4: =SUMIF($S$11:$S$300,$A4,C$11:C$300) -> 0 | D4: =SUMIF($S$11:$S$300,$A4,D$11:D$300) -> 0 | E4: =SUMIF($S$11:$S$300,$A4,E$11:E$300) -> 0 | F4: =SUMIF($S$11:$S$300,$A4,F$11:F$300) -> 0 | G4: =SUMIF($S$11:$S$300,$A4,G$11:G$300) -> 0 | H4: =SUMIF($S$11:$S$300,$A4,H$11:H$300) -> 0 | I4: =SUMIF($S$11:$S$300,$A4,I$11:I$300) -> 0 | ... N4: =SUMIF($S$11:$S$300,$A4,N$11:N$300) -> 0
A5: Consumption | B5: =SUMIF($S$11:$S$300,$A5,B$11:B$300) -> 89.059517 | C5: =SUMIF($S$11:$S$300,$A5,C$11:C$300) -> 0 | D5: =SUMIF($S$11:$S$300,$A5,D$11:D$300) -> 0 | E5: =SUMIF($S$11:$S$300,$A5,E$11:E$300) -> 0 | F5: =SUMIF($S$11:$S$300,$A5,F$11:F$300) -> 0 | G5: =SUMIF($S$11:$S$300,$A5,G$11:G$300) -> 0 | H5: =SUMIF($S$11:$S$300,$A5,H$11:H$300) -> 0 | I5: =SUMIF($S$11:$S$300,$A5,I$11:I$300) -> 0 | ... N5: =SUMIF($S$11:$S$300,$A5,N$11:N$300) -> 0
A6: Balance | B6: =SUM(B4:B5) -> -4.9805776e-05 | C6: =SUM(C4:C5) -> 0 | D6: =SUM(D4:D5) -> 0 | E6: =SUM(E4:E5) -> 0 | F6: =SUM(F4:F5) -> 0 | G6: =SUM(G4:G5) -> 0 | H6: =SUM(H4:H5) -> 0 | I6: =SUM(I4:I5) -> 0 | ... N6: =SUM(N4:N5) -> 0
A9: Region | B9: Regio1
A10: Option
A11: 1045 Hydrogen Medium Temp Boilers - Industry | B11: -3.1980031e-05 | S11: =IF(SUM(B11:N11)>0,"Consumption","Production") -> Production
A12: 1054 WKK gas eDesign 2011 | B12: -0.72580129 | S12: =IF(SUM(B12:N12)>0,"Consumption","Production") -> Production
A13: 1065 Natural Gas Medium Temp Boilers - Industry | B13: -0.15678444 | S13: =IF(SUM(B13:N13)>0,"Consumption","Production") -> Production
A14: 1071 Biomass High Temp Boilers - Industry | B14: -0.00028811583 | S14: =IF(SUM(B14:N14)>0,"Consumption","Production") -> Production
A15: 1072 REF Ketels aardgas industrie eDesign 2011 | B15: -0.023074688 | S15: =IF(SUM(B15:N15)>0,"Consumption","Production") -> Production
A16: 1073 REF WKK gas eDesign 2011 | B16: -0.00011345647 | S16: =IF(SUM(B16:N16)>0,"Consumption","Production") -> Production
A17: 1157 REF Final Heat Demand - Industry | B17: 3.0207826 | S17: =IF(SUM(B17:N17)>0,"Consumption","Production") -> Consumption
A18: 1159 REF Ketels rest industrie ebalans | B18: -1.2125266 | S18: =IF(SUM(B18:N18)>0,"Consumption","Production") -> Production
A19: 1284 REF OvOmz raffinaderijen ebalans | B19: 79.037411 | S19: =IF(SUM(B19:N19)>0,"Consumption","Production") -> Consumption
A20: 1286 REF Ketels aardgas raffinaderijen ebalans | B20: -0.00010853856 | S20: =IF(SUM(B20:N20)>0,"Consumption","Production") -> Production
A21: 1289 REF Ketels rest raffinaderijen ebalans | B21: -2.862243e-05 | S21: =IF(SUM(B21:N21)>0,"Consumption","Production") -> Production
A22: 1290 REF WKK rest raffinaderijen ebalans | B22: -6.8857845e-05 | S22: =IF(SUM(B22:N22)>0,"Consumption","Production") -> Production
... A86: 2508 Aromatics production via biomass | B86: 5.216137e-06 | S86: =IF(SUM(B86:N86)>0,"Consumption","Production") -> Consumption
S87: =IF(SUM(B87:N87)>0,"Consumption","Production") -> Production
S88: =IF(SUM(B88:N88)>0,"Consumption","Production") -> Production
S89: =IF(SUM(B89:N89)>0,"Consumption","Production") -> Production
S90: =IF(SUM(B90:N90)>0,"Consumption","Production") -> Production
S91: =IF(SUM(B91:N91)>0,"Consumption","Production") -> Production
S92: =IF(SUM(B92:N92)>0,"Consumption","Production") -> Production
S93: =IF(SUM(B93:N93)>0,"Consumption","Production") -> Production
S94: =IF(SUM(B94:N94)>0,"Consumption","Production") -> Production
S95: =IF(SUM(B95:N95)>0,"Consumption","Production") -> Production
S96: =IF(SUM(B96:N96)>0,"Consumption","Production") -> Production
S97: =IF(SUM(B97:N97)>0,"Consumption","Production") -> Production
S98: =IF(SUM(B98:N98)>0,"Consumption","Production") -> Production
... S250: =IF(SUM(B250:N250)>0,"Consumption","Production") -> Production
A301: 2203 Energy in hospitals - A label | B301: 2.6540997e-05 | C301: 2.6404155e-05 | D301: 0.030322071 | E301: 2.3329791e-05 | F301: 4.8337796e-05
A302: 2204 Energy in hospitals - A+ label | B302: 0.11623882 | C302: 0.14573917 | D302: 0.00018376882 | E302: 0.28976899 | F302: 3.3510107
A303: 2205 Energy in rest services - GFE label | B303: 6.7593304e-06 | C303: 7.4324736e-06 | D303: 1.1452316e-05 | E303: 6.4322503e-06 | F303: 6.5228763e-06
A304: 2206 Energy in rest services - DC label | B304: 0.88536357 | C304: 1.29795 | D304: 0.35305471 | E304: 0.75025011 | F304: 29.160648
A305: 2207 Energy in rest services - B label | B305: 2.2655723e-05 | C305: 2.5141148e-05 | D305: 0.31365607 | E305: 1.9557272e-05 | F305: 4.4823394e-05
A306: 2208 Energy in rest services - A label | B306: 0.5886034 | C306: 0.86291491 | D306: 0.0010280757 | E306: 0.49874562 | F306: 19.387681
A307: 2209 Energy in rest services - A+ label | B307: 0.0020039182 | C307: 0.0029265385 | D307: 0.00079409574 | E307: 0.0017248284 | F307: 0.06530042
A308: 2219 REF Natural gas boilers - Low Temp - FBI | B308: -1.1282085e-05 | C308: -1.0998361e-05 | E308: -1.4636988e-05 | F308: -1.3554433e-05
A309: 2220 REF Natural gas CHP - Low Temp - FBI | B309: -1.0367094e-05 | C309: -9.9406424e-06 | E309: -1.2481469e-05 | F309: -1.2897329e-05
A310: 2221 REF rest boilers - Low Temp - FBI | B310: -5.3287948e-06 | C310: -5.3214982e-06 | E310: -5.7266749e-06 | F310: -5.4006369e-06
A311: 2224 Deep geothermal heat - FBI | B311: -3.0456416 | C311: -1.0271566 | E311: -11.203647 | F311: -34.192788
A312: 2228 REF Final Medium Temp Heat Demand - FBI | B312: 3.0472915 | C312: 1.0297805 | E312: 14.413051 | F312: 34.194539
A313: 2231 Electric boiler - Low Temp - FBI | B313: -0.00058726363 | C313: -0.0014095357 | E313: -0.001622961 | F313: -0.00065174971
A314: 2232 Electric Heat Pump - Low Temp - FBI | B314: -0.00099337355 | C314: -0.0011622963 | E314: -3.2076989 | F314: -0.0010337995
A315: 2233 Biomass boilers - Low Temp - FBI | B315: -3.0893561e-06 | C315: -3.0896039e-06 | E315: -3.4397451e-06 | F315: -3.4205074e-06
A316: 2234 Natural Gas boilers - Low Temp - FBI | B316: -1.3193036e-05 | C316: -1.3257779e-05 | E316: -1.6151839e-05 | F316: -1.4622852e-05
A317: 2235 Hydrogen boilers - Low Temp - FBI | B317: -5.3633816e-06 | C317: -5.3236604e-06 | E317: -5.9204799e-06 | F317: -5.4956515e-06
A318: 2236 Anaerobic Digestion biolers - Low Temp - FBI | B318: -1.741001e-05 | C318: -1.8686696e-05 | E318: -1.8418435e-05 | F318: -1.8115903e-05
A319: 2237 REF process_salt | C319: 0.12968067 | E319: 0.40861043 | F319: 0.44394893
A320: 2238 MVR brine vaporization_salt | C320: 0.7983412 | E320: 2.5226567 | F320: 2.7279996
A321: 2239 REF Natural Gas Medium Temp Boilers - Salt | B321: -7.936874e-06 | C321: -1.3133855e-05 | E321: -1.3042285e-05 | F321: -1.3656824e-05
A322: 2240 Hydrogen Medium Temp Boilers - Salt | B322: -5.5732184e-05 | C322: -0.82271524 | E322: -2.8472456 | F322: -2.6523593
A323: 2241 Electric Medium Temp Boilers - Salt | B323: -5.0074376e-05 | C323: -0.00023939554 | E323: -0.00021407688 | F323: -0.00019925718

Sheet Rg HtD200to400 Balance Options
A2: Energy balance of all options of HEAT. Unit: PJ. '+' is input, '-' is output.
A4: Production | B4: =SUMIF($S$11:$S$300,$A4,B$11:B$300) -> -16.808921 | C4: =SUMIF($S$11:$S$300,$A4,C$11:C$300) -> 0 | D4: =SUMIF($S$11:$S$300,$A4,D$11:D$300) -> 0 | E4: =SUMIF($S$11:$S$300,$A4,E$11:E$300) -> 0 | F4: =SUMIF($S$11:$S$300,$A4,F$11:F$300) -> 0 | G4: =SUMIF($S$11:$S$300,$A4,G$11:G$300) -> 0 | H4: =SUMIF($S$11:$S$300,$A4,H$11:H$300) -> 0 | I4: =SUMIF($S$11:$S$300,$A4,I$11:I$300) -> 0 | ... N4: =SUMIF($S$11:$S$300,$A4,N$11:N$300) -> 0
A5: Consumption | B5: =SUMIF($S$11:$S$300,$A5,B$11:B$300) -> 16.808921 | C5: =SUMIF($S$11:$S$300,$A5,C$11:C$300) -> 0 | D5: =SUMIF($S$11:$S$300,$A5,D$11:D$300) -> 0 | E5: =SUMIF($S$11:$S$300,$A5,E$11:E$300) -> 0 | F5: =SUMIF($S$11:$S$300,$A5,F$11:F$300) -> 0 | G5: =SUMIF($S$11:$S$300,$A5,G$11:G$300) -> 0 | H5: =SUMIF($S$11:$S$300,$A5,H$11:H$300) -> 0 | I5: =SUMIF($S$11:$S$300,$A5,I$11:I$300) -> 0 | ... N5: =SUMIF($S$11:$S$300,$A5,N$11:N$300) -> 0
A6: Balance | B6: =SUM(B4:B5) -> -5.0842513e-07 | C6: =SUM(C4:C5) -> 0 | D6: =SUM(D4:D5) -> 0 | E6: =SUM(E4:E5) -> 0 | F6: =SUM(F4:F5) -> 0 | G6: =SUM(G4:G5) -> 0 | H6: =SUM(H4:H5) -> 0 | I6: =SUM(I4:I5) -> 0 | ... N6: =SUM(N4:N5) -> 0
A9: Region | B9: Regio1
A10: Option
A11: 1157 REF Final Heat Demand - Industry | B11: 3.0207826 | S11: =IF(SUM(B11:N11)>0,"Consumption","Production") -> Consumption
A12: 1378 REF Final Heat Demand Not Covered By Processes - Chemical | B12: 12.229115 | S12: =IF(SUM(B12:N12)>0,"Consumption","Production") -> Consumption
A13: 1379 REF Final Heat Demand Not Covered By Processes - Basic Metals ferro | B13: 0.32214374 | S13: =IF(SUM(B13:N13)>0,"Consumption","Production") -> Consumption
A14: 1592 NG DF 200-400C- Industry | B14: -0.018085249 | S14: =IF(SUM(B14:N14)>0,"Consumption","Production") -> Production
A15: 1778 REF Heat Demand Not Covered By Processes - Fertilizers | B15: 1.1341807 | S15: =IF(SUM(B15:N15)>0,"Consumption","Production") -> Consumption
A16: 2013 Biomass DF 200-400C - Basic Metals Ferro | B16: -0.32201774 | S16: =IF(SUM(B16:N16)>0,"Consumption","Production") -> Production
A17: 2026 NG DF 100-200C- Chemie | B17: -0.010262563 | S17: =IF(SUM(B17:N17)>0,"Consumption","Production") -> Production
A18: 2312 REF remaining Final heat demand - Basic Metals non-ferro | B18: 0.10269887 | S18: =IF(SUM(B18:N18)>0,"Consumption","Production") -> Consumption
A19: 2329 REF NG Direct Firing - High Temp - Fertilizer | B19: -1.1341807 | S19: =IF(SUM(B19:N19)>0,"Consumption","Production") -> Production
A20: 2330 Direct Firing NG 200-400 C - Chemicals | B20: -0.010262563 | S20: =IF(SUM(B20:N20)>0,"Consumption","Production") -> Production
A21: 2331 Direct Firing Elec 200-400 C - Chemicals | B21: -3.8161715e-05 | S21: =IF(SUM(B21:N21)>0,"Consumption","Production") -> Production
A22: 2332 Direct Firing NG 200-400 C - Ferro | B22: -0.0001058451 | S22: =IF(SUM(B22:N22)>0,"Consumption","Production") -> Production
... A28: 2353 Direct Firing WG 200-400 C - Chemicals | B28: -12.208552 | S28: =IF(SUM(B28:N28)>0,"Consumption","Production") -> Production
S29: =IF(SUM(B29:N29)>0,"Consumption","Production") -> Production
S30: =IF(SUM(B30:N30)>0,"Consumption","Production") -> Production
S31: =IF(SUM(B31:N31)>0,"Consumption","Production") -> Production
S32: =IF(SUM(B32:N32)>0,"Consumption","Production") -> Production
S33: =IF(SUM(B33:N33)>0,"Consumption","Production") -> Production
S34: =IF(SUM(B34:N34)>0,"Consumption","Production") -> Production
S35: =IF(SUM(B35:N35)>0,"Consumption","Production") -> Production
S36: =IF(SUM(B36:N36)>0,"Consumption","Production") -> Production
S37: =IF(SUM(B37:N37)>0,"Consumption","Production") -> Production
S38: =IF(SUM(B38:N38)>0,"Consumption","Production") -> Production
S39: =IF(SUM(B39:N39)>0,"Consumption","Production") -> Production
S40: =IF(SUM(B40:N40)>0,"Consumption","Production") -> Production
... S250: =IF(SUM(B250:N250)>0,"Consumption","Production") -> Production
A301: 2203 Energy in hospitals - A label | B301: 2.6540997e-05 | C301: 2.6404155e-05 | D301: 0.030322071 | E301: 2.3329791e-05 | F301: 4.8337796e-05
A302: 2204 Energy in hospitals - A+ label | B302: 0.11623882 | C302: 0.14573917 | D302: 0.00018376882 | E302: 0.28976899 | F302: 3.3510107
A303: 2205 Energy in rest services - GFE label | B303: 6.7593304e-06 | C303: 7.4324736e-06 | D303: 1.1452316e-05 | E303: 6.4322503e-06 | F303: 6.5228763e-06
A304: 2206 Energy in rest services - DC label | B304: 0.88536357 | C304: 1.29795 | D304: 0.35305471 | E304: 0.75025011 | F304: 29.160648
A305: 2207 Energy in rest services - B label | B305: 2.2655723e-05 | C305: 2.5141148e-05 | D305: 0.31365607 | E305: 1.9557272e-05 | F305: 4.4823394e-05
A306: 2208 Energy in rest services - A label | B306: 0.5886034 | C306: 0.86291491 | D306: 0.0010280757 | E306: 0.49874562 | F306: 19.387681
A307: 2209 Energy in rest services - A+ label | B307: 0.0020039182 | C307: 0.0029265385 | D307: 0.00079409574 | E307: 0.0017248284 | F307: 0.06530042
A308: 2219 REF Natural gas boilers - Low Temp - FBI | B308: -1.1282085e-05 | C308: -1.0998361e-05 | E308: -1.4636988e-05 | F308: -1.3554433e-05
A309: 2220 REF Natural gas CHP - Low Temp - FBI | B309: -1.0367094e-05 | C309: -9.9406424e-06 | E309: -1.2481469e-05 | F309: -1.2897329e-05
A310: 2221 REF rest boilers - Low Temp - FBI | B310: -5.3287948e-06 | C310: -5.3214982e-06 | E310: -5.7266749e-06 | F310: -5.4006369e-06
A311: 2224 Deep geothermal heat - FBI | B311: -3.0456416 | C311: -1.0271566 | E311: -11.203647 | F311: -34.192788
A312: 2228 REF Final Medium Temp Heat Demand - FBI | B312: 3.0472915 | C312: 1.0297805 | E312: 14.413051 | F312: 34.194539
A313: 2231 Electric boiler - Low Temp - FBI | B313: -0.00058726363 | C313: -0.0014095357 | E313: -0.001622961 | F313: -0.00065174971
A314: 2232 Electric Heat Pump - Low Temp - FBI | B314: -0.00099337355 | C314: -0.0011622963 | E314: -3.2076989 | F314: -0.0010337995
A315: 2233 Biomass boilers - Low Temp - FBI | B315: -3.0893561e-06 | C315: -3.0896039e-06 | E315: -3.4397451e-06 | F315: -3.4205074e-06
A316: 2234 Natural Gas boilers - Low Temp - FBI | B316: -1.3193036e-05 | C316: -1.3257779e-05 | E316: -1.6151839e-05 | F316: -1.4622852e-05
A317: 2235 Hydrogen boilers - Low Temp - FBI | B317: -5.3633816e-06 | C317: -5.3236604e-06 | E317: -5.9204799e-06 | F317: -5.4956515e-06
A318: 2236 Anaerobic Digestion biolers - Low Temp - FBI | B318: -1.741001e-05 | C318: -1.8686696e-05 | E318: -1.8418435e-05 | F318: -1.8115903e-05
A319: 2237 REF process_salt | C319: 0.12968067 | E319: 0.40861043 | F319: 0.44394893
A320: 2238 MVR brine vaporization_salt | C320: 0.7983412 | E320: 2.5226567 | F320: 2.7279996
A321: 2239 REF Natural Gas Medium Temp Boilers - Salt | B321: -7.936874e-06 | C321: -1.3133855e-05 | E321: -1.3042285e-05 | F321: -1.3656824e-05
A322: 2240 Hydrogen Medium Temp Boilers - Salt | B322: -5.5732184e-05 | C322: -0.82271524 | E322: -2.8472456 | F322: -2.6523593
A323: 2241 Electric Medium Temp Boilers - Salt | B323: -5.0074376e-05 | C323: -0.00023939554 | E323: -0.00021407688 | F323: -0.00019925718

Sheet Rg HtHT400 Balance Options
A2: Energy balance of all options of HEAT. Unit: PJ. '+' is input, '-' is output.
A4: Production | B4: =SUMIF($S$11:$S$300,$A4,B$11:B$300) -> -7.0772188 | C4: =SUMIF($S$11:$S$300,$A4,C$11:C$300) -> 0 | D4: =SUMIF($S$11:$S$300,$A4,D$11:D$300) -> 0 | E4: =SUMIF($S$11:$S$300,$A4,E$11:E$300) -> 0 | F4: =SUMIF($S$11:$S$300,$A4,F$11:F$300) -> 0 | G4: =SUMIF($S$11:$S$300,$A4,G$11:G$300) -> 0 | H4: =SUMIF($S$11:$S$300,$A4,H$11:H$300) -> 0 | I4: =SUMIF($S$11:$S$300,$A4,I$11:I$300) -> 0 | ... N4: =SUMIF($S$11:$S$300,$A4,N$11:N$300) -> 0
A5: Consumption | B5: =SUMIF($S$11:$S$300,$A5,B$11:B$300) -> 7.0772183 | C5: =SUMIF($S$11:$S$300,$A5,C$11:C$300) -> 0 | D5: =SUMIF($S$11:$S$300,$A5,D$11:D$300) -> 0 | E5: =SUMIF($S$11:$S$300,$A5,E$11:E$300) -> 0 | F5: =SUMIF($S$11:$S$300,$A5,F$11:F$300) -> 0 | G5: =SUMIF($S$11:$S$300,$A5,G$11:G$300) -> 0 | H5: =SUMIF($S$11:$S$300,$A5,H$11:H$300) -> 0 | I5: =SUMIF($S$11:$S$300,$A5,I$11:I$300) -> 0 | ... N5: =SUMIF($S$11:$S$300,$A5,N$11:N$300) -> 0
A6: Balance | B6: =SUM(B4:B5) -> -4.6992668e-07 | C6: =SUM(C4:C5) -> 0 | D6: =SUM(D4:D5) -> 0 | E6: =SUM(E4:E5) -> 0 | F6: =SUM(F4:F5) -> 0 | G6: =SUM(G4:G5) -> 0 | H6: =SUM(H4:H5) -> 0 | I6: =SUM(I4:I5) -> 0 | ... N6: =SUM(N4:N5) -> 0
A9: Region | B9: Regio1
A10: Option
A11: 1070 Natural Gas DF > 400 C - Industry | B11: -0.0094684102 | S11: =IF(SUM(B11:N11)>0,"Consumption","Production") -> Production
A12: 1157 REF Final Heat Demand - Industry | B12: 1.3277377 | S12: =IF(SUM(B12:N12)>0,"Consumption","Production") -> Consumption
A13: 1379 REF Final Heat Demand Not Covered By Processes - Basic Metals ferro | B13: 5.2872969 | S13: =IF(SUM(B13:N13)>0,"Consumption","Production") -> Consumption
A14: 1705 Biomass DF > 400 C Boilers - Industry | B14: -0.046665294 | S14: =IF(SUM(B14:N14)>0,"Consumption","Production") -> Production
A15: 2010 Natural Gas Direct Firing HT400 - Ferro | B15: -0.00013515609 | S15: =IF(SUM(B15:N15)>0,"Consumption","Production") -> Production
A16: 2011 Electric Direct Firing HT400 - Ferro | B16: -2.6941262e-05 | S16: =IF(SUM(B16:N16)>0,"Consumption","Production") -> Production
A17: 2012 Hydrogen DF > 400 C - Basic Metals Ferro | B17: -2.3386139e-05 | S17: =IF(SUM(B17:N17)>0,"Consumption","Production") -> Production
A18: 2014 Biomass DF > 400C - Basic Metals | B18: -5.2871116 | S18: =IF(SUM(B18:N18)>0,"Consumption","Production") -> Production
A19: 2059 Hydrogen DF > 400 C - Industry | B19: -2.2445865e-05 | S19: =IF(SUM(B19:N19)>0,"Consumption","Production") -> Production
A20: 2072 Biomass DF > 400C - Industry | B20: -1.2715817 | S20: =IF(SUM(B20:N20)>0,"Consumption","Production") -> Production
A21: 2312 REF remaining Final heat demand - Basic Metals non-ferro | B21: 0.46218375 | S21: =IF(SUM(B21:N21)>0,"Consumption","Production") -> Consumption
A22: 2314 NG Direct Firing - Basic metal non-ferro | B22: -0.46212024 | S22: =IF(SUM(B22:N22)>0,"Consumption","Production") -> Production
... A24: 2316 Hydrogen DF > 400 C - Basic metal non-ferro | B24: -2.4733105e-05 | S24: =IF(SUM(B24:N24)>0,"Consumption","Production") -> Production
S25: =IF(SUM(B25:N25)>0,"Consumption","Production") -> Production
S26: =IF(SUM(B26:N26)>0,"Consumption","Production") -> Production
S27: =IF(SUM(B27:N27)>0,"Consumption","Production") -> Production
S28: =IF(SUM(B28:N28)>0,"Consumption","Production") -> Production
S29: =IF(SUM(B29:N29)>0,"Consumption","Production") -> Production
S30: =IF(SUM(B30:N30)>0,"Consumption","Production") -> Production
S31: =IF(SUM(B31:N31)>0,"Consumption","Production") -> Production
S32: =IF(SUM(B32:N32)>0,"Consumption","Production") -> Production
S33: =IF(SUM(B33:N33)>0,"Consumption","Production") -> Production
S34: =IF(SUM(B34:N34)>0,"Consumption","Production") -> Production
S35: =IF(SUM(B35:N35)>0,"Consumption","Production") -> Production
S36: =IF(SUM(B36:N36)>0,"Consumption","Production") -> Production
... S250: =IF(SUM(B250:N250)>0,"Consumption","Production") -> Production
A301: 2203 Energy in hospitals - A label | B301: 2.6540997e-05 | C301: 2.6404155e-05 | D301: 0.030322071 | E301: 2.3329791e-05 | F301: 4.8337796e-05
A302: 2204 Energy in hospitals - A+ label | B302: 0.11623882 | C302: 0.14573917 | D302: 0.00018376882 | E302: 0.28976899 | F302: 3.3510107
A303: 2205 Energy in rest services - GFE label | B303: 6.7593304e-06 | C303: 7.4324736e-06 | D303: 1.1452316e-05 | E303: 6.4322503e-06 | F303: 6.5228763e-06
A304: 2206 Energy in rest services - DC label | B304: 0.88536357 | C304: 1.29795 | D304: 0.35305471 | E304: 0.75025011 | F304: 29.160648
A305: 2207 Energy in rest services - B label | B305: 2.2655723e-05 | C305: 2.5141148e-05 | D305: 0.31365607 | E305: 1.9557272e-05 | F305: 4.4823394e-05
A306: 2208 Energy in rest services - A label | B306: 0.5886034 | C306: 0.86291491 | D306: 0.0010280757 | E306: 0.49874562 | F306: 19.387681
A307: 2209 Energy in rest services - A+ label | B307: 0.0020039182 | C307: 0.0029265385 | D307: 0.00079409574 | E307: 0.0017248284 | F307: 0.06530042
A308: 2219 REF Natural gas boilers - Low Temp - FBI | B308: -1.1282085e-05 | C308: -1.0998361e-05 | E308: -1.4636988e-05 | F308: -1.3554433e-05
A309: 2220 REF Natural gas CHP - Low Temp - FBI | B309: -1.0367094e-05 | C309: -9.9406424e-06 | E309: -1.2481469e-05 | F309: -1.2897329e-05
A310: 2221 REF rest boilers - Low Temp - FBI | B310: -5.3287948e-06 | C310: -5.3214982e-06 | E310: -5.7266749e-06 | F310: -5.4006369e-06
A311: 2224 Deep geothermal heat - FBI | B311: -3.0456416 | C311: -1.0271566 | E311: -11.203647 | F311: -34.192788
A312: 2228 REF Final Medium Temp Heat Demand - FBI | B312: 3.0472915 | C312: 1.0297805 | E312: 14.413051 | F312: 34.194539
A313: 2231 Electric boiler - Low Temp - FBI | B313: -0.00058726363 | C313: -0.0014095357 | E313: -0.001622961 | F313: -0.00065174971
A314: 2232 Electric Heat Pump - Low Temp - FBI | B314: -0.00099337355 | C314: -0.0011622963 | E314: -3.2076989 | F314: -0.0010337995
A315: 2233 Biomass boilers - Low Temp - FBI | B315: -3.0893561e-06 | C315: -3.0896039e-06 | E315: -3.4397451e-06 | F315: -3.4205074e-06
A316: 2234 Natural Gas boilers - Low Temp - FBI | B316: -1.3193036e-05 | C316: -1.3257779e-05 | E316: -1.6151839e-05 | F316: -1.4622852e-05
A317: 2235 Hydrogen boilers - Low Temp - FBI | B317: -5.3633816e-06 | C317: -5.3236604e-06 | E317: -5.9204799e-06 | F317: -5.4956515e-06
A318: 2236 Anaerobic Digestion biolers - Low Temp - FBI | B318: -1.741001e-05 | C318: -1.8686696e-05 | E318: -1.8418435e-05 | F318: -1.8115903e-05
A319: 2237 REF process_salt | C319: 0.12968067 | E319: 0.40861043 | F319: 0.44394893
A320: 2238 MVR brine vaporization_salt | C320: 0.7983412 | E320: 2.5226567 | F320: 2.7279996
A321: 2239 REF Natural Gas Medium Temp Boilers - Salt | B321: -7.936874e-06 | C321: -1.3133855e-05 | E321: -1.3042285e-05 | F321: -1.3656824e-05
A322: 2240 Hydrogen Medium Temp Boilers - Salt | B322: -5.5732184e-05 | C322: -0.82271524 | E322: -2.8472456 | F322: -2.6523593
A323: 2241 Electric Medium Temp Boilers - Salt | B323: -5.0074376e-05 | C323: -0.00023939554 | E323: -0.00021407688 | F323: -0.00019925718

Sheet Rg NG Balance Options
A2: Energy balance of all options of NATURAL GAS. Unit: PJ. '+' is input, '-' is output.
A4: Production | B4: =SUMIF($S$11:$S$225,$A4,B$11:B$225) -> 0 | C4: =SUMIF($S$11:$S$225,$A4,C$11:C$225) -> 665.52026 | D4: =SUMIF($S$11:$S$225,$A4,D$11:D$225) -> 0 | E4: =SUMIF($S$11:$S$225,$A4,E$11:E$225) -> 0 | F4: =SUMIF($S$11:$S$225,$A4,F$11:F$225) -> 0 | G4: =SUMIF($S$11:$S$225,$A4,G$11:G$225) -> 0 | H4: =SUMIF($S$11:$S$225,$A4,H$11:H$225) -> 0 | I4: =SUMIF($S$11:$S$225,$A4,I$11:I$225) -> 0 | ... N4: =SUMIF($S$11:$S$225,$A4,N$11:N$225) -> 0
A5: Consumption | B5: =SUMIF($S$11:$S$225,$A5,B$11:B$225) -> 3.5889646e-06 | C5: =SUMIF($S$11:$S$225,$A5,C$11:C$225) -> 3.5889677e-06 | D5: =SUMIF($S$11:$S$225,$A5,D$11:D$225) -> 0 | E5: =SUMIF($S$11:$S$225,$A5,E$11:E$225) -> 0 | F5: =SUMIF($S$11:$S$225,$A5,F$11:F$225) -> 0 | G5: =SUMIF($S$11:$S$225,$A5,G$11:G$225) -> 0 | H5: =SUMIF($S$11:$S$225,$A5,H$11:H$225) -> 0 | I5: =SUMIF($S$11:$S$225,$A5,I$11:I$225) -> 0 | ... N5: =SUMIF($S$11:$S$225,$A5,N$11:N$225) -> 0
A6: Balance | B6: =SUM(B4:B5) -> 3.5889646e-06 | C6: =SUM(C4:C5) -> 665.52026 | D6: =SUM(D4:D5) -> 0 | E6: =SUM(E4:E5) -> 0 | F6: =SUM(F4:F5) -> 0 | G6: =SUM(G4:G5) -> 0 | H6: =SUM(H4:H5) -> 0 | I6: =SUM(I4:I5) -> 0 | ... N6: =SUM(N4:N5) -> 0
A9: Region | B9: Import | C9: Regio1
A10: Option
A11: 913 Mono manure AD Green gas | C11: -14.999909 | S11: =IF(B11>0,"Consumption","Production") -> Production
A12: 1016 ATR with CC | C12: 13.154776 | S12: =IF(B12>0,"Consumption","Production") -> Production
A13: 1023 Ground water heat pump - Services | C13: 0.19446466 | S13: =IF(B13>0,"Consumption","Production") -> Production
A14: 1027 REF HR-107 - Services | C14: 23.402685 | S14: =IF(B14>0,"Consumption","Production") -> Production
A15: 1035 REF HR-107 - Existing - Residential | C15: 195.97316 | S15: =IF(B15>0,"Consumption","Production") -> Production
A16: 1037 REF HR-107 - Newly built - Residential | C16: 28.817742 | S16: =IF(B16>0,"Consumption","Production") -> Production
A17: 1043 REF H2 uit SMR 2011 | C17: 8.226362e-05 | S17: =IF(B17>0,"Consumption","Production") -> Production
A18: 1054 WKK gas eDesign 2011 | C18: 1.2086321 | S18: =IF(B18>0,"Consumption","Production") -> Production
A19: 1060 Natural Gas Low Temp Boilers - Industry | C19: 7.342707 | S19: =IF(B19>0,"Consumption","Production") -> Production
A20: 1065 Natural Gas Medium Temp Boilers - Industry | C20: 0.17418751 | S20: =IF(B20>0,"Consumption","Production") -> Production
A21: 1070 Natural Gas DF > 400 C - Industry | C21: 0.0094684102 | S21: =IF(B21>0,"Consumption","Production") -> Production
A22: 1072 REF Ketels aardgas industrie eDesign 2011 | C22: 0.025639982 | S22: =IF(B22>0,"Consumption","Production") -> Production
... A36: 1263 REF Aardgas MD pijplijn | C36: 3.5889541e-06 | S36: =IF(B36>0,"Consumption","Production") -> Production
A37: 1264 REF Aardgas HD pijplijn | B37: 3.5889646e-06 | C37: 3.5889677e-06 | S37: =IF(B37>0,"Consumption","Production") -> Consumption
A38: 1265 REF Aardgas LD to MD connector | C38: 3.5889647e-06 | S38: =IF(B38>0,"Consumption","Production") -> Production
A39: 1266 REF Aardgas MD to LD connector | C39: 3.5889613e-06 | S39: =IF(B39>0,"Consumption","Production") -> Production
A40: 1267 REF Aardgas LD distributienet | C40: 7.2206467e-06 | S40: =IF(B40>0,"Consumption","Production") -> Production
A41: 1270 CAES ontlader | C41: 3.6751005e-05 | S41: =IF(B41>0,"Consumption","Production") -> Production
A42: 1286 REF Ketels aardgas raffinaderijen ebalans | C42: 0.00011706187 | S42: =IF(B42>0,"Consumption","Production") -> Production
A43: 1354 CNG auto | C43: 0.0002174835 | S43: =IF(B43>0,"Consumption","Production") -> Production
A44: 1364 REF HDV vracht | C44: 1.9084953 | S44: =IF(B44>0,"Consumption","Production") -> Production
A45: 1365 LNG truck | C45: 1.5571493e-05 | S45: =IF(B45>0,"Consumption","Production") -> Production
A46: 1371 Natural Gas Medium Temp Boilers - Chemical | C46: 0.00019467578 | S46: =IF(B46>0,"Consumption","Production") -> Production
A47: 1372 Natural Gas Medium Temp Boilers - Refineries | C47: 0.80337348 | S47: =IF(B47>0,"Consumption","Production") -> Production
A48: 1373 Natural Gas CHP - Chemical | C48: 0.00018470046 | S48: =IF(B48>0,"Consumption","Production") -> Production
A49: 1374 Natural Gas CHP - Refineries | C49: 10.247452 | S49: =IF(B49>0,"Consumption","Production") -> Production
... A115: 2519 Gasification of mixed plastic waste to methanol with high yield | C115: 2.0398158e-06 | S115: =IF(B115>0,"Consumption","Production") -> Production
S116: =IF(B116>0,"Consumption","Production") -> Production
S117: =IF(B117>0,"Consumption","Production") -> Production
S118: =IF(B118>0,"Consumption","Production") -> Production
S119: =IF(B119>0,"Consumption","Production") -> Production
S120: =IF(B120>0,"Consumption","Production") -> Production
S121: =IF(B121>0,"Consumption","Production") -> Production
S122: =IF(B122>0,"Consumption","Production") -> Production
S123: =IF(B123>0,"Consumption","Production") -> Production
S124: =IF(B124>0,"Consumption","Production") -> Production
S125: =IF(B125>0,"Consumption","Production") -> Production
S126: =IF(B126>0,"Consumption","Production") -> Production
S127: =IF(B127>0,"Consumption","Production") -> Production
... S226: =IF(B226>0,"Consumption","Production") -> Production

Sheet Rg H2 Balance Options
A2: Energy balance of all options of HYDROGEN. Unit: PJ. '+' is input, '-' is output.
A4: Production | B4: =SUMIF($S$11:$S$225,$A4,B$11:B$225) -> -72.229946 | C4: =SUMIF($S$11:$S$225,$A4,C$11:C$225) -> 0 | D4: =SUMIF($S$11:$S$225,$A4,D$11:D$225) -> 0 | E4: =SUMIF($S$11:$S$225,$A4,E$11:E$225) -> 0 | F4: =SUMIF($S$11:$S$225,$A4,F$11:F$225) -> 0 | G4: =SUMIF($S$11:$S$225,$A4,G$11:G$225) -> 0 | H4: =SUMIF($S$11:$S$225,$A4,H$11:H$225) -> 0 | I4: =SUMIF($S$11:$S$225,$A4,I$11:I$225) -> 0 | ... N4: =SUMIF($S$11:$S$225,$A4,N$11:N$225) -> 0
A5: Consumption | B5: =SUMIF($S$11:$S$225,$A5,B$11:B$225) -> 72.229941 | C5: =SUMIF($S$11:$S$225,$A5,C$11:C$225) -> 0 | D5: =SUMIF($S$11:$S$225,$A5,D$11:D$225) -> 0 | E5: =SUMIF($S$11:$S$225,$A5,E$11:E$225) -> 0 | F5: =SUMIF($S$11:$S$225,$A5,F$11:F$225) -> 0 | G5: =SUMIF($S$11:$S$225,$A5,G$11:G$225) -> 0 | H5: =SUMIF($S$11:$S$225,$A5,H$11:H$225) -> 0 | I5: =SUMIF($S$11:$S$225,$A5,I$11:I$225) -> 0 | ... N5: =SUMIF($S$11:$S$225,$A5,N$11:N$225) -> 0
A6: Balance | B6: =SUM(B4:B5) -> -5.6237812e-06 | C6: =SUM(C4:C5) -> 0 | D6: =SUM(D4:D5) -> 0 | E6: =SUM(E4:E5) -> 0 | F6: =SUM(F4:F5) -> 0 | G6: =SUM(G4:G5) -> 0 | H6: =SUM(H4:H5) -> 0 | I6: =SUM(I4:I5) -> 0 | ... N6: =SUM(N4:N5) -> 0
A9: Region | B9: Regio1
A10: Option
A11: 998 H2 uit biomassavergassing 2011 | B11: -1.3819046e-05 | S11: =IF(V11>0,"Consumption","Production") -> Production | V11: =SUM(B11:Q11) -> -1.3819046e-05
A12: 1003 Micro-WKK Brandstofcel 2011 (WB nieuwbouw) | B12: 4.8668062e-07 | S12: =IF(V12>0,"Consumption","Production") -> Consumption | V12: =SUM(B12:Q12) -> 4.8668062e-07
A13: 1016 ATR with CC | B13: -10.962314 | S13: =IF(V13>0,"Consumption","Production") -> Production | V13: =SUM(B13:Q13) -> -10.962314
A14: 1021 Micro WKK brandstofcel Utiliteitsbouw eDesign 2011 | B14: 3.7003776e-07 | S14: =IF(V14>0,"Consumption","Production") -> Consumption | V14: =SUM(B14:Q14) -> 3.7003776e-07
A15: 1043 REF H2 uit SMR 2011 | B15: -6.1632287e-05 | S15: =IF(V15>0,"Consumption","Production") -> Production | V15: =SUM(B15:Q15) -> -6.1632287e-05
A16: 1045 Hydrogen Medium Temp Boilers - Industry | B16: 3.5493134e-05 | S16: =IF(V16>0,"Consumption","Production") -> Consumption | V16: =SUM(B16:Q16) -> 3.5493134e-05
A17: 1083 REF Steam Cracking (conventional) | B17: -9.5283926 | S17: =IF(V17>0,"Consumption","Production") -> Production | V17: =SUM(B17:Q17) -> -9.5283926
A18: 1284 REF OvOmz raffinaderijen ebalans | B18: 57.722363 | S18: =IF(V18>0,"Consumption","Production") -> Consumption | V18: =SUM(B18:Q18) -> 57.722363
A19: 1294 H2 vessels on pipeline charge | B19: 1.4365679e-18 | S19: =IF(V19>0,"Consumption","Production") -> Consumption | V19: =SUM(B19:Q19) -> 1.4365679e-18
A20: 1295 H2 vessels on pipeline discharge | B20: 1.1113072e-18 | S20: =IF(V20>0,"Consumption","Production") -> Consumption | V20: =SUM(B20:Q20) -> 1.1113072e-18
A21: 1296 H2 vessels on pipeline | B21: -1.6805134e-18 | S21: =IF(V21>0,"Consumption","Production") -> Production | V21: =SUM(B21:Q21) -> -1.6805134e-18
A22: 1297 H2 vessels on distribution net charge | B22: 1.3552527e-19 | S22: =IF(V22>0,"Consumption","Production") -> Consumption | V22: =SUM(B22:Q22) -> 1.3552527e-19
... A89: 2521 Biomethanol via direct gasification with ext H2 | B89: 9.9274232e-05 | S89: =IF(V89>0,"Consumption","Production") -> Consumption | V89: =SUM(B89:Q89) -> 9.9274232e-05
S90: =IF(V90>0,"Consumption","Production") -> Production | V90: =SUM(B90:Q90) -> 0
S91: =IF(V91>0,"Consumption","Production") -> Production | V91: =SUM(B91:Q91) -> 0
S92: =IF(V92>0,"Consumption","Production") -> Production | V92: =SUM(B92:Q92) -> 0
S93: =IF(V93>0,"Consumption","Production") -> Production | V93: =SUM(B93:Q93) -> 0
S94: =IF(V94>0,"Consumption","Production") -> Production | V94: =SUM(B94:Q94) -> 0
S95: =IF(V95>0,"Consumption","Production") -> Production | V95: =SUM(B95:Q95) -> 0
S96: =IF(V96>0,"Consumption","Production") -> Production | V96: =SUM(B96:Q96) -> 0
S97: =IF(V97>0,"Consumption","Production") -> Production | V97: =SUM(B97:Q97) -> 0
S98: =IF(V98>0,"Consumption","Production") -> Production | V98: =SUM(B98:Q98) -> 0
S99: =IF(V99>0,"Consumption","Production") -> Production | V99: =SUM(B99:Q99) -> 0
S100: =IF(V100>0,"Consumption","Production") -> Production | V100: =SUM(B100:Q100) -> 0
S101: =IF(V101>0,"Consumption","Production") -> Production | V101: =SUM(B101:Q101) -> 0
... S300: =IF(V300>0,"Consumption","Production") -> Production | V300: =SUM(B300:Q300) -> 0

Sheet Rg Capacity per option
A2: Capacity per option. For the units, see sheet 'Capacity per option'. Mton means the installation can if operated 100% produce x Mton per year, idem for the unit PJ.
A4: rg | B4: Import | C4: Regio1
A5: Option
A6: 913 Mono manure AD Green gas | C6: 1472.3381
A7: 985 Lignocellulosic ethanol production | C7: 3.0068617e-06
A8: 987 Ethanol uit biomassa (suiker) 2011 | C8: 1.4809979e-06
A9: 998 H2 uit biomassavergassing 2011 | C9: 2.386886e-05
A10: 1003 Micro-WKK Brandstofcel 2011 (WB nieuwbouw) | C10: 2.7656913e-06
A11: 1012 Solar-PV Residential | C11: 9.8301053
A12: 1013 Biomassavergassing met CCS 7000u 2011 | C12: 1.1742872e-07
A13: 1016 ATR with CC | C13: 12.003734
A14: 1020 Solar thermal - Services | C14: 0.014183517
A15: 1021 Micro WKK brandstofcel Utiliteitsbouw eDesign 2011 | C15: 2.4020965e-06
A16: 1022 Soil heat pump - Services | C16: 0.00049308666
A17: 1023 Ground water heat pump - Services | C17: 80.781017
... A66: 1263 REF Aardgas MD pijplijn | C66: 46.516037
A67: 1264 REF Aardgas HD pijplijn | B67: 4.9507378 | C67: 45.049263
A68: 1265 REF Aardgas LD to MD connector | C68: 331.4265
A69: 1266 REF Aardgas MD to LD connector | C69: 1416.0827
A70: 1267 REF Aardgas LD distributienet | C70: 44.903815
A71: 1268 CAES Opslag | C71: 1.6219273e-06
A72: 1269 CAES lader | C72: 0.0017760104
A73: 1270 CAES ontlader | C73: 0.001184007
A74: 1273 REF diesel | C74: 420.16547
A75: 1274 REF benzine | C75: 517.95883
A76: 1284 REF OvOmz raffinaderijen ebalans | C76: 1654.015
A77: 1286 REF Ketels aardgas raffinaderijen ebalans | C77: 0.00039220507
A78: 1289 REF Ketels rest raffinaderijen ebalans | C78: 0.00028875915
A79: 1290 REF WKK rest raffinaderijen ebalans | C79: 0.00011704606
... A536: 2521 Biomethanol via direct gasification with ext H2 | C536: 0.00016892264

Sheet Rg Energy balance options
A2: Energy balance of all options and all energy carriers. Unit: PJ, but Mton CO2 for CO2flow. '+' is input, '-' is output.
B4: Identifier | C4: Sector | D4: Activity | E4: Energy input(+) / output(-) | F4: Energy input(+) / output(-) | G4: Energy input(+) / output(-) | H4: Energy input(+) / output(-) | I4: Energy input(+) / output(-) | J4: Energy input(+) / output(-) | K4: Energy input(+) / output(-) | L4: Energy input(+) / output(-) | M4: Energy input(+) / output(-) | N4: Energy input(+) / output(-) | O4: Energy input(+) / output(-) | P4: Energy input(+) / output(-) | Q4: Energy input(+) / output(-) | R4: Energy input(+) / output(-) | S4: Energy input(+) / output(-) | BK4: LNG for shipping | BL4: LPG | BM4: Methanol | BN4: Methanol for shipping | BO4: Naphta | BP4: Olie | BQ4: Olie excl gassen | BR4: Oliegrondstoffen | BS4: Omgevingswarmte | BT4: Overige bio-olieproducten | BU4: Overige olieproducten | BV4: Plastic pyrolysis oil | BW4: Plastic waste | BX4: Restgassen | BY4: SNG | BZ4: Synthetic benzine | CA4: Synthetic diesel | CB4: Synthetic kerosine | CC4: Synthetic LNG for shipping | CD4: Synthetic LPG | CE4: Synthetic methanol for shipping | CF4: Synthetic methanol for shipping import | CG4: Synthetische brandstoffen uit FT | CH4: Synthetische brandstoffen uit methanol synthese | CI4: Uranium | CJ4: Warmte | CK4: Waterkracht | CL4: Waterstof | CM4: Wind | CN4: Zon | CO4: Zon thermisch | CP4: Ethylene | CQ4: Synthetic methanol | CR4: Synthetic methanol
E5: Import | F5: Regio1 | G5: Mid NL | H5: North Brabant | I5: North Holland | J5: North NL | K5: Offshore A | L5: Offshore B | M5: Offshore C | N5: Offshore D | O5: Offshore E | P5: Offshore F | Q5: Offshore G | R5: South Holland | S5: Zeeland
A6: Option | B6: Energy Carrier
A7: 913 Mono manure AD Green gas | B7: Aardgas | C7: Landbouw | F7: -14.999909 | G7: -3.4947629 | H7: -1.9040055 | I7: -0.72235119 | J7: -0.3661856 | R7: -0.96349139 | S7: -0.090810991
A8: 913 Mono manure AD Green gas | B8: Biogas | C8: Landbouw
A9: 913 Mono manure AD Green gas | B9: E-inhoud mest | C9: Landbouw | F9: 14.999909 | G9: 3.4947629 | H9: 1.9040055 | I9: 0.72235119 | J9: 0.3661856 | R9: 0.96349139 | S9: 0.090810991
A10: 985 Lignocellulosic ethanol production | B10: Bio-ethanol | C10: Raffinaderijen | F10: -3.3420919e-06 | R10: -3.6055564e-07 | S10: -3.5864254e-07
A11: 985 Lignocellulosic ethanol production | B11: Biomassa (hout) | C11: Raffinaderijen | F11: 9.099403e-06 | R11: 1.0301588e-06 | S11: 1.0246928e-06
A12: 985 Lignocellulosic ethanol production | B12: Elektriciteit | C12: Raffinaderijen | F12: -3.9679289e-07
A13: 986 Ethanol uit biomassa (starch) 2011 | B13: Bio-ethanol | C13: Raffinaderijen
A14: 986 Ethanol uit biomassa (starch) 2011 | B14: Biomassa (zetmeel) | C14: Raffinaderijen
A15: 987 Ethanol uit biomassa (suiker) 2011 | B15: Bio-ethanol | C15: Raffinaderijen | F15: -3.9487323e-06 | R15: -2.316417 | S15: -1.706584
A16: 987 Ethanol uit biomassa (suiker) 2011 | B16: Biomassa (suikers) | C16: Raffinaderijen | F16: 8.833853e-06 | R16: 5.1821409 | S16: 3.8178612
A17: 993 H2 uit olievergassing met CCS 2011 | B17: CO2Flow | C17: H2 voorziening | CJ17: Raffinaderijen
A18: 993 H2 uit olievergassing met CCS 2011 | B18: Elektriciteit | C18: H2 voorziening | CJ18: Gasvoorziening
A19: 993 H2 uit olievergassing met CCS 2011 | B19: Olie | C19: H2 voorziening | BP19: H2 voorziening | CL19: H2 voorziening
A20: 993 H2 uit olievergassing met CCS 2011 | B20: Waterstof | C20: H2 voorziening | CL20: H2 voorziening
A21: 996 H2 uit biomassavergassing CCS 2011 | B21: Biomassa (hout) | C21: H2 voorziening | CL21: H2 voorziening
A22: 996 H2 uit biomassavergassing CCS 2011 | B22: CO2Flow | C22: H2 voorziening | CL22: H2 voorziening
A23: 996 H2 uit biomassavergassing CCS 2011 | B23: Elektriciteit | C23: H2 voorziening | CL23: H2 voorziening
A24: 996 H2 uit biomassavergassing CCS 2011 | B24: Waterstof | C24: H2 voorziening | CJ24: Huishoudens | CL24: Huishoudens
A25: 998 H2 uit biomassavergassing 2011 | B25: Biomassa (hout) | C25: H2 voorziening | F25: 1.8932093e-05 | G25: 2.9927724e-07 | H25: 3.0198242e-07 | I25: 2.9897056e-07 | J25: 5.8763835e-07 | R25: 3.0146276e-07 | S25: 5.9562029e-07 | CJ25: Huishoudens | CL25: Huishoudens
A26: 998 H2 uit biomassavergassing 2011 | B26: Elektriciteit | C26: H2 voorziening | F26: 1.1576299e-06 | CN26: Huishoudens
A27: 998 H2 uit biomassavergassing 2011 | B27: Waterstof | C27: H2 voorziening | F27: -1.3819046e-05 | G27: -2.1845054e-07 | H27: -2.2042512e-07 | I27: -2.1822669e-07 | J27: -4.289331e-07 | R27: -2.2004581e-07 | S27: -4.3475934e-07
A28: 999 H2 uit SMR met CCS 2011 | B28: Aardgas | C28: H2 voorziening | CL28: H2 voorziening
A29: 999 H2 uit SMR met CCS 2011 | B29: CO2Flow | C29: H2 voorziening
A30: 999 H2 uit SMR met CCS 2011 | B30: Waterstof | C30: H2 voorziening | CJ30: HDO | CO30: HDO
A31: 1003 Micro-WKK Brandstofcel 2011 (WB nieuwbouw) | B31: Elektriciteit | C31: Huishoudens | F31: -2.0253418e-07 | CJ31: HDO | CL31: HDO
A32: 1003 Micro-WKK Brandstofcel 2011 (WB nieuwbouw) | B32: Warmte | C32: Huishoudens | F32: -3.024147e-07 | BS32: HDO | CJ32: HDO
A33: 1003 Micro-WKK Brandstofcel 2011 (WB nieuwbouw) | B33: Waterstof | C33: Huishoudens | F33: 4.8668062e-07 | BS33: HDO | CJ33: HDO
A34: 1010 Micro-WKK Brandstofcel 2011 (WB bestaande bouw) | B34: Elektriciteit | C34: Huishoudens | BS34: HDO | CJ34: HDO
A35: 1010 Micro-WKK Brandstofcel 2011 (WB bestaande bouw) | B35: Warmte | C35: Huishoudens | CJ35: HDO
A36: 1010 Micro-WKK Brandstofcel 2011 (WB bestaande bouw) | B36: Waterstof | C36: Huishoudens | CJ36: Huishoudens | CO36: Huishoudens
A37: 1012 Solar-PV Residential | B37: Elektriciteit | C37: Huishoudens | F37: -30.326279 | G37: -12.568054 | H37: -6.7076997 | I37: -6.6957368 | J37: -2.0284346 | R37: -8.4277998 | S37: -2.5019104e-05 | CJ37: Huishoudens
A38: 1012 Solar-PV Residential | B38: Zon | C38: Huishoudens | F38: 30.326279 | G38: 12.568054 | H38: 6.7076997 | I38: 6.6957368 | J38: 2.0284346 | R38: 8.4277998 | S38: 2.5019104e-05 | CJ38: Huishoudens
A39: 1013 Biomassavergassing met CCS 7000u 2011 | B39: Biomassa (hout) | C39: Elektriciteitsopwekking | F39: 2.0531186e-05 | G39: 6.8449163e-07 | H39: 6.840414e-07 | I39: 6.8501716e-07 | J39: 6.794194e-07 | R39: 6.8404115e-07 | S39: 6.8275902e-07 | CJ39: Huishoudens | CO39: Huishoudens
A40: 1013 Biomassavergassing met CCS 7000u 2011 | B40: CO2Flow | C40: Elektriciteitsopwekking | F40: -2.025198e-06 | CM40: Elektriciteitsopwekking
A41: 1013 Biomassavergassing met CCS 7000u 2011 | B41: Elektriciteit | C41: Elektriciteitsopwekking | F41: -1.2125396e-06 | CL41: H2 voorziening
A42: 1016 ATR with CC | B42: Aardgas | C42: H2 voorziening | F42: 13.154776 | G42: 4.8687335e-05 | H42: 7.3625682e-06 | I42: 0.11988141 | J42: 2.2755681e-05 | R42: 2.2519967e-05 | S42: 1.0650701e-05
A43: 1016 ATR with CC | B43: CO2Flow | C43: H2 voorziening | F43: -0.68499555 | G43: -2.5402925e-06 | H43: -3.884292e-07 | I43: -0.00624247 | J43: -1.1899794e-06 | R43: -1.1777053e-06 | S43: -5.5964886e-07 | CL43: Industrie
A44: 1016 ATR with CC | B44: Elektriciteit | C44: H2 voorziening | F44: 0.54811571 | G44: 2.0572108e-06 | H44: 3.3534546e-07 | I44: 0.0049950874 | J44: 9.7672517e-07 | R44: 9.6690375e-07 | S44: 4.7235101e-07 | CJ44: Industrie
A45: 1016 ATR with CC | B45: Waterstof | C45: H2 voorziening | F45: -10.962314 | G45: -4.0653526e-05 | H45: -6.2162198e-06 | I45: -0.099901258 | J45: -1.9043814e-05 | R45: -1.8847386e-05 | S45: -8.9563307e-06 | BS45: Industrie | CJ45: Industrie
A46: 1017 Kolenvergassing CCS 7000u eDesign 2011 | B46: CO2Flow | C46: Elektriciteitsopwekking | BS46: Industrie | CJ46: Industrie
A47: 1017 Kolenvergassing CCS 7000u eDesign 2011 | B47: Elektriciteit | C47: Elektriciteitsopwekking | CJ47: Industrie
A48: 1017 Kolenvergassing CCS 7000u eDesign 2011 | B48: Kolen | C48: Elektriciteitsopwekking | CJ48: Industrie
A49: 1020 Solar thermal - Services | B49: Warmte | C49: HDO | F49: -0.0013633231 | G49: -5.776519e-05 | H49: -1.0008837 | I49: -5.88526e-05 | J49: -2.6040123e-05 | R49: -8.9182197e-05 | S49: -0.096614143
A50: 1020 Solar thermal - Services | B50: Zon thermisch | C50: HDO | F50: 0.0013633231 | G50: 5.776519e-05 | H50: 1.0008837 | I50: 5.88526e-05 | J50: 2.6040123e-05 | R50: 8.9182197e-05 | S50: 0.096614143
A51: 1021 Micro WKK brandstofcel Utiliteitsbouw eDesign 2011 | B51: Elektriciteit | C51: HDO | F51: -1.6054678e-07
A52: 1021 Micro WKK brandstofcel Utiliteitsbouw eDesign 2011 | B52: Warmte | C52: HDO | F52: -2.3418511e-07
A53: 1021 Micro WKK brandstofcel Utiliteitsbouw eDesign 2011 | B53: Waterstof | C53: HDO | F53: 3.7003776e-07
A54: 1022 Soil heat pump - Services | B54: Elektriciteit | C54: HDO | F54: 4.1408401e-05 | G54: 5.4627203e-07 | H54: 5.1653772e-07 | I54: 5.2046983e-07 | J54: 5.0315237e-07 | R54: 5.4591354e-07 | S54: 4.4455551e-07
A55: 1022 Soil heat pump - Services | B55: Omgevingswarmte | C55: HDO | F55: 7.3425054e-05 | G55: 1.2172795e-06 | H55: 1.1647353e-06 | I55: 1.1716838e-06 | J55: 1.1410817e-06 | R55: 1.216646e-06 | S55: 1.0375339e-06
A56: 1022 Soil heat pump - Services | B56: Warmte | C56: HDO | F56: -0.00011253718 | G56: -1.458917e-06 | H56: -1.3766385e-06 | I56: -1.3875191e-06 | J56: -1.3395996e-06 | R56: -1.457925e-06 | S56: -1.1774548e-06
A57: 1023 Ground water heat pump - Services | B57: Aardgas | C57: HDO | F57: 0.19446466 | G57: 0.086648505 | H57: 0.059252443 | I57: 0.058459569 | J57: 0.026289545 | R57: 0.07456093 | S57: 0.0084532215
A58: 1023 Ground water heat pump - Services | B58: Elektriciteit | C58: HDO | F58: 3.3197678 | G58: 1.4792039 | H58: 1.0115169 | I58: 0.99798154 | J58: 0.44879675 | R58: 1.272853 | S58: 0.14430717
A59: 1023 Ground water heat pump - Services | B59: Omgevingswarmte | C59: HDO | F59: 14.929367 | G59: 6.6521444 | H59: 4.5489042 | I59: 4.488034 | J59: 2.018289 | R59: 5.7241616 | S59: 0.64896552
A60: 1023 Ground water heat pump - Services | B60: Warmte | C60: HDO | F60: -18.443155 | G60: -8.2177993 | H60: -5.6195385 | I60: -5.5443417 | J60: -2.4933152 | R60: -7.0714056 | S60: -0.80170638
A61: 1024 Hybride WP ketel Utiliteitsbouw eDesign 2011 | B61: Aardgas | C61: HDO
A62: 1024 Hybride WP ketel Utiliteitsbouw eDesign 2011 | B62: Elektriciteit | C62: HDO
A63: 1024 Hybride WP ketel Utiliteitsbouw eDesign 2011 | B63: Omgevingswarmte | C63: HDO | F63: 1.8203577e-06 | G63: 2.3553927e-07 | H63: 2.3615018e-07 | I63: 2.3615623e-07 | J63: 2.3655225e-07 | R63: 2.3635342e-07 | S63: 2.3672999e-07
A64: 1024 Hybride WP ketel Utiliteitsbouw eDesign 2011 | B64: Warmte | C64: HDO | F64: -1.642413e-07
A65: 1027 REF HR-107 - Services | B65: Aardgas | C65: HDO | F65: 23.402685 | G65: 0.0025242958 | H65: 0.0013089204 | I65: 0.0021738635 | J65: 1.5944744 | R65: 0.0012516427 | S65: 0.0010187732
A66: 1027 REF HR-107 - Services | B66: Warmte | C66: HDO | F66: -21.593238 | G66: -0.0023273874 | H66: -0.0012068189 | I66: -0.002004291 | J66: -1.4700955 | R66: -0.0011540091 | S66: -0.0009393049
A67: 1029 Solar thermal - Newly built - Residential | B67: Warmte | C67: Huishoudens | F67: -0.0061403542 | G67: -0.0042364276 | H67: -0.0023484737 | I67: -0.0016031261 | J67: -0.00040905747 | R67: -0.0019368482 | S67: -0.00038487331
A68: 1029 Solar thermal - Newly built - Residential | B68: Zon thermisch | C68: Huishoudens | F68: 0.0061403542 | G68: 0.0042364276 | H68: 0.0023484737 | I68: 0.0016031261 | J68: 0.00040905747 | R68: 0.0019368482 | S68: 0.00038487331
A69: 1035 REF HR-107 - Existing - Residential | B69: Aardgas | C69: Huishoudens | F69: 195.97316 | G69: 68.581281 | H69: 33.52999 | I69: 34.282814 | J69: 27.422164 | R69: 38.789057 | S69: 1.4279244
A70: 1035 REF HR-107 - Existing - Residential | B70: Warmte | C70: Huishoudens | F70: -182.9331 | G70: -65.43797 | H70: -31.993197 | I70: -32.711516 | J70: -26.165314 | R70: -37.011223 | S70: -1.3624778
A71: 1037 REF HR-107 - Newly built - Residential | B71: Aardgas | C71: Huishoudens | F71: 28.817742 | G71: 3.2050444 | H71: 0.14362557 | I71: 2.3520795 | J71: 1.213901 | R71: 1.1115156 | S71: 0.0001576537 | BO71: Chemie | BU71: Chemie | BX71: Chemie
A72: 1037 REF HR-107 - Newly built - Residential | B72: Warmte | C72: Huishoudens | F72: -29.057134 | G72: -3.0578391 | H72: -0.13702895 | I72: -2.2440502 | J72: -1.1581474 | R72: -1.0604645 | S72: -0.00015041415
A73: 1039 Solar thermal - Existing - Residential | B73: Warmte | C73: Huishoudens | F73: -0.18151226 | G73: -0.00036916717 | H73: -0.042480113 | I73: -0.00082081261 | J73: -4.0991337e-05 | R73: -0.0095214114 | S73: -0.0077485428
A74: 1039 Solar thermal - Existing - Residential | B74: Zon thermisch | C74: Huishoudens | F74: 0.18151226 | G74: 0.00036916717 | H74: 0.042480113 | I74: 0.00082081261 | J74: 4.0991337e-05 | R74: 0.0095214114 | S74: 0.0077485428
A75: 1042 Wind op Zee band 1 | B75: Elektriciteit | C75: Elektriciteitsopwekking | F75: -232.98281 | K75: -26.810213 | L75: -29.755888 | M75: -208.99893 | Q75: -25.185522
A76: 1042 Wind op Zee band 1 | B76: Wind | C76: Elektriciteitsopwekking | F76: 232.98281 | K76: 26.810213 | L76: 29.755888 | M76: 208.99893 | Q76: 25.185522
A77: 1043 REF H2 uit SMR 2011 | B77: Aardgas | C77: H2 voorziening | F77: 8.226362e-05 | G77: 2.9219491e-06 | H77: 1.8410084e-06 | I77: 2.7712659e-06 | J77: 1.0856366e-05 | R77: 2.2535796e-06 | S77: 2.916604e-06 | CM77: Elektriciteitsopwekking
A78: 1043 REF H2 uit SMR 2011 | B78: Waterstof | C78: H2 voorziening | F78: -6.1632287e-05 | G78: -2.2361813e-06 | H78: -1.4354845e-06 | I78: -2.1245641e-06 | J78: -8.168738e-06 | R78: -1.7410927e-06 | S78: -2.2874331e-06
A79: 1044 Ketels SHT kolen eDesign 2011 | B79: HeatHT400 | C79: Industrie
A80: 1044 Ketels SHT kolen eDesign 2011 | B80: Kolen | C80: Industrie
A81: 1045 Hydrogen Medium Temp Boilers - Industry | B81: Heat200to400 | C81: Industrie | F81: -3.1980031e-05 | G81: -6.2221139e-07 | H81: -5.9595342e-07 | I81: -5.6523104e-07 | J81: -5.5434606e-07 | R81: -6.8283708e-07 | S81: -7.2232786e-07 | CJ81: Elektriciteitsopwekking
A82: 1045 Hydrogen Medium Temp Boilers - Industry | B82: Waterstof | C82: Industrie | F82: 3.5493134e-05 | G82: 6.873751e-07 | H82: 6.5822876e-07 | I82: 6.2412691e-07 | J82: 6.1204458e-07 | R82: 7.5466961e-07 | S82: 7.9850439e-07 | CJ82: Elektriciteitsopwekking
A83: 1046 Hot water electric boiler - Industry | B83: Elektriciteit | C83: Industrie | F83: 0.0002864567 | G83: 3.0937823e-06 | H83: 2.4708838e-06 | I83: 7.9136081e-07 | J83: 8.2138957e-06 | R83: 5.1497225e-06 | S83: 2.3610023e-05
A84: 1046 Hot water electric boiler - Industry | B84: Warmte | C84: Industrie | F84: -0.00028362092 | G84: -3.063446e-06 | H84: -2.4467148e-06 | I84: -7.8382075e-07 | J84: -8.1328652e-06 | R84: -5.0990304e-06 | S84: -2.3376555e-05
A85: 1047 Electric Industrial Heat Pump - Industry | B85: Elektriciteit | C85: Industrie | F85: 3.0567026 | G85: 1.2422914e-05 | H85: 0.78563355 | I85: 1.5321109e-07 | J85: 8.2262625e-06 | R85: 0.39051829 | S85: 0.062192412
A86: 1047 Electric Industrial Heat Pump - Industry | B86: Omgevingswarmte | C86: Industrie | F86: 7.6417591 | G86: 3.1323481e-05 | H86: 1.9640841 | I86: 6.4922451e-07 | J86: 2.0831853e-05 | R86: 0.97629598 | S86: 0.1554813
A87: 1047 Electric Industrial Heat Pump - Industry | B87: Warmte | C87: Industrie | F87: -10.698459 | G87: -4.3405663e-05 | H87: -2.7497173 | I87: -4.6170371e-07 | J87: -2.8717384e-05 | R87: -1.3668139 | S87: -0.21767337 | CJ87: Landbouw
A88: 1048 Natural Gas Industrial Heat Pump - Industry | B88: Aardgas | C88: Industrie | CJ88: Landbouw
A89: 1048 Natural Gas Industrial Heat Pump - Industry | B89: Omgevingswarmte | C89: Industrie | BS89: Landbouw | CJ89: Landbouw
A90: 1048 Natural Gas Industrial Heat Pump - Industry | B90: Warmte | C90: Industrie | CJ90: Elektriciteitsopwekking
A91: 1049 WKK biomassa (vloeibaar) eDesign 2011 | B91: Biomassa (natte stromen) | C91: Industrie
A92: 1049 WKK biomassa (vloeibaar) eDesign 2011 | B92: Elektriciteit | C92: Industrie
A93: 1049 WKK biomassa (vloeibaar) eDesign 2011 | B93: Warmte | C93: Industrie
